Workbook

Sheet Front
B2: THE METHODIST CHURCH GHANA
B3: ACCRA NORTH DIOCESE
B4: GA SUB-URBAN CIRCUIT
B5: HEBRON SOCIETY
B6: STATEMENT OF ACCOUNT FOR THE PERIOD 1ST JANUARY,2024 TO 31ST DECEMBER,2024
B11: DRAFT
B19: FINANCIAL STATEMENTS
B20: FOR THE PERIOD ENDING 31ST DECEMBER, 2024

Sheet Rec & Pmt
A1: =+Front!B2 -> THE METHODIST CHURCH GHANA
A2: =+Front!B3 -> ACCRA NORTH DIOCESE
A3: =+Front!B4 -> GA SUB-URBAN CIRCUIT
A4: =+Front!B5 -> HEBRON SOCIETY
A5: =+Front!B6 -> STATEMENT OF ACCOUNT FOR THE PERIOD 1ST JANUARY,2024 TO 31ST DECEMBER,2024
B7: 2024 | C7: 2023 | G7: 2022 | H7: 2021 | I7: TOTAL
B8: GHS | C8: GHS | G8: GHS | H8: GHS | I8: GHS
A10: BALANCE b/f
A11: GA RURAL BANK CURRENT | B11: =C75 -> 52205.88 | C11: 75100
A12: REPUBLIC BANK | B12: =C76 -> 200 | C12: 0
A13: CASH ON HAND | B13: =C77 -> 6557.7 | C13: 12166 | G13: 8030
B14: =+B12+B11+B13 -> 58963.58 | C14: 87266 | G14: 8030
A15: RECEIPTS
A16: OFFERING | B16: =+'RECEIPTS AND PAYMENT ANANLYSIS'!N8 -> 40490.5 | C16: 30724 | G16: 19146.6 | H16: 9074.3 | I16: =+B16+C16+H16+G16 -> 99435.4
A17: TITHE | B17: =+'RECEIPTS AND PAYMENT ANANLYSIS'!N9 -> 96711 | C17: 61571 | G17: 46708 | H17: 13965 | I17: =+B17+C17+H17+G17 -> 218955
A18: WEEKDAY ACTIVITY | B18: =+'RECEIPTS AND PAYMENT ANANLYSIS'!N10 -> 2772.1 | C18: 4168.7 | G18: 4350.9 | H18: 3617 | I18: =+B18+C18+H18+G18 -> 14908.7
A19: THANKS OFFERING | B19: =+'RECEIPTS AND PAYMENT ANANLYSIS'!N11 -> 4490 | C19: 6414 | G19: 1570 | H19: 140 | I19: =+B19+C19+H19+G19 -> 12614
A20: HARVEST | B20: =+'RECEIPTS AND PAYMENT ANANLYSIS'!N12 -> 238458.9 | C20: 150421 | G20: 55750.8 | H20: 24354.3 | I20: =+B20+C20+H20+G20 -> 468985
A21: WELFARE | B21: =+'RECEIPTS AND PAYMENT ANANLYSIS'!N13 -> 4704.5 | C21: 0 | G21: 0 | I21: =+B21+C21+H21+G21 -> 4704.5
A22: SPECIAL OFFERING | B22: =+'RECEIPTS AND PAYMENT ANANLYSIS'!N14 -> 893 | C22: 1296 | G22: 9245 | H22: 240 | I22: =+B22+C22+H22+G22 -> 11674
A23: POOR FUND | B23: =+'RECEIPTS AND PAYMENT ANANLYSIS'!N15 -> 2429.6 | I23: =+B23+C23+H23+G23 -> 2429.6
A24: MDF AWARENESS | B24: =+'RECEIPTS AND PAYMENT ANANLYSIS'!N16 -> 671 | C24: 0 | G24: 724 | H24: 242 | I24: =+B24+C24+H24+G24 -> 1637
A25: CIRCUIT HARVEST | B25: =+'RECEIPTS AND PAYMENT ANANLYSIS'!N17 -> 1011 | C25: 0 | G25: 0 | I25: =+B25+C25+H25+G25 -> 1011
A26: LAY MOVEMENT OFFERING | B26: =+'RECEIPTS AND PAYMENT ANANLYSIS'!N18 -> 0 | C26: 242 | G26: 40 | H26: 1450 | I26: =+B26+C26+H26+G26 -> 1732
A27: SPECIAL APPEAL | B27: =+'RECEIPTS AND PAYMENT ANANLYSIS'!N19 -> 1190 | C27: 140 | G27: 647 | I27: =+B27+C27+H27+G27 -> 1977
A28: WOMEN FELLOWSHIP | B28: =+'RECEIPTS AND PAYMENT ANANLYSIS'!N20 -> 2610 | C28: 0 | G28: 0 | H28: 13000 | I28: =+B28+C28+H28+G28 -> 15610
A29: OTHERS/NORTHERN GHANA | B29: =+'RECEIPTS AND PAYMENT ANANLYSIS'!N21 -> 0 | C29: 0 | G29: 80 | I29: =+B29+C29+H29+G29 -> 80
A30: AUTONOMY | B30: =+'RECEIPTS AND PAYMENT ANANLYSIS'!N22 -> 0 | C30: 0 | G30: 0 | H30: 140 | I30: =+B30+C30+H30+G30 -> 140
A31: WATCHNIGHT SERVICE | B31: =+'RECEIPTS AND PAYMENT ANANLYSIS'!N23 -> 0 | C31: 2011.5 | G31: 237 | I31: =+B31+C31+H31+G31 -> 2248.5
A32: CONVENANT SUNDAY | B32: =+'RECEIPTS AND PAYMENT ANANLYSIS'!N24 -> 535 | C32: 1220 | G32: 474.5 | I32: =+B32+C32+H32+G32 -> 2229.5
A33: TOTAL RECEIPTS | B33: =SUM(B16:B32) -> 396966.6 | C33: 258208.2 | G33: =SUM(G16:G32) -> 138973.8 | H33: =SUM(H16:H32) -> 66222.6 | I33: =SUM(I16:I32) -> 860371.2
A36: PAYMENT
A37: HONARARIUM TO PREACHERS | B37: =+'RECEIPTS AND PAYMENT ANANLYSIS'!N30 -> 15000 | C37: 11035 | G37: 8400 | H37: 750 | I37: =+B37+C37+H37+G37 -> 35185
A38: T&T | B38: =+'RECEIPTS AND PAYMENT ANANLYSIS'!N31 -> 2700 | C38: 1825 | G38: 285 | I38: =+B38+C38+H38+G38 -> 4810
A39: WELFARE | B39: =+'RECEIPTS AND PAYMENT ANANLYSIS'!N32 -> 4200 | C39: 4100 | G39: 250 | H39: 200 | I39: =+B39+C39+H39+G39 -> 8750
A40: FURNITURE | B40: =+'RECEIPTS AND PAYMENT ANANLYSIS'!N33 -> 28407.5 | C40: 0 | G40: 540 | H40: 500 | I40: =+B40+C40+H40+G40 -> 29447.5
A41: INSTRUMENTS | B41: =+'RECEIPTS AND PAYMENT ANANLYSIS'!N34 -> 11798 | C41: 0 | G41: 8390 | H41: 630 | I41: =+B41+C41+H41+G41 -> 20818
A42: MDF & SPECIAL OFFERING | B42: =+'RECEIPTS AND PAYMENT ANANLYSIS'!N35 -> 671 | C42: 2224 | G42: 2729 | H42: 242 | I42: =+B42+C42+H42+G42 -> 5866
A43: LAYMOVEMENT | B43: =+'RECEIPTS AND PAYMENT ANANLYSIS'!N36 -> 0 | C43: 242 | G43: 0 | I43: =+B43+C43+H43+G43 -> 242
A44: CIRCUIT HARVEST | B44: =+'RECEIPTS AND PAYMENT ANANLYSIS'!N37 -> 1199 | C44: 0 | G44: 0 | I44: =+B44+C44+H44+G44 -> 1199
A45: WESLEY TOWERS & DONATION | B45: =+'RECEIPTS AND PAYMENT ANANLYSIS'!N38 -> 3050 | C45: 5000 | G45: 800 | I45: =+B45+C45+H45+G45 -> 8850
A46: MINISTERS APPRECIATION | B46: =+'RECEIPTS AND PAYMENT ANANLYSIS'!N39 -> 0 | C46: 0 | G46: 0 | I46: =+B46+C46+H46+G46 -> 0
A47: PURCHASE OF METHODIST STATIONARY | B47: =+'RECEIPTS AND PAYMENT ANANLYSIS'!N40 -> 2110 | C47: 2420 | G47: 1403 | H47: 2230 | I47: =+B47+C47+H47+G47 -> 8163
A48: DIOCESAN APPEAL | B48: =+'RECEIPTS AND PAYMENT ANANLYSIS'!N41 -> 0 | C48: 1233 | G48: 0 | I48: =+B48+C48+H48+G48 -> 1233
A49: WATER/ECG | B49: =+'RECEIPTS AND PAYMENT ANANLYSIS'!N42 -> 600 | C49: 270 | G49: 0 | I49: =+B49+C49+H49+G49 -> 870
A50: LAND | B50: =+'RECEIPTS AND PAYMENT ANANLYSIS'!N43 -> 66200 | C50: 0 | G50: 1950 | H50: 44500 | I50: =+B50+C50+H50+G50 -> 112650
A51: HARVEST & ANNIVERSARY EXPENDITURE | B51: =+'RECEIPTS AND PAYMENT ANANLYSIS'!N44 -> 600 | C51: 565 | G51: 6904.3 | I51: =+B51+C51+H51+G51 -> 8069.3
A52: BANNER | B52: =+'RECEIPTS AND PAYMENT ANANLYSIS'!N45 -> 480 | C52: 0 | G52: 0 | I52: =+B52+C52+H52+G52 -> 480
A53: REFRESHMENT | B53: =+'RECEIPTS AND PAYMENT ANANLYSIS'!N46 -> 5300 | C53: 0 | G53: 100 | I53: =+B53+C53+H53+G53 -> 5400
A54: BUILDING PROJECT | B54: =+'RECEIPTS AND PAYMENT ANANLYSIS'!N47 -> 259100 | C54: 254940 | G54: 0 | I54: =+B54+C54+H54+G54 -> 514040
A55: FILLING | B55: =+'RECEIPTS AND PAYMENT ANANLYSIS'!N48 -> 0 | C55: 0 | G55: 26740 | H55: 9000 | I55: =+B55+C55+H55+G55 -> 35740
A56: AUTONOMY | B56: =+'RECEIPTS AND PAYMENT ANANLYSIS'!N49 -> 0 | C56: 0 | G56: 0 | H56: 140 | I56: =+B56+C56+H56+G56 -> 140
A57: BANK CHARGES | B57: =+'RECEIPTS AND PAYMENT ANANLYSIS'!N55 -> 231.2 | C57: 35.12 | G57: 0 | I57: =+B57+C57+H57+G57 -> 266.32
A58: MISCELLANEOUS | B58: =+'RECEIPTS AND PAYMENT ANANLYSIS'!N50 -> 1900 | C58: 0 | G58: 325 | I58: =+B58+C58+H58+G58 -> 2225
A59: WATCHNIGHT SERVICE | B59: =+'RECEIPTS AND PAYMENT ANANLYSIS'!N51 -> 0 | C59: 2011.5 | G59: 684 | I59: =+B59+C59+H59+G59 -> 2695.5
A60: CONVENANT SUNDAY | B60: =+'RECEIPTS AND PAYMENT ANANLYSIS'!N52 -> 275 | C60: 610 | G60: 237.5 | I60: =+B60+C60+H60+G60 -> 1122.5
A61: RENT | B61: ='RECEIPTS AND PAYMENT ANANLYSIS'!N56 -> 7200 | I61: =+B61+C61+H61+G61 -> 7200
A62: SALARY | B62: ='RECEIPTS AND PAYMENT ANANLYSIS'!N57 -> 4700 | I62: =+B62+C62+H62+G62 -> 4700
A63: ASSESSMENT | B63: =Expend!O55 -> 16495.78 | I63: =+B63+C63+H63+G63 -> 16495.78
A64: ALLOWANCE FOR MINISTER | B64: =Expend!O50 -> 3500 | I64: =+B64+C64+H64+G64 -> 3500
I65: =+B65+C65+H65+G65 -> 0
I66: =+B66+C66+H66+G66 -> 0
I67: =+B67+C67+H67+G67 -> 0
I68: =+B68+C68+H68+G68 -> 0
A69: TOTAL PAYMENTS | B69: =SUM(B37:B68) -> 435717.48 | C69: =SUM(C37:C68) -> 286510.62 | G69: =SUM(G37:G68) -> 59737.8 | H69: =SUM(H37:H68) -> 58192 | I69: =SUM(I37:I68) -> 840157.9
A71: EXCESS OF RECEIPTS OVER EXPENDITURE | B71: =B33-B69 -> -38750.88 | C71: =C33-C69 -> -28302.42 | G71: =G33-G69 -> 79236 | H71: =H33-H69 -> 8030.6 | I71: =I33-I69 -> 20213.3
K72: 200
A74: STATEMENT OF ACCOUNT FOR THE PERIOD ENDING 30TH NOVEMBER,2024 | Y74: 2850
A75: GA RURAL BANK | B75: ='CASH BOOK'!L26 -> 14173.5 | C75: 52205.88 | G75: 75100 | Y75: -2200
A76: REPUBLIC BANK | B76: =C76+Expend!O95 -> 200 | C76: 200 | Y76: =SUM(Y74:Y75) -> 650
A77: CASH ON HAND | B77: ='CASH BOOK'!M26 -> 6339.8 | C77: 6557.7 | G77: 12166 | H77: 8030.6 | J77: 1480 | Y77: =552+137+130 -> 819
A78: FUND BALANCE AS AT 31ST DECEMBER 2024 | B78: =SUM(B75:B77) -> 20713.3 | C78: =SUM(C75:C77) -> 58963.58 | D78: =SUM(D75:D77) -> 0 | E78: =SUM(E75:E77) -> 0 | F78: =SUM(F75:F77) -> 0 | G78: =SUM(G75:G77) -> 87266 | H78: =SUM(H75:H77) -> 8030.6 | J78: 8000 | Y78: =SUM(Y76:Y77) -> 1469
A81: FOOT NOTE:
A82: WELFARE: | B82: GHC | C82: GHC
A83: NAMING CEREMONY
A84: FUNERAL BENEFIT
A85: SICK BENEFIT
A86: VISITATION | C86: =SUM(B83:B86) -> 0
A88: DONATIONS | B88: GHC | C88: GHC
A89: HARVEST INVITATION
A90: INVITATIONS (ORG ANNIVERSARIES AND OTHERS)
A91: OTHER DONATIONS (GIRLS FELLOWSHIP)
C92: =SUM(B89:B92) -> 0
J94: 1000
A96: STEWARD……………………………….. | B96: MINISTER IN CHARGE ………………………………….. | J96: =J77+J78+J94 -> 10480 | K96: =B77-J96 -> -4140.2
A97: (BRO. PETER ASARE) | B97: (V REV. KOBINA S. ANAMAN)
A100: ASSETS
A101: BANK &CASH BALANCE
A102: BUILDING - W.I.P
A103: TOTAL
A105: FUNDED BY
A106: ACCUMULATED FUND
M107: Total Flow to roof = GHS 155,240.00
M109: Advance payment = GHS 120,000.00
M111: Balance = GHS 35,240.00
A119: FOOT NOTE:
A120: DONATIONS
A121: DETAILS | B121: PURPOSE | H121: AMOUNT | K121: =SUM(K118:K120) -> 0
H122: GHS
A136: TOTAL | H136: =SUM(H123:H134) -> 0
...

Sheet TB
A1: HEBRON METHODIST CHURCH
A2: EXTENDED TRIAL BALANCE
A3: Account Code | C3: Details | D3: OPENING BALANCES | F3: CURRENT ACTIVITY | H3: ADJUSTMENT | J3: CLOSING BALANCES
B4: Non-current assets | D4: DR | E4: CR | F4: DR | G4: CR | H4: DR | I4: CR | J4: DR | K4: CR
D5: GHS | E5: GHS | F5: GHS | G5: GHS | H5: GHS | I5: GHS | J5: GHS | K5: GHS
A6: 00001 | C6: Office Building | J6: =+D6+F6+H6-E6-G6-I6 -> 0 | K6: =+E6+G6+I6-D6-F6-H6 -> 0
A7: 00002 | C7: Fixtures & fittings | J7: =+D7+F7+H7-E7-G7-I7 -> 0 | K7: =+E7+G7+I7-D7-F7-H7 -> 0
A8: 00003 | C8: Office equipment | J8: =+D8+F8+H8-E8-G8-I8 -> 0 | K8: =+E8+G8+I8-D8-F8-H8 -> 0
A9: 00004 | C9: Computers & accessories | J9: =+D9+F9+H9-E9-G9-I9 -> 0 | K9: =+E9+G9+I9-D9-F9-H9 -> 0
B10: Accummulative Depreciation | J10: =+D10+F10+H10-E10-G10-I10 -> 0 | K10: =+E10+G10+I10-D10-F10-H10 -> 0
A11: 00005 | C11: Office equipment | J11: =+D11+F11+H11-E11-G11-I11 -> 0 | K11: =+E11+G11+I11-D11-F11-H11 -> 0
A12: 00006 | C12: Computers & accessories | J12: =+D12+F12+H12-E12-G12-I12 -> 0 | K12: =+E12+G12+I12-D12-F12-H12 -> 0
C13: Fixtures & fittings | J13: =+D13+F13+H13-E13-G13-I13 -> 0 | K13: =+E13+G13+I13-D13-F13-H13 -> 0
B14: Intangible | J14: =+D14+F14+H14-E14-G14-I14 -> 0 | K14: =+E14+G14+I14-D14-F14-H14 -> 0
A15: 00007 | C15: Account Receivables | J15: =+D15+F15+H15-E15-G15-I15 -> 0 | K15: =+E15+G15+I15-D15-F15-H15 -> 0
J16: =+D16+F16+H16-E16-G16-I16 -> 0 | K16: =+E16+G16+I16-D16-F16-H16 -> 0
A17: 00008 | C17: Cash & Bank Equivalent | J17: =+D17+F17+H17-E17-G17-I17 -> 0 | K17: =+E17+G17+I17-D17-F17-H17 -> 0
A18: 00009 | C18: Cash at bank | J18: =+D18+F18+H18-E18-G18-I18 -> 0 | K18: =+E18+G18+I18-D18-F18-H18 -> 0
A19: 00010 | C19: Cash in hand | J19: =+D19+F19+H19-E19-G19-I19 -> 0 | K19: =+E19+G19+I19-D19-F19-H19 -> 0
J20: =+D20+F20+H20-E20-G20-I20 -> 0 | K20: =+E20+G20+I20-D20-F20-H20 -> 0
A21: 00011 | B21: Shareholders equity and liabilities | J21: =+D21+F21+H21-E21-G21-I21 -> 0 | K21: =+E21+G21+I21-D21-F21-H21 -> 0
A22: 00012 | C22: Current liabilities | J22: =+D22+F22+H22-E22-G22-I22 -> 0 | K22: =+E22+G22+I22-D22-F22-H22 -> 0
A23: 00013 | C23: Trade and other payables | J23: =+D23+F23+H23-E23-G23-I23 -> 0 | K23: =+E23+G23+I23-D23-F23-H23 -> 0
A24: 00014 | C24: Overdraft | J24: =+D24+F24+H24-E24-G24-I24 -> 0 | K24: =+E24+G24+I24-D24-F24-H24 -> 0
A25: 00015 | C25: Audit fees | J25: =+D25+F25+H25-E25-G25-I25 -> 0 | K25: =+E25+G25+I25-D25-F25-H25 -> 0
A26: 00016 | C26: Accrual-Rent | J26: =+D26+F26+H26-E26-G26-I26 -> 0 | K26: =+E26+G26+I26-D26-F26-H26 -> 0
A27: 00017 | C27: Accrual-PAYE | J27: =+D27+F27+H27-E27-G27-I27 -> 0 | K27: =+E27+G27+I27-D27-F27-H27 -> 0
A28: 00018 | C28: Long term loan | J28: =+D28+F28+H28-E28-G28-I28 -> 0 | K28: =+E28+G28+I28-D28-F28-H28 -> 0
A29: 00019 | C29: Stated capital | J29: =+D29+F29+H29-E29-G29-I29 -> 0 | K29: =+E29+G29+I29-D29-F29-H29 -> 0
A30: 00020 | C30: Amount held toward capital | J30: =+D30+F30+H30-E30-G30-I30 -> 0 | K30: =+E30+G30+I30-D30-F30-H30 -> 0
A31: 00021 | C31: Retained earnings | J31: =+D31+F31+H31-E31-G31-I31 -> 0 | K31: =+E31+G31+I31-D31-F31-H31 -> 0
B32: Revenue | J32: =+D32+F32+H32-E32-G32-I32 -> 0 | K32: =+E32+G32+I32-D32-F32-H32 -> 0
A33: 00022 | C33: Revenue | J33: =+D33+F33+H33-E33-G33-I33 -> 0 | K33: =+E33+G33+I33-D33-F33-H33 -> 0
A34: 00023 | C34: Foods and drinks | J34: =+D34+F34+H34-E34-G34-I34 -> 0 | K34: =+E34+G34+I34-D34-F34-H34 -> 0
J35: =+D35+F35+H35-E35-G35-I35 -> 0 | K35: =+E35+G35+I35-D35-F35-H35 -> 0
B36: Cost of sale | J36: =+D36+F36+H36-E36-G36-I36 -> 0 | K36: =+E36+G36+I36-D36-F36-H36 -> 0
A37: 00024 | C37: Cost of Ticket | J37: =+D37+F37+H37-E37-G37-I37 -> 0 | K37: =+E37+G37+I37-D37-F37-H37 -> 0
A38: 00025 | C38: Communication expenses | J38: =+D38+F38+H38-E38-G38-I38 -> 0 | K38: =+E38+G38+I38-D38-F38-H38 -> 0
A39: 00026 | C39: Depreciation | J39: =+D39+F39+H39-E39-G39-I39 -> 0 | K39: =+E39+G39+I39-D39-F39-H39 -> 0
A40: 00027 | C40: Utilites | J40: =+D40+F40+H40-E40-G40-I40 -> 0 | K40: =+E40+G40+I40-D40-F40-H40 -> 0
A41: 00028 | C41: Marketing costs | J41: =+D41+F41+H41-E41-G41-I41 -> 0 | K41: =+E41+G41+I41-D41-F41-H41 -> 0
A42: 00029 | C42: Medical expenses/staff welfare | J42: =+D42+F42+H42-E42-G42-I42 -> 0 | K42: =+E42+G42+I42-D42-F42-H42 -> 0
A43: 00030 | C43: Printing & stationery | J43: =+D43+F43+H43-E43-G43-I43 -> 0 | K43: =+E43+G43+I43-D43-F43-H43 -> 0
A44: 00031 | C44: Registration & licencing | J44: =+D44+F44+H44-E44-G44-I44 -> 0 | K44: =+E44+G44+I44-D44-F44-H44 -> 0
A45: 00032 | C45: Refreshment | J45: =+D45+F45+H45-E45-G45-I45 -> 0 | K45: =+E45+G45+I45-D45-F45-H45 -> 0
A46: 00033 | C46: Security | J46: =+D46+F46+H46-E46-G46-I46 -> 0 | K46: =+E46+G46+I46-D46-F46-H46 -> 0
A47: 00034 | C47: Licence Fees | J47: =+D47+F47+H47-E47-G47-I47 -> 0 | K47: =+E47+G47+I47-D47-F47-H47 -> 0
A48: 00035 | C48: Fuel | J48: =+D48+F48+H48-E48-G48-I48 -> 0 | K48: =+E48+G48+I48-D48-F48-H48 -> 0
... A54: 00041 | C54: Bank Charges & Interest | J54: =+D54+F54+H54-E54-G54-I54 -> 0 | K54: =+E54+G54+I54-D54-F54-H54 -> 0
C55: TOTAL | J55: =SUM(J7:J54) -> 0 | K55: =SUM(K7:K54) -> 0

Sheet RECEIPTS AND PAYMENT ANANLYSIS
A1: =+'Rec & Pmt'!A1:C1 -> THE METHODIST CHURCH GHANA
A2: =+'Rec & Pmt'!A2:C2 -> ACCRA NORTH DIOCESE
A3: =+'Rec & Pmt'!A3:C3 -> GA SUB-URBAN CIRCUIT
A4: =+'Rec & Pmt'!A4:H4 -> HEBRON SOCIETY
A5: =+'Rec & Pmt'!A5:C5 -> STATEMENT OF ACCOUNT FOR THE PERIOD 1ST JANUARY,2024 TO 31ST DECEMBER,2024
B6: JAN | C6: FEB | D6: MAR | E6: APR | F6: MAY | G6: JUN | H6: JUL | I6: AUG | J6: SEP | K6: OCT | L6: NOV | M6: DEC | N6: TOTAL
A7: RECEIPTS | B7: GHC | C7: GHC | D7: GHC | E7: GHC | F7: GHC | G7: GHC | H7: GHC | I7: GHC | J7: GHC | K7: GHC | L7: GHC | M7: GHC | N7: GHC
A8: OFFERING | B8: ='weekly income statement'!C15 -> 2682.2 | C8: ='weekly income statement'!D15 -> 2715.3 | D8: ='weekly income statement'!E15 -> 4454.4 | E8: ='weekly income statement'!F15 -> 2965.6 | F8: ='weekly income statement'!G15 -> 2499.3 | G8: ='weekly income statement'!H15 -> 3969.5 | H8: ='weekly income statement'!I15 -> 2818.3 | I8: ='weekly income statement'!J15 -> 2336.5 | ... M8: ='weekly income statement'!N15 -> 5076.7 | N8: =B8+C8+D8+E8+F8+G8+H8+I8+J8+K8+L8+M8 -> 40490.5
A9: TITHE | B9: ='weekly income statement'!C23 -> 2085 | C9: ='weekly income statement'!D23 -> 9010 | D9: ='weekly income statement'!E23 -> 10180 | E9: ='weekly income statement'!F23 -> 5240 | F9: ='weekly income statement'!G23 -> 7405 | G9: ='weekly income statement'!H23 -> 9338 | H9: ='weekly income statement'!I23 -> 7218 | I9: ='weekly income statement'!J23 -> 3820 | ... M9: ='weekly income statement'!N23 -> 9715 | N9: =B9+C9+D9+E9+F9+G9+H9+I9+J9+K9+L9+M9 -> 96711
A10: WEEKDAY ACTIVITY | B10: ='weekly income statement'!C36 -> 482.6 | C10: ='weekly income statement'!D36 -> 260 | D10: ='weekly income statement'!E36 -> 218.5 | E10: ='weekly income statement'!F36 -> 0 | F10: ='weekly income statement'!G36 -> 0 | G10: ='weekly income statement'!H36 -> 0 | H10: ='weekly income statement'!I36 -> 55 | I10: ='weekly income statement'!J36 -> 306 | ... M10: ='weekly income statement'!N36 -> 435 | N10: =B10+C10+D10+E10+F10+G10+H10+I10+J10+K10+L10+M10 -> 2772.1 | S10: 2110
A11: THANKS OFFERING | B11: ='weekly income statement'!C44 -> 350 | C11: ='weekly income statement'!D44 -> 200 | D11: ='weekly income statement'!E44 -> 50 | E11: ='weekly income statement'!F44 -> 100 | F11: ='weekly income statement'!G44 -> 250 | G11: ='weekly income statement'!H44 -> 0 | H11: ='weekly income statement'!I44 -> 310 | I11: ='weekly income statement'!J44 -> 350 | ... M11: ='weekly income statement'!N44 -> 1050 | N11: =B11+C11+D11+E11+F11+G11+H11+I11+J11+K11+L11+M11 -> 4490 | S11: 880
A12: HARVEST | B12: ='weekly income statement'!C52 -> 0 | C12: ='weekly income statement'!D52 -> 12134.9 | D12: ='weekly income statement'!E52 -> 47785 | E12: ='weekly income statement'!F52 -> 15950 | F12: ='weekly income statement'!G52 -> 3890 | G12: ='weekly income statement'!H52 -> 40200 | H12: ='weekly income statement'!I52 -> 630 | I12: ='weekly income statement'!J52 -> 100 | ... M12: ='weekly income statement'!N52 -> 58680 | N12: =B12+C12+D12+E12+F12+G12+H12+I12+J12+K12+L12+M12 -> 238458.9 | S12: 660
A13: WELFARE | B13: ='weekly income statement'!C54 -> 0 | C13: ='weekly income statement'!D54 -> 0 | D13: ='weekly income statement'!E54 -> 0 | E13: ='weekly income statement'!F54 -> 0 | F13: ='weekly income statement'!G54 -> 2970 | G13: ='weekly income statement'!H54 -> 334 | H13: ='weekly income statement'!I54 -> 513.5 | I13: ='weekly income statement'!J54 -> 347 | ... M13: ='weekly income statement'!N54 -> 0 | N13: =B13+C13+D13+E13+F13+G13+H13+I13+J13+K13+L13+M13 -> 4704.5
A14: SPECIAL OFFERING | B14: ='weekly income statement'!C55 -> 0 | C14: ='weekly income statement'!D55 -> 0 | D14: ='weekly income statement'!E55 -> 0 | E14: ='weekly income statement'!F55 -> 432 | F14: ='weekly income statement'!G55 -> 0 | G14: ='weekly income statement'!H55 -> 0 | H14: ='weekly income statement'!I55 -> 190 | I14: ='weekly income statement'!J55 -> 70 | ... M14: ='weekly income statement'!N55 -> 191 | N14: =B14+C14+D14+E14+F14+G14+H14+I14+J14+K14+L14+M14 -> 893 | S14: 100
A15: POOR FUND | B15: ='weekly income statement'!C56 -> 0 | C15: ='weekly income statement'!D56 -> 0 | D15: ='weekly income statement'!E56 -> 0 | E15: ='weekly income statement'!F56 -> 584 | F15: ='weekly income statement'!G56 -> 210 | G15: ='weekly income statement'!H56 -> 253 | H15: ='weekly income statement'!I56 -> 0 | I15: ='weekly income statement'!J56 -> 75 | ... M15: ='weekly income statement'!N56 -> 0 | N15: =B15+C15+D15+E15+F15+G15+H15+I15+J15+K15+L15+M15 -> 2429.6
A16: MDF AWARENESS | B16: ='weekly income statement'!C57 -> 0 | C16: ='weekly income statement'!D57 -> 0 | D16: ='weekly income statement'!E57 -> 0 | E16: ='weekly income statement'!F57 -> 0 | F16: ='weekly income statement'!G57 -> 0 | G16: ='weekly income statement'!H57 -> 0 | H16: ='weekly income statement'!I57 -> 0 | I16: ='weekly income statement'!J57 -> 0 | ... M16: ='weekly income statement'!N57 -> 0 | N16: =B16+C16+D16+E16+F16+G16+H16+I16+J16+K16+L16+M16 -> 671 | S16: =SUM(S10:S14) -> 3750
A17: CIRCUIT HARVEST | B17: ='weekly income statement'!C58 -> 0 | C17: ='weekly income statement'!D58 -> 0 | D17: ='weekly income statement'!E58 -> 661 | E17: ='weekly income statement'!F58 -> 0 | F17: ='weekly income statement'!G58 -> 350 | G17: ='weekly income statement'!H58 -> 0 | H17: ='weekly income statement'!I58 -> 0 | I17: ='weekly income statement'!J58 -> 0 | ... M17: ='weekly income statement'!N58 -> 0 | N17: =B17+C17+D17+E17+F17+G17+H17+I17+J17+K17+L17+M17 -> 1011
A18: LAY MOVEMENT OFFERING | B18: ='weekly income statement'!C59 -> 0 | C18: ='weekly income statement'!D59 -> 0 | D18: ='weekly income statement'!E59 -> 0 | E18: ='weekly income statement'!F59 -> 0 | F18: ='weekly income statement'!G59 -> 0 | G18: ='weekly income statement'!H59 -> 0 | H18: ='weekly income statement'!I59 -> 0 | I18: ='weekly income statement'!J59 -> 0 | ... M18: ='weekly income statement'!N59 -> 0 | N18: =B18+C18+D18+E18+F18+G18+H18+I18+J18+K18+L18+M18 -> 0
A19: SPECIAL APPEAL | B19: ='weekly income statement'!C60 -> 0 | C19: ='weekly income statement'!D60 -> 0 | D19: ='weekly income statement'!E60 -> 0 | E19: ='weekly income statement'!F60 -> 1190 | F19: ='weekly income statement'!G60 -> 0 | G19: ='weekly income statement'!H60 -> 0 | H19: ='weekly income statement'!I60 -> 0 | I19: ='weekly income statement'!J60 -> 0 | ... M19: ='weekly income statement'!N60 -> 0 | N19: =B19+C19+D19+E19+F19+G19+H19+I19+J19+K19+L19+M19 -> 1190
A20: WOMEN FELLOWSHIP | B20: ='weekly income statement'!C61 -> 0 | C20: ='weekly income statement'!D61 -> 0 | D20: ='weekly income statement'!E61 -> 0 | E20: ='weekly income statement'!F61 -> 0 | F20: ='weekly income statement'!G61 -> 0 | G20: ='weekly income statement'!H61 -> 0 | H20: ='weekly income statement'!I61 -> 2610 | I20: ='weekly income statement'!J61 -> 0 | ... M20: ='weekly income statement'!N61 -> 0 | N20: =B20+C20+D20+E20+F20+G20+H20+I20+J20+K20+L20+M20 -> 2610
A21: OTHERS/NORTHERN GHANA | B21: ='weekly income statement'!C62 -> 0 | C21: ='weekly income statement'!D62 -> 0 | D21: ='weekly income statement'!E62 -> 0 | E21: ='weekly income statement'!F62 -> 0 | F21: ='weekly income statement'!G62 -> 0 | G21: ='weekly income statement'!H62 -> 0 | H21: ='weekly income statement'!I62 -> 0 | I21: ='weekly income statement'!J62 -> 0 | ... M21: ='weekly income statement'!N62 -> 0 | N21: =B21+C21+D21+E21+F21+G21+H21+I21+J21+K21+L21+M21 -> 0
A22: AUTONOMY | B22: ='weekly income statement'!C63 -> 0 | C22: ='weekly income statement'!D63 -> 0 | D22: ='weekly income statement'!E63 -> 0 | E22: ='weekly income statement'!F63 -> 0 | F22: ='weekly income statement'!G63 -> 0 | G22: ='weekly income statement'!H63 -> 0 | H22: ='weekly income statement'!I63 -> 0 | I22: ='weekly income statement'!J63 -> 0 | ... M22: ='weekly income statement'!N63 -> 0 | N22: =B22+C22+D22+E22+F22+G22+H22+I22+J22+K22+L22+M22 -> 0
A23: WATCHNIGHT SERVICE | B23: ='weekly income statement'!C64 -> 0 | C23: ='weekly income statement'!D64 -> 0 | D23: ='weekly income statement'!E64 -> 0 | E23: ='weekly income statement'!F64 -> 0 | F23: ='weekly income statement'!G64 -> 0 | G23: ='weekly income statement'!H64 -> 0 | H23: ='weekly income statement'!I64 -> 0 | I23: ='weekly income statement'!J64 -> 0 | ... M23: ='weekly income statement'!N64 -> 0 | N23: =B23+C23+D23+E23+F23+G23+H23+I23+J23+K23+L23+M23 -> 0
A24: CONVENANT SUNDAY | B24: ='weekly income statement'!C65 -> 535 | C24: ='weekly income statement'!D65 -> 0 | D24: ='weekly income statement'!E65 -> 0 | E24: ='weekly income statement'!F65 -> 0 | F24: ='weekly income statement'!G65 -> 0 | G24: ='weekly income statement'!H65 -> 0 | H24: ='weekly income statement'!I65 -> 0 | I24: ='weekly income statement'!J65 -> 0 | ... M24: ='weekly income statement'!N65 -> 0 | N24: =B24+C24+D24+E24+F24+G24+H24+I24+J24+K24+L24+M24 -> 535
B27: =SUM(B8:B24) -> 6134.8 | C27: =SUM(C8:C24) -> 24320.2 | D27: =SUM(D8:D24) -> 63348.9 | E27: =SUM(E8:E24) -> 26461.6 | F27: =SUM(F8:F24) -> 17574.3 | G27: =SUM(G8:G24) -> 54094.5 | H27: =SUM(H8:H24) -> 14344.8 | I27: =SUM(I8:I24) -> 7404.5 | ... N27: =SUM(N8:N24) -> 396966.6
A29: EXPENDITURE
A30: HONARARIUM TO PREACHERS | B30: =Expend!C15 -> 500 | C30: =Expend!D15 -> 450 | D30: =Expend!E15 -> 2300 | E30: =Expend!F15 -> 400 | F30: =Expend!G15 -> 950 | G30: =Expend!H15 -> 4100 | H30: =Expend!I15 -> 1800 | I30: =Expend!J15 -> 1000 | ... M30: =Expend!N15 -> 1100 | N30: =B30+C30+D30+E30+F30+G30+H30+I30+J30+K30+L30+M30 -> 15000
A31: T&T | B31: =Expend!C22 -> 200 | C31: =Expend!D22 -> 0 | D31: =Expend!E22 -> 0 | E31: =Expend!F22 -> 900 | F31: =Expend!G22 -> 1200 | G31: =Expend!H22 -> 0 | H31: =Expend!I22 -> 400 | I31: =Expend!J22 -> 0 | ... M31: =Expend!N22 -> 0 | N31: =B31+C31+D31+E31+F31+G31+H31+I31+J31+K31+L31+M31 -> 2700
A32: WELFARE | B32: =Expend!C29 -> 200 | C32: =Expend!D29 -> 0 | D32: =Expend!E29 -> 700 | E32: =Expend!F29 -> 0 | F32: =Expend!G29 -> 300 | G32: =Expend!H29 -> 200 | H32: =Expend!I29 -> 0 | I32: =Expend!J29 -> 300 | ... M32: =Expend!N29 -> 200 | N32: =B32+C32+D32+E32+F32+G32+H32+I32+J32+K32+L32+M32 -> 4200
A33: FURNITURE | B33: =Expend!C34 -> 0 | C33: =Expend!D34 -> 0 | D33: =Expend!E34 -> 0 | E33: =Expend!F34 -> 0 | F33: =Expend!G34 -> 0 | G33: =Expend!H34 -> 3440 | H33: =Expend!I34 -> 0 | I33: =Expend!J34 -> 0 | ... M33: =Expend!N34 -> 5300 | N33: =B33+C33+D33+E33+F33+G33+H33+I33+J33+K33+L33+M33 -> 28407.5
A34: INSTRUMENTS | B34: =Expend!C35 -> 0 | C34: =Expend!D35 -> 0 | D34: =Expend!E35 -> 3000 | E34: =Expend!F35 -> 550 | F34: =Expend!G35 -> 4650 | G34: =Expend!H35 -> 0 | H34: =Expend!I35 -> 0 | I34: =Expend!J35 -> 0 | ... M34: =Expend!N35 -> 400 | N34: =B34+C34+D34+E34+F34+G34+H34+I34+J34+K34+L34+M34 -> 11798
A35: MDF | B35: =Expend!C36 -> 0 | C35: =Expend!D36 -> 0 | D35: =Expend!E36 -> 0 | E35: =Expend!F36 -> 0 | F35: =Expend!G36 -> 0 | G35: =Expend!H36 -> 0 | H35: =Expend!I36 -> 0 | I35: =Expend!J36 -> 0 | ... M35: =Expend!N36 -> 0 | N35: =B35+C35+D35+E35+F35+G35+H35+I35+J35+K35+L35+M35 -> 671
A36: LAYMOVEMENT | B36: =Expend!C37 -> 0 | C36: =Expend!D37 -> 0 | D36: =Expend!E37 -> 0 | E36: =Expend!F37 -> 0 | F36: =Expend!G37 -> 0 | G36: =Expend!H37 -> 0 | H36: =Expend!I37 -> 0 | I36: =Expend!J37 -> 0 | ... M36: =Expend!N37 -> 0 | N36: =B36+C36+D36+E36+F36+G36+H36+I36+J36+K36+L36+M36 -> 0
A37: CIRCUIT HARVEST | B37: =Expend!C38 -> 0 | C37: =Expend!D38 -> 188 | D37: =Expend!E38 -> 661 | E37: =Expend!F38 -> 0 | F37: =Expend!G38 -> 350 | G37: =Expend!H38 -> 0 | H37: =Expend!I38 -> 0 | I37: =Expend!J38 -> 0 | ... M37: =Expend!N38 -> 0 | N37: =B37+C37+D37+E37+F37+G37+H37+I37+J37+K37+L37+M37 -> 1199
A38: DONATIONS | B38: =Expend!C39 -> 0 | C38: =Expend!D39 -> 0 | D38: =Expend!E39 -> 0 | E38: =Expend!F39 -> 0 | F38: =Expend!G39 -> 0 | G38: =Expend!H39 -> 0 | H38: =Expend!I39 -> 0 | I38: =Expend!J39 -> 0 | ... M38: =Expend!N39 -> 2050 | N38: =B38+C38+D38+E38+F38+G38+H38+I38+J38+K38+L38+M38 -> 3050
A39: MINISTERS APPRECIATION | B39: =Expend!C40 -> 0 | C39: =Expend!D40 -> 0 | D39: =Expend!E40 -> 0 | E39: =Expend!F40 -> 0 | F39: =Expend!G40 -> 0 | G39: =Expend!H40 -> 0 | H39: =Expend!I40 -> 0 | I39: =Expend!J40 -> 0 | ... M39: =Expend!N40 -> 0 | N39: =B39+C39+D39+E39+F39+G39+H39+I39+J39+K39+L39+M39 -> 0
A40: PURCHASE OF METHODIST STATIONARY | B40: =Expend!C41 -> 160 | C40: =Expend!D41 -> 280 | D40: =Expend!E41 -> 1100 | E40: =Expend!F41 -> 70 | F40: =Expend!G41 -> 0 | G40: =Expend!H41 -> 0 | H40: =Expend!I41 -> 500 | I40: =Expend!J41 -> 0 | ... M40: =Expend!N41 -> 0 | N40: =B40+C40+D40+E40+F40+G40+H40+I40+J40+K40+L40+M40 -> 2110
A41: DIOCESAN APPEAL(CHILD WEEK) | B41: =Expend!C42 -> 0 | C41: =Expend!D42 -> 0 | D41: =Expend!E42 -> 0 | E41: =Expend!F42 -> 0 | F41: =Expend!G42 -> 0 | G41: =Expend!H42 -> 0 | H41: =Expend!I42 -> 0 | I41: =Expend!J42 -> 0 | ... M41: =Expend!N42 -> 0 | N41: =B41+C41+D41+E41+F41+G41+H41+I41+J41+K41+L41+M41 -> 0
A42: =+Expend!B47 -> WATER & ECG | B42: =+Expend!C47 -> 0 | C42: =+Expend!D47 -> 0 | D42: =+Expend!E47 -> 0 | E42: =+Expend!F47 -> 0 | F42: =+Expend!G47 -> 0 | G42: =+Expend!H47 -> 0 | H42: =+Expend!I47 -> 300 | ... M42: =+Expend!N47 -> 300 | N42: =B42+C42+D42+E42+F42+G42+H42+I42+J42+K42+L42+M42 -> 600
A43: LAND | B43: =Expend!C80 -> 0 | C43: =Expend!D80 -> 0 | D43: =Expend!E80 -> 200 | E43: =Expend!F80 -> 0 | F43: =Expend!G80 -> 0 | G43: =Expend!H80 -> 0 | H43: =Expend!I80 -> 0 | I43: =Expend!J80 -> 0 | ... M43: =Expend!N80 -> 20000 | N43: =B43+C43+D43+E43+F43+G43+H43+I43+J43+K43+L43+M43 -> 66200
A44: HARVEST ENVELOPES | B44: =Expend!C81 -> 0 | C44: =Expend!D81 -> 300 | D44: =Expend!E81 -> 0 | E44: =Expend!F81 -> 0 | F44: =Expend!G81 -> 300 | G44: =Expend!H81 -> 0 | H44: =Expend!I81 -> 0 | I44: =Expend!J81 -> 0 | ... M44: =Expend!N81 -> 0 | N44: =B44+C44+D44+E44+F44+G44+H44+I44+J44+K44+L44+M44 -> 600
A45: BANNER | B45: =Expend!C82 -> 0 | C45: =Expend!D82 -> 250 | D45: =Expend!E82 -> 230 | E45: =Expend!F82 -> 0 | F45: =Expend!G82 -> 0 | G45: =Expend!H82 -> 0 | H45: =Expend!I82 -> 0 | I45: =Expend!J82 -> 0 | ... M45: =Expend!N82 -> 0 | N45: =B45+C45+D45+E45+F45+G45+H45+I45+J45+K45+L45+M45 -> 480
A46: REFRESHMENT | B46: =Expend!C83 -> 0 | C46: =Expend!D83 -> 0 | D46: =Expend!E83 -> 0 | E46: =Expend!F83 -> 0 | F46: =Expend!G83 -> 0 | G46: =Expend!H83 -> 0 | H46: =Expend!I83 -> 0 | I46: =Expend!J83 -> 0 | ... M46: =Expend!N83 -> 5300 | N46: =B46+C46+D46+E46+F46+G46+H46+I46+J46+K46+L46+M46 -> 5300
A47: BUILDING PROJECT | B47: =Expend!C84 -> 60000 | C47: =Expend!D84 -> 46000 | D47: =Expend!E84 -> 25000 | E47: =Expend!F84 -> 26600 | F47: =Expend!G84 -> 0 | G47: =Expend!H84 -> 43040 | H47: =Expend!I84 -> 20000 | I47: =Expend!J84 -> 0 | ... M47: =Expend!N84 -> 38460 | N47: =B47+C47+D47+E47+F47+G47+H47+I47+J47+K47+L47+M47 -> 259100
A48: FILLING | B48: =Expend!C85 -> 0 | C48: =Expend!D85 -> 0 | D48: =Expend!E85 -> 0 | E48: =Expend!F85 -> 0 | F48: =Expend!G85 -> 0 | G48: =Expend!H85 -> 0 | H48: =Expend!I85 -> 0 | I48: =Expend!J85 -> 0 | ... M48: =Expend!N85 -> 0 | N48: =B48+C48+D48+E48+F48+G48+H48+I48+J48+K48+L48+M48 -> 0
A49: AUTONOMY | B49: =Expend!C86 -> 0 | C49: =Expend!D86 -> 0 | D49: =Expend!E86 -> 0 | E49: =Expend!F86 -> 0 | F49: =Expend!G86 -> 0 | G49: =Expend!H86 -> 0 | H49: =Expend!I86 -> 0 | I49: =Expend!J86 -> 0 | ... M49: =Expend!N86 -> 0 | N49: =B49+C49+D49+E49+F49+G49+H49+I49+J49+K49+L49+M49 -> 0
A50: MISCELLANEOUS | B50: =Expend!C87 -> 0 | C50: =Expend!D87 -> 0 | D50: =Expend!E87 -> 0 | E50: =Expend!O87 -> 1400 | F50: =Expend!G87 -> 0 | G50: =Expend!H87 -> 300 | H50: =Expend!I87 -> 0 | I50: =Expend!J87 -> 100 | J50: =Expend!K87 -> 0 | K50: =Expend!L87 -> 100 | L50: =Expend!M87 -> 0 | M50: =Expend!N87 -> 0 | N50: =B50+C50+D50+E50+F50+G50+H50+I50+J50+K50+L50+M50 -> 1900
A51: WATCHNIGHT SERVICE | B51: =Expend!C88 -> 0 | C51: =Expend!D88 -> 0 | D51: =Expend!E88 -> 0 | E51: =Expend!F88 -> 0 | F51: =Expend!G88 -> 0 | G51: =Expend!H88 -> 0 | H51: =Expend!I88 -> 0 | I51: =Expend!J88 -> 0 | ... M51: =Expend!N88 -> 0 | N51: =B51+C51+D51+E51+F51+G51+H51+I51+J51+K51+L51+M51 -> 0
A52: CONVENANT SUNDAY | B52: =Expend!C89 -> 275 | C52: =Expend!D89 -> 0 | D52: =Expend!E89 -> 0 | E52: =Expend!F89 -> 0 | F52: =Expend!G89 -> 0 | G52: =Expend!H89 -> 0 | H52: =Expend!I89 -> 0 | I52: =Expend!J89 -> 0 | ... M52: =Expend!N89 -> 0 | N52: =B52+C52+D52+E52+F52+G52+H52+I52+J52+K52+L52+M52 -> 275
A53: GA RURAL BANK | B53: =Expend!C93 -> 8212 | C53: =Expend!D93 -> 23982 | D53: =Expend!E93 -> 36600 | E53: =Expend!F93 -> 26065 | F53: =Expend!G93 -> 0 | G53: =Expend!H93 -> 47250 | H53: =Expend!I93 -> 21210 | I53: =Expend!J93 -> 1500 | ... M53: =Expend!N93 -> 53275 | N53: =B53+C53+D53+E53+F53+G53+H53+I53+J53+K53+L53+M53 -> 289814
A54: REPUBLIC BANK | B54: =Expend!C95 -> 0 | C54: =Expend!D95 -> 0 | D54: =Expend!E95 -> 0 | E54: =Expend!F95 -> 0 | F54: =Expend!G95 -> 0 | G54: =Expend!H95 -> 0 | H54: =Expend!I95 -> 0 | I54: =Expend!J95 -> 0 | ... M54: =Expend!N95 -> 0 | N54: =B54+C54+D54+E54+F54+G54+H54+I54+J54+K54+L54+M54 -> 0
A55: BANK CHARGES | B55: =Expend!C94 -> 231.2 | C55: =Expend!D94 -> 0 | D55: =Expend!E94 -> 0 | E55: =Expend!F94 -> 0 | F55: =Expend!G94 -> 0 | G55: =Expend!H94 -> 0 | H55: =Expend!I94 -> 0 | I55: =Expend!J94 -> 0 | ... M55: =Expend!N94 -> 0 | N55: =B55+C55+D55+E55+F55+G55+H55+I55+J55+K55+L55+M55 -> 231.2
A56: RENT | B56: =Expend!C48 -> 0 | C56: =Expend!D48 -> 0 | D56: =Expend!E48 -> 0 | E56: =Expend!F48 -> 0 | F56: =Expend!G48 -> 0 | G56: =Expend!H48 -> 0 | H56: =Expend!I48 -> 0 | I56: =Expend!J48 -> 0 | ... M56: =Expend!N48 -> 0 | N56: =B56+C56+D56+E56+F56+G56+H56+I56+J56+K56+L56+M56 -> 7200
A57: SALARY - ORGANIST | B57: =Expend!C49 -> 0 | C57: =Expend!D49 -> 0 | D57: =Expend!E49 -> 0 | E57: =Expend!F49 -> 0 | F57: =Expend!G49 -> 0 | G57: =Expend!H49 -> 0 | H57: =Expend!I49 -> 0 | I57: =Expend!J49 -> 0 | ... M57: =Expend!N49 -> 3100 | N57: =B57+C57+D57+E57+F57+G57+H57+I57+J57+K57+L57+M57 -> 4700
A58: ALLOWANCE FOR MINISTER | B58: =Expend!C50 -> 0 | C58: =Expend!D50 -> 0 | D58: =Expend!E50 -> 0 | E58: =Expend!F50 -> 0 | F58: =Expend!G50 -> 0 | G58: =Expend!H50 -> 0 | H58: =Expend!I50 -> 0 | I58: =Expend!J50 -> 0 | ... N58: =Expend!O50 -> 3500
A59: ASSESSMENT | B59: =Expend!C55 -> 0 | C59: =Expend!D55 -> 0 | D59: =Expend!E55 -> 0 | E59: =Expend!F55 -> 0 | F59: =Expend!G55 -> 0 | G59: =Expend!H55 -> 0 | H59: =Expend!I55 -> 0 | I59: =Expend!J55 -> 0 | ... N59: =Expend!O55 -> 16495.78
A60: SALARY ADVANCE
B62: =SUM(B30:B55) -> 69778.2 | C62: =SUM(C30:C55) -> 71450 | D62: =SUM(D30:D55) -> 69791 | E62: =SUM(E30:E55) -> 55985 | F62: =SUM(F30:F55) -> 7750 | G62: =SUM(G30:G55) -> 98330 | H62: =SUM(H30:H55) -> 44210 | I62: =SUM(I30:I55) -> 2900 | ... N62: =SUM(N30:N55) -> 693635.7
B63: GHS
A64: GA RURAL BANK | B64: =+'Rec & Pmt'!B75 -> 14173.5
A65: REPUBLIC BANK | B65: =+'Rec & Pmt'!B76 -> 200
A66: CASH | B66: =+'Rec & Pmt'!B77 -> 6339.8
A67: TOTAL | B67: =SUM(B64:B66) -> 20713.3

Sheet weekly income statement
A1: =+'RECEIPTS AND PAYMENT ANANLYSIS'!A1:N1 -> THE METHODIST CHURCH GHANA
A2: =+'RECEIPTS AND PAYMENT ANANLYSIS'!A2:N2 -> ACCRA NORTH DIOCESE
A3: =+'RECEIPTS AND PAYMENT ANANLYSIS'!A3:N3 -> GA SUB-URBAN CIRCUIT
A4: =+'RECEIPTS AND PAYMENT ANANLYSIS'!A4:N4 -> HEBRON SOCIETY
A5: =+'RECEIPTS AND PAYMENT ANANLYSIS'!A5:N5 -> STATEMENT OF ACCOUNT FOR THE PERIOD 1ST JANUARY,2024 TO 31ST DECEMBER,2024
A7: S/N | B7: NAME | C7: JAN | D7: FEB | E7: MAR | F7: APR | G7: MAY | H7: JUN | I7: JUL | J7: AUG | K7: SEP | L7: OCT | M7: NOV | N7: DEC | O7: TOTAL
A8: DATE | C8: GHC | D8: GHC | E8: GHC | F8: GHC | G8: GHC | H8: GHC | I8: GHC | J8: GHC | K8: GHC | L8: GHC | M8: GHC | N8: GHC | O8: GHC
B9: OFFERING | C9: 0 | O9: =C9+D9+E9+F9+G9+H9+I9+J9+K9+L9+M9+N9 -> 0
A10: WK 1 | C10: 215 | D10: =437+111.5 -> 548.5 | E10: =483.7+128.5 -> 612.2 | F10: =495+104 -> 599 | G10: 757.1 | H10: =736+114 -> 850 | I10: 846 | J10: 542.3 | K10: =132+573 -> 705 | L10: =780+137.6 -> 917.6 | M10: =785+55.4 -> 840.4 | N10: 830 | O10: =C10+D10+E10+F10+G10+H10+I10+J10+K10+L10+M10+N10 -> 8263.1
A11: WK 2 | C11: =609+112.7 -> 721.7 | D11: =687+86.1 -> 773.1 | E11: =511.5+109.5 -> 621 | F11: 865.5 | G11: =395.7+106.5 -> 502.2 | H11: =754+70.8 -> 824.8 | I11: =522.5+137.4 -> 659.9 | J11: 496.5 | K11: =748.5+100.5 -> 849 | L11: =754.5+54 -> 808.5 | M11: =619+151.9 -> 770.9 | N11: =666+151.5 -> 817.5 | O11: =C11+D11+E11+F11+G11+H11+I11+J11+K11+L11+M11+N11 -> 8710.6
A12: WK 3 | C12: =662+214 -> 876 | D12: 238 | E12: =649+156.5 -> 805.5 | F12: =696.3+153.9 -> 850.2 | G12: =702.5+105 -> 807.5 | H12: =772+131.5 -> 903.5 | I12: 774 | J12: =643.4+89.2 -> 732.6 | K12: 815.7 | L12: =614.5+282.1+51 -> 947.6 | M12: =774.2+146.9 -> 921.1 | N12: =926+139.3 -> 1065.3 | O12: =C12+D12+E12+F12+G12+H12+I12+J12+K12+L12+M12+N12 -> 9737
A13: WK 4 | C13: 869.5 | D13: 538 | E13: =673+128.7 -> 801.7 | F13: =539+111.9 -> 650.9 | G13: =355+77.5 -> 432.5 | H13: =420+147.5 -> 567.5 | I13: =436.4+102 -> 538.4 | J13: =416+149.1 -> 565.1 | K13: 1032.2 | L13: =602+101 -> 703 | M13: =774+113 -> 887 | N13: =703+532+135.4 -> 1370.4 | O13: =C13+D13+E13+F13+G13+H13+I13+J13+K13+L13+M13+N13 -> 8956.2
A14: WK 5 | D14: =476.2+141.5 -> 617.7 | E14: =864.5+625.5+124 -> 1614 | H14: =681.7+142 -> 823.7 | K14: =666.5+108.2 -> 774.7 | N14: =953.5+40 -> 993.5 | O14: =C14+D14+E14+F14+G14+H14+I14+J14+K14+L14+M14+N14 -> 4823.6
C15: =SUM(C9:C14) -> 2682.2 | D15: =SUM(D9:D14) -> 2715.3 | E15: =SUM(E9:E14) -> 4454.4 | F15: =SUM(F9:F14) -> 2965.6 | G15: =SUM(G9:G14) -> 2499.3 | H15: =SUM(H9:H14) -> 3969.5 | I15: =SUM(I9:I14) -> 2818.3 | J15: =SUM(J9:J14) -> 2336.5 | ... N15: =SUM(N9:N14) -> 5076.7 | O15: =C15+D15+E15+F15+G15+H15+I15+J15+K15+L15+M15+N15 -> 40490.5
O16: =C16+D16+E16+F16+G16+H16+I16+J16+K16+L16+M16+N16 -> 0
B17: TITHE | C17: 0 | O17: =C17+D17+E17+F17+G17+H17+I17+J17+K17+L17+M17+N17 -> 0
A18: WK 1 | C18: 450 | D18: 4775 | E18: 970 | F18: 1120 | G18: 2820 | H18: 4510 | I18: 3978 | J18: 900 | K18: 5570 | L18: 3340 | M18: 2590 | N18: 2490 | O18: =C18+D18+E18+F18+G18+H18+I18+J18+K18+L18+M18+N18 -> 33513
A19: WK 2 | C19: 840 | D19: 265 | E19: 3555 | F19: 1550 | G19: 4265 | H19: 3448 | I19: 2850 | J19: 1010 | K19: 5380 | L19: 4680 | M19: 4610 | N19: 3240 | O19: =C19+D19+E19+F19+G19+H19+I19+J19+K19+L19+M19+N19 -> 35693
A20: WK 3 | C20: 795 | D20: 1050 | E20: 280 | F20: 1700 | G20: 100 | H20: 410 | I20: 270 | J20: 420 | K20: 900 | L20: 60 | M20: 890 | N20: 2840 | O20: =C20+D20+E20+F20+G20+H20+I20+J20+K20+L20+M20+N20 -> 9715
A21: WK 4 | D21: =2360+560 -> 2920 | E21: 650 | F21: 870 | G21: 220 | H21: 520 | I21: 120 | J21: 1490 | K21: 1550 | L21: 1020 | M21: 2010 | N21: 745 | O21: =C21+D21+E21+F21+G21+H21+I21+J21+K21+L21+M21+N21 -> 12115
A22: WK 5 | E22: =4325+400 -> 4725 | H22: 450 | K22: 100 | N22: 400 | O22: =C22+D22+E22+F22+G22+H22+I22+J22+K22+L22+M22+N22 -> 5675
C23: =SUM(C17:C22) -> 2085 | D23: =SUM(D17:D22) -> 9010 | E23: =SUM(E17:E22) -> 10180 | F23: =SUM(F17:F22) -> 5240 | G23: =SUM(G17:G22) -> 7405 | H23: =SUM(H17:H22) -> 9338 | I23: =SUM(I17:I22) -> 7218 | J23: =SUM(J17:J22) -> 3820 | ... N23: =SUM(N17:N22) -> 9715 | O23: =C23+D23+E23+F23+G23+H23+I23+J23+K23+L23+M23+N23 -> 96711
B25: WEEK DAY OFFERING | O25: =C25+D25+E25+F25+G25+H25+I25+J25+K25+L25+M25+N25 -> 0
A26: WK 1 | B26: WEDNESDAY | C26: 75 | D26: 55 | J26: 45 | K26: 80 | L26: 176 | M26: 42 | O26: =C26+D26+E26+F26+G26+H26+I26+J26+K26+L26+M26+N26 -> 473
B27: FRIDAY | C27: 57 | D27: 75 | E27: 55 | J27: 53 | K27: 35 | L27: 161 | M27: 102 | N27: 55 | O27: =C27+D27+E27+F27+G27+H27+I27+J27+K27+L27+M27+N27 -> 593
A28: WK 2 | B28: WEDNESDAY | C28: 55 | D28: 65 | E28: 41 | J28: 85 | K28: 80 | M28: 116 | N28: 110 | O28: =C28+D28+E28+F28+G28+H28+I28+J28+K28+L28+M28+N28 -> 552
B29: FRIDAY | C29: 102 | D29: 30 | E29: 31 | J29: 30 | K29: 50 | M29: 113 | N29: 57 | O29: =C29+D29+E29+F29+G29+H29+I29+J29+K29+L29+M29+N29 -> 413
A30: WK 3 | B30: WEDNESDAY | C30: 137.4 | D30: 35 | E30: 91.5 | J30: 53 | K30: 30 | N30: 213 | O30: =C30+D30+E30+F30+G30+H30+I30+J30+K30+L30+M30+N30 -> 559.9
B31: FRIDAY | C31: 56.2 | I31: 55 | J31: 40 | K31: 30 | O31: =C31+D31+E31+F31+G31+H31+I31+J31+K31+L31+M31+N31 -> 181.2
A32: WK 4 | B32: WEDNESDAY | O32: =C32+D32+E32+F32+G32+H32+I32+J32+K32+L32+M32+N32 -> 0
B33: FRIDAY | O33: =C33+D33+E33+F33+G33+H33+I33+J33+K33+L33+M33+N33 -> 0
A34: WK 5 | B34: WEDNESDAY | O34: =C34+D34+E34+F34+G34+H34+I34+J34+K34+L34+M34+N34 -> 0
B35: FRIDAY | O35: =C35+D35+E35+F35+G35+H35+I35+J35+K35+L35+M35+N35 -> 0
C36: =SUM(C25:C35) -> 482.6 | D36: =SUM(D25:D35) -> 260 | E36: =SUM(E25:E35) -> 218.5 | F36: =SUM(F25:F35) -> 0 | G36: =SUM(G25:G35) -> 0 | H36: =SUM(H25:H35) -> 0 | I36: =SUM(I25:I35) -> 55 | J36: =SUM(J25:J35) -> 306 | ... N36: =SUM(N25:N35) -> 435 | O36: =C36+D36+E36+F36+G36+H36+I36+J36+K36+L36+M36+N36 -> 2772.1
O37: =C37+D37+E37+F37+G37+H37+I37+J37+K37+L37+M37+N37 -> 0
B38: THANKS OFFERING | C38: 300 | D38: 200 | E38: 50 | F38: 50 | G38: 250 | I38: 200 | J38: 200 | K38: 500 | L38: 200 | M38: 100 | N38: 50 | O38: =C38+D38+E38+F38+G38+H38+I38+J38+K38+L38+M38+N38 -> 2100
C39: 50 | F39: 50 | I39: 110 | J39: 150 | K39: 80 | L39: 100 | M39: 250 | N39: 700 | O39: =C39+D39+E39+F39+G39+H39+I39+J39+K39+L39+M39+N39 -> 1490
K40: 50 | L40: 200 | M40: 50 | N40: 100 | O40: =C40+D40+E40+F40+G40+H40+I40+J40+K40+L40+M40+N40 -> 400
K41: 200 | N41: 200 | O41: =C41+D41+E41+F41+G41+H41+I41+J41+K41+L41+M41+N41 -> 400
K42: 100 | O42: =C42+D42+E42+F42+G42+H42+I42+J42+K42+L42+M42+N42 -> 100
O43: =SUM(O38:O42) -> 4490
C44: =SUM(C38:C43) -> 350 | D44: =SUM(D38:D43) -> 200 | E44: =SUM(E38:E43) -> 50 | F44: =SUM(F38:F43) -> 100 | G44: =SUM(G38:G43) -> 250 | H44: =SUM(H38:H43) -> 0 | I44: =SUM(I38:I43) -> 310 | J44: =SUM(J38:J43) -> 350 | ... N44: =SUM(N38:N43) -> 1050 | O44: =C44+D44+E44+F44+G44+H44+I44+J44+K44+L44+M44+N44 -> 4490
O45: =C45+D45+E45+F45+G45+H45+I45+J45+K45+L45+M45+N45 -> 0
B46: HARVEST | D46: 50 | E46: =500+50 -> 550 | F46: 550 | G46: =3500+375 -> 3875 | H46: 30585 | I46: 500 | J46: 20 | K46: =19295+6255-1200 -> 24350 | M46: 120 | N46: =32390+14505 -> 46895 | O46: =C46+D46+E46+F46+G46+H46+I46+J46+K46+L46+M46+N46 -> 107495
D47: 500 | E47: =90+29250 -> 29340 | F47: =9200+6200 -> 15400 | G47: 15 | H47: 8100 | I47: 130 | J47: 80 | K47: =165+80 -> 245 | M47: 31509 | N47: =2205+1000 -> 3205 | O47: =C47+D47+E47+F47+G47+H47+I47+J47+K47+L47+M47+N47 -> 88524
D48: =1224.9-280 -> 944.9 | E48: 490 | H48: 810 | K48: 50 | M48: 205 | N48: 1300 | O48: =C48+D48+E48+F48+G48+H48+I48+J48+K48+L48+M48+N48 -> 3799.9
D49: 10640 | E49: =9000+1000 -> 10000 | H49: 305 | M49: 210 | N49: =2000+50 -> 2050 | O49: =C49+D49+E49+F49+G49+H49+I49+J49+K49+L49+M49+N49 -> 23205
E50: =4000+3000+265+140 -> 7405 | H50: 0 | M50: 2400 | N50: 600 | O50: =C50+D50+E50+F50+G50+H50+I50+J50+K50+L50+M50+N50 -> 10405
H51: 400 | N51: =1130+3500 -> 4630 | O51: =C51+D51+E51+F51+G51+H51+I51+J51+K51+L51+M51+N51 -> 5030
C52: =SUM(C46:C51) -> 0 | D52: =SUM(D46:D51) -> 12134.9 | E52: =SUM(E46:E51) -> 47785 | F52: =SUM(F46:F51) -> 15950 | G52: =SUM(G46:G51) -> 3890 | H52: =SUM(H46:H51) -> 40200 | I52: =SUM(I46:I51) -> 630 | J52: =SUM(J46:J51) -> 100 | ... N52: =SUM(N46:N51) -> 58680 | O52: =C52+D52+E52+F52+G52+H52+I52+J52+K52+L52+M52+N52 -> 238458.9
B54: WELFARE | G54: =1990+610+370 -> 2970 | H54: 334 | I54: 513.5 | J54: 347 | K54: 540 | O54: =C54+D54+E54+F54+G54+H54+I54+J54+K54+L54+M54+N54 -> 4704.5
B55: SPECIAL OFFERING | F55: 432 | I55: =150+40 -> 190 | J55: =20+50 -> 70 | K55: 10 | N55: 191 | O55: =C55+D55+E55+F55+G55+H55+I55+J55+K55+L55+M55+N55 -> 893
B56: POOR FUND | F56: 584 | G56: 210 | H56: 253 | J56: 75 | L56: =85+460.6 -> 545.6 | M56: 762 | O56: =C56+D56+E56+F56+G56+H56+I56+J56+K56+L56+M56+N56 -> 2429.6
B57: MDF AWARENESS | M57: 671 | O57: =C57+D57+E57+F57+G57+H57+I57+J57+K57+L57+M57+N57 -> 671
B58: CIRCUIT HARVEST | E58: 661 | G58: 350 | O58: =C58+D58+E58+F58+G58+H58+I58+J58+K58+L58+M58+N58 -> 1011
B59: LAY MOVEMENT OFFERING | O59: =C59+D59+E59+F59+G59+H59+I59+J59+K59+L59+M59+N59 -> 0
B60: SPECIAL FUND RAISING FOR INSTRUMENTS | F60: 1190 | O60: =C60+D60+E60+F60+G60+H60+I60+J60+K60+L60+M60+N60 -> 1190
B61: WOMEN FELLOWSHIP | I61: 2610 | O61: =C61+D61+E61+F61+G61+H61+I61+J61+K61+L61+M61+N61 -> 2610
B62: OTHERS/NORTHERN GHANA | O62: =C62+D62+E62+F62+G62+H62+I62+J62+K62+L62+M62+N62 -> 0
B63: AUTONOMY SUNDAY | O63: =C63+D63+E63+F63+G63+H63+I63+J63+K63+L63+M63+N63 -> 0
B64: WATCHNIGHT SERVICE | O64: =C64+D64+E64+F64+G64+H64+I64+J64+K64+L64+M64+N64 -> 0
B65: CONVENANT SUNDAY | C65: 535 | O65: =C65+D65+E65+F65+G65+H65+I65+J65+K65+L65+M65+N65 -> 535
O66: =C66+D66+E66+F66+G66+H66+I66+J66+K66+L66+M66+N66 -> 0
C67: =SUM(C54:C66) -> 535 | D67: =SUM(D54:D66) -> 0 | E67: =SUM(E54:E66) -> 661 | F67: =SUM(F54:F66) -> 2206 | G67: =SUM(G54:G66) -> 3530 | H67: =SUM(H54:H66) -> 587 | I67: =SUM(I54:I66) -> 3313.5 | J67: =SUM(J54:J66) -> 492 | ... O67: =SUM(O54:O66) -> 14044.1
C68: =+C15+C23+C36+C44+C52+C67 -> 6134.8 | D68: =+D15+D23+D36+D44+D52+D67 -> 24320.2 | E68: =+E15+E23+E36+E44+E52+E67 -> 63348.9 | F68: =+F15+F23+F36+F44+F52+F67 -> 26461.6 | G68: =+G15+G23+G36+G44+G52+G67 -> 17574.3 | H68: =+H15+H23+H36+H44+H52+H67 -> 54094.5 | I68: =+I15+I23+I36+I44+I52+I67 -> 14344.8 | J68: =+J15+J23+J36+J44+J52+J67 -> 7404.5 | ... O68: =+O15+O23+O36+O44+O52+O67 -> 396966.6

Sheet Expend
A1: =+'weekly income statement'!A1:O1 -> THE METHODIST CHURCH GHANA
A2: =+'weekly income statement'!A2:O2 -> ACCRA NORTH DIOCESE
A3: =+'weekly income statement'!A3:O3 -> GA SUB-URBAN CIRCUIT
A4: =+'weekly income statement'!A4:O4 -> HEBRON SOCIETY
A5: =+'weekly income statement'!A5:O5 -> STATEMENT OF ACCOUNT FOR THE PERIOD 1ST JANUARY,2024 TO 31ST DECEMBER,2024
A6: rev
A8: S/N | B8: NAME | C8: JAN | D8: FEB | E8: MAR | F8: APR | G8: MAY | H8: JUN | I8: JUL | J8: AUG | K8: SEP | L8: OCT | M8: NOV | N8: DEC | O8: TOTAL
C9: GHC | D9: GHC | E9: GHC | F9: GHC | G9: GHC | H9: GHC | I9: GHC | J9: GHC | K9: GHC | L9: GHC | M9: GHC | N9: GHC | O9: GHC
B10: HONARARIUM TO PREACHERS | C10: 100 | D10: 100 | E10: 600 | F10: 50 | G10: 650 | H10: 400 | I10: 100 | J10: 100 | K10: 400 | L10: 200 | M10: 100 | N10: 500 | O10: =C10+D10+E10+F10+G10+H10+I10+J10+K10+L10+M10+N10 -> 3300
C11: 400 | D11: 50 | E11: 100 | F11: 100 | G11: 100 | H11: 100 | I11: 200 | J11: 200 | K11: 100 | L11: 100 | M11: 100 | N11: 200 | O11: =C11+D11+E11+F11+G11+H11+I11+J11+K11+L11+M11+N11 -> 1750
D12: =200+50 -> 250 | E12: 1000 | F12: 50 | H12: 200 | I12: 100 | J12: 200 | K12: 150 | L12: 200 | M12: 100 | N12: 200 | O12: =C12+D12+E12+F12+G12+H12+I12+J12+K12+L12+M12+N12 -> 2450
D13: 50 | E13: 600 | F13: 200 | G13: 200 | H13: 400 | I13: 1000 | J13: 500 | K13: 450 | L13: 200 | M13: 200 | N13: 200 | O13: =C13+D13+E13+F13+G13+H13+I13+J13+K13+L13+M13+N13 -> 4000
H14: 3000 | I14: 400 | L14: 100 | N14: 0 | O14: =C14+D14+E14+F14+G14+H14+I14+J14+K14+L14+M14+N14 -> 3500
C15: =SUM(C10:C14) -> 500 | D15: =SUM(D10:D14) -> 450 | E15: =SUM(E10:E14) -> 2300 | F15: =SUM(F10:F14) -> 400 | G15: =SUM(G10:G14) -> 950 | H15: =SUM(H10:H14) -> 4100 | I15: =SUM(I10:I14) -> 1800 | J15: =SUM(J10:J14) -> 1000 | ... N15: =SUM(N10:N14) -> 1100 | O15: =C15+D15+E15+F15+G15+H15+I15+J15+K15+L15+M15+N15 -> 15000
O16: =C16+D16+E16+F16+G16+H16+I16+J16+K16+L16+M16+N16 -> 0
B17: T&T TO CIRCUIT & SESSIONAL EVENTS | C17: 200 | F17: 900 | G17: 1200 | I17: 400 | O17: =C17+D17+E17+F17+G17+H17+I17+J17+K17+L17+M17+N17 -> 2700
O18: =C18+D18+E18+F18+G18+H18+I18+J18+K18+L18+M18+N18 -> 0
O19: =C19+D19+E19+F19+G19+H19+I19+J19+K19+L19+M19+N19 -> 0
O20: =C20+D20+E20+F20+G20+H20+I20+J20+K20+L20+M20+N20 -> 0
O21: =C21+D21+E21+F21+G21+H21+I21+J21+K21+L21+M21+N21 -> 0
C22: =SUM(C17:C21) -> 200 | D22: =SUM(D17:D21) -> 0 | E22: =SUM(E17:E21) -> 0 | F22: =SUM(F17:F21) -> 900 | G22: =SUM(G17:G21) -> 1200 | H22: =SUM(H17:H21) -> 0 | I22: =SUM(I17:I21) -> 400 | J22: =SUM(J17:J21) -> 0 | ... N22: =SUM(N17:N21) -> 0 | O22: =C22+D22+E22+F22+G22+H22+I22+J22+K22+L22+M22+N22 -> 2700
O23: =C23+D23+E23+F23+G23+H23+I23+J23+K23+L23+M23+N23 -> 0
B24: WELFARE | C24: 200 | E24: 200 | G24: 300 | H24: 200 | J24: =100+200 -> 300 | K24: 400 | L24: 200 | M24: =200+1000 -> 1200 | N24: 200 | O24: =C24+D24+E24+F24+G24+H24+I24+J24+K24+L24+M24+N24 -> 3200
E25: 500 | M25: 500 | O25: =C25+D25+E25+F25+G25+H25+I25+J25+K25+L25+M25+N25 -> 1000
O26: =C26+D26+E26+F26+G26+H26+I26+J26+K26+L26+M26+N26 -> 0
O27: =C27+D27+E27+F27+G27+H27+I27+J27+K27+L27+M27+N27 -> 0
O28: =C28+D28+E28+F28+G28+H28+I28+J28+K28+L28+M28+N28 -> 0
C29: =SUM(C24:C28) -> 200 | D29: =SUM(D24:D28) -> 0 | E29: =SUM(E24:E28) -> 700 | F29: =SUM(F24:F28) -> 0 | G29: =SUM(G24:G28) -> 300 | H29: =SUM(H24:H28) -> 200 | I29: =SUM(I24:I28) -> 0 | J29: =SUM(J24:J28) -> 300 | ... N29: =SUM(N24:N28) -> 200 | O29: =C29+D29+E29+F29+G29+H29+I29+J29+K29+L29+M29+N29 -> 4200
D30: 0 | F30: =SUM(F29) -> 0
B34: PURCHASE OF FURNITURE | H34: 3440 | M34: =5400+3500+3129.3+1618.2+120+600+3900+300+1100 -> 19667.5 | N34: 5300 | O34: =C34+D34+E34+F34+G34+H34+I34+J34+K34+L34+M34+N34 -> 28407.5
B35: PURCHASE OF INSTRUMENTS | E35: 3000 | F35: 550 | G35: =750+400+3500 -> 4650 | M35: =1147+500+1251+300 -> 3198 | N35: 400 | O35: =C35+D35+E35+F35+G35+H35+I35+J35+K35+L35+M35+N35 -> 11798
B36: PAYMENT OF MDF/SPECIAL APPEAL | M36: 671 | O36: =C36+D36+E36+F36+G36+H36+I36+J36+K36+L36+M36+N36 -> 671
B37: PAYMENT OF LAYMOVEMENT FUNDS | O37: =C37+D37+E37+F37+G37+H37+I37+J37+K37+L37+M37+N37 -> 0
B38: PAYMENT OF CIRCUIT HARVEST | D38: 188 | E38: 661 | G38: 350 | O38: =C38+D38+E38+F38+G38+H38+I38+J38+K38+L38+M38+N38 -> 1199
B39: DONATION | K39: =500+300+200 -> 1000 | N39: 2050 | O39: =C39+D39+E39+F39+G39+H39+I39+J39+K39+L39+M39+N39 -> 3050
B40: MINISTERS APPRECIATION | O40: =C40+D40+E40+F40+G40+H40+I40+J40+K40+L40+M40+N40 -> 0
B41: PURCHASE OF METHODIST STATIONARY | C41: 160 | D41: 280 | E41: =100+1000 -> 1100 | F41: 70 | I41: =460+40 -> 500 | O41: =C41+D41+E41+F41+G41+H41+I41+J41+K41+L41+M41+N41 -> 2110
B42: DIOCESAN APPEAL | O42: =C42+D42+E42+F42+G42+H42+I42+J42+K42+L42+M42+N42 -> 0
O43: =C43+D43+E43+F43+G43+H43+I43+J43+K43+L43+M43+N43 -> 0
C44: =SUM(C34:C43) -> 160 | D44: =SUM(D34:D43) -> 468 | E44: =SUM(E34:E43) -> 4761 | F44: =SUM(F34:F43) -> 620 | G44: =SUM(G34:G43) -> 5000 | H44: =SUM(H34:H43) -> 3440 | I44: =SUM(I34:I43) -> 500 | J44: =SUM(J34:J43) -> 0 | ... N44: =SUM(N34:N43) -> 7750 | O44: =C44+D44+E44+F44+G44+H44+I44+J44+K44+L44+M44+N44 -> 47235.5
B47: WATER & ECG | I47: 300 | N47: 300 | O47: =C47+D47+E47+F47+G47+H47+I47+J47+K47+L47+M47+N47 -> 600 | P47: REFUND | Q47: 300
B48: RENT | M48: 7200 | O48: =C48+D48+E48+F48+G48+H48+I48+J48+K48+L48+M48+N48 -> 7200 | P48: REFUND | Q48: 2400
B49: SALARY | M49: 1600 | N49: =1300+1300+500 -> 3100 | O49: =C49+D49+E49+F49+G49+H49+I49+J49+K49+L49+M49+N49 -> 4700
B50: ALLOWANCE FOR MINISTER | N50: =1000+1000+500+1000 -> 3500 | O50: =C50+D50+E50+F50+G50+H50+I50+J50+K50+L50+M50+N50 -> 3500 | P50: REFUND | Q50: 1000
O51: =C51+D51+E51+F51+G51+H51+I51+J51+K51+L51+M51+N51 -> 0
C52: =SUM(C47:C51) -> 0 | D52: =SUM(D47:D51) -> 0 | E52: =SUM(E47:E51) -> 0 | F52: =SUM(F47:F51) -> 0 | G52: =SUM(G47:G51) -> 0 | H52: =SUM(H47:H51) -> 0 | I52: =SUM(I47:I51) -> 300 | J52: =SUM(J47:J51) -> 0 | ... O52: =SUM(O47:O51) -> 16000
B55: ASSESSMENT | N55: =8254.49+8241.29 -> 16495.78 | O55: =C55+D55+E55+F55+G55+H55+I55+J55+K55+L55+M55+N55 -> 16495.78
O56: =C56+D56+E56+F56+G56+H56+I56+J56+K56+L56+M56+N56 -> 0
O57: =C57+D57+E57+F57+G57+H57+I57+J57+K57+L57+M57+N57 -> 0
O58: =C58+D58+E58+F58+G58+H58+I58+J58+K58+L58+M58+N58 -> 0
O59: =C59+D59+E59+F59+G59+H59+I59+J59+K59+L59+M59+N59 -> 0
C60: =SUM(C55:C59) -> 0 | D60: =SUM(D55:D59) -> 0 | E60: =SUM(E55:E59) -> 0 | F60: =SUM(F55:F59) -> 0 | G60: =SUM(G55:G59) -> 0 | H60: =SUM(H55:H59) -> 0 | I60: =SUM(I55:I59) -> 0 | J60: =SUM(J55:J59) -> 0 | ... N60: =SUM(N55:N59) -> 16495.78 | O60: =C60+D60+E60+F60+G60+H60+I60+J60+K60+L60+M60+N60 -> 16495.78
O63: =C63+D63+E63+F63+G63+H63+I63+J63+K63+L63+M63+N63 -> 0
O64: =C64+D64+E64+F64+G64+H64+I64+J64+K64+L64+M64+N64 -> 0
O65: =C65+D65+E65+F65+G65+H65+I65+J65+K65+L65+M65+N65 -> 0
O66: =C66+D66+E66+F66+G66+H66+I66+J66+K66+L66+M66+N66 -> 0
O67: =C67+D67+E67+F67+G67+H67+I67+J67+K67+L67+M67+N67 -> 0
D68: =SUM(D63:D67) -> 0 | E68: =SUM(E63:E67) -> 0 | F68: =SUM(F63:F67) -> 0 | G68: =SUM(G63:G67) -> 0 | H68: =SUM(H63:H67) -> 0 | I68: =SUM(I63:I67) -> 0 | J68: =SUM(J63:J67) -> 0 | K68: =SUM(K63:K67) -> 0 | ... N68: =SUM(N63:N67) -> 0 | O68: =C68+D68+E68+F68+G68+H68+I68+J68+K68+L68+M68+N68 -> 0
K71: 0 | O71: =C71+D71+E71+F71+G71+H71+I71+J71+K71+L71+M71+N71 -> 0
O72: =C72+D72+E72+F72+G72+H72+I72+J72+K72+L72+M72+N72 -> 0
O73: =C73+D73+E73+F73+G73+H73+I73+J73+K73+L73+M73+N73 -> 0
O74: =C74+D74+E74+F74+G74+H74+I74+J74+K74+L74+M74+N74 -> 0
O75: =C75+D75+E75+F75+G75+H75+I75+J75+K75+L75+M75+N75 -> 0
C76: =SUM(C71:C75) -> 0 | D76: =SUM(D71:D75) -> 0 | E76: =SUM(E71:E75) -> 0 | F76: =SUM(F71:F75) -> 0 | G76: =SUM(G71:G75) -> 0 | H76: =SUM(H71:H75) -> 0 | I76: =SUM(I71:I75) -> 0 | J76: =SUM(J71:J75) -> 0 | ... N76: =SUM(N71:N75) -> 0 | O76: =C76+D76+E76+F76+G76+H76+I76+J76+K76+L76+M76+N76 -> 0
B79: HARVEST- PROJECT | O79: =C79+D79+E79+F79+G79+H79+I79+J79+K79+L79+M79+N79 -> 0
B80: PURCHASE OF LAND | E80: 200 | L80: =40000+6000 -> 46000 | N80: 20000 | O80: =C80+D80+E80+F80+G80+H80+I80+J80+K80+L80+M80+N80 -> 66200
B81: HARVEST ENVELOPE PRINTING | D81: 300 | G81: 300 | O81: =C81+D81+E81+F81+G81+H81+I81+J81+K81+L81+M81+N81 -> 600
B82: HARVEST BANNER | D82: 250 | E82: 230 | O82: =C82+D82+E82+F82+G82+H82+I82+J82+K82+L82+M82+N82 -> 480
B83: REFRESHMENT | N83: 5300 | O83: =C83+D83+E83+F83+G83+H83+I83+J83+K83+L83+M83+N83 -> 5300
B84: BUILDING PROJECT | C84: 60000 | D84: 46000 | E84: =4000+3000+14000+2500+1500 -> 25000 | F84: =25000+1600 -> 26600 | H84: =10540+32500 -> 43040 | I84: 20000 | N84: 38460 | O84: =C84+D84+E84+F84+G84+H84+I84+J84+K84+L84+M84+N84 -> 259100
B85: FILLING | O85: =C85+D85+E85+F85+G85+H85+I85+J85+K85+L85+M85+N85 -> 0
B86: AUTONOMY | O86: =C86+D86+E86+F86+G86+H86+I86+J86+K86+L86+M86+N86 -> 0
B87: MISCELLANEOUS | E87: 0 | F87: 900 | H87: 300 | J87: 100 | L87: 100 | O87: =C87+D87+E87+F87+G87+H87+I87+J87+K87+L87+M87+N87 -> 1400
B88: WATCHNIGHT SERVICE | O88: =C88+D88+E88+F88+G88+H88+I88+J88+K88+L88+M88+N88 -> 0
B89: CONVENANT SUNDAY | C89: 275 | O89: =C89+D89+E89+F89+G89+H89+I89+J89+K89+L89+M89+N89 -> 275
C90: =SUM(C79:C89) -> 60275 | D90: =SUM(D79:D89) -> 46550 | E90: =SUM(E79:E89) -> 25430 | F90: =SUM(F79:F89) -> 27500 | G90: =SUM(G79:G89) -> 300 | H90: =SUM(H79:H89) -> 43340 | I90: =SUM(I79:I89) -> 20000 | J90: =SUM(J79:J89) -> 100 | ... O90: =SUM(O79:O89) -> 333355
B93: GA RURAL BANK | C93: =7212+1000 -> 8212 | D93: =1600+9635+7387+5360 -> 23982 | E93: =22600+9000+5000 -> 36600 | F93: =15400+10665 -> 26065 | H93: =12360+34890 -> 47250 | I93: =1600+17000+2610 -> 21210 | J93: 1500 | K93: =14720+25000 -> 39720 | L93: 18000 | M93: 14000 | N93: =34880+14505+3890 -> 53275 | O93: =C93+D93+E93+F93+G93+H93+I93+J93+K93+L93+M93+N93 -> 289814
B94: BANK CHARGES | C94: 231.2 | O94: =C94+D94+E94+F94+G94+H94+I94+J94+K94+L94+M94+N94 -> 231.2
B95: REPUBLIC BANK | O95: =C95+D95+E95+F95+G95+H95+I95+J95+K95+L95+M95+N95 -> 0
C96: =SUM(C93:C95) -> 8443.2 | D96: =SUM(D93:D95) -> 23982 | E96: =SUM(E93:E95) -> 36600 | F96: =SUM(F93:F95) -> 26065 | G96: =SUM(G93:G95) -> 0 | H96: =SUM(H93:H95) -> 47250 | I96: =SUM(I93:I95) -> 21210 | J96: =SUM(J93:J95) -> 1500 | ... O96: =SUM(O93:O95) -> 290045.2
O100: =C100+D100+E100+F100+G100+H100+I100+J100+K100+L100+M100+N100 -> 0
O101: =C101+D101+E101+F101+G101+H101+I101+J101+K101+L101+M101+N101 -> 0
O102: =C102+D102+E102+F102+G102+H102+I102+J102+K102+L102+M102+N102 -> 0
O103: =C103+D103+E103+F103+G103+H103+I103+J103+K103+L103+M103+N103 -> 0
O104: =C104+D104+E104+F104+G104+H104+I104+J104+K104+L104+M104+N104 -> 0
C108: =+C15+C22+C29+C44+C90-C84+C93+C94+C95+C52 -> 9778.2 | D108: =+D15+D22+D29+D44+D90-P84+D93+D94+D95+D52 -> 71450 | E108: =+E15+E22+E29+E44+E90-Q84+E93+E94+E95+E52 -> 69791 | F108: =+F15+F22+F29+F44+F90-R84+F93+F94+F95+F52 -> 55485 | G108: =+G15+G22+G29+G44+G90-S84+G93+G94+G95+G52 -> 7750 | H108: =+H15+H22+H29+H44+H90-T84+H93+H94+H95+H52 -> 98330 | I108: =+I15+I22+I29+I44+I90-U84+I93+I94+I95+I52 -> 44210 | J108: =+J15+J22+J29+J44+J90-V84+J93+J94+J95+J52 -> 2900 | K108: =+K15+K22+K29+K44+K90-W84+K93+K94+K95+K52 -> 42220 | ... M108: =+M15+M22+M29+M44+M90-Y84+M93+M94+M95+M52 -> 48536.5 | N108: =+N15+N22+N29+N44+N90-Z84+N93+N94+N95+N52+N60+N68+N76 -> 149480.78 | O108: =+O15+O22+O29+O44+O90+O93+O94+O95 -> 692535.7

Sheet MEMBERS DUES ANALYSIS 17
B1: ASSOCIATION OF METHODIST MENS FELLOWSHIP
B2: KOFORIDUA DIOCESE
B3: WESLEY SOCIETY NSAWAM
B4: MEMBERS DUES CONTRIBUTIONS | C4: 2016 | N4: 2017 | O4: 2017 | R4: 2018 | Z4: 2018
A5: S/N | B5: NAME | C5: OCT | D5: NOV | E5: DEC | F5: JAN | G5: FEB | H5: MAR | I5: APR | J5: MAY | K5: JUNE | L5: JULY | M5: AUG | N5: SEP | O5: OCT | P5: NOV | Q5: DEC | R5: JAN | S5: FEB | T5: MAR | U5: APR | V5: MAY | W5: JUNE | X5: JULY | Y5: AUG | Z5: SEP | AA5: TOTAL | AB5: EXPECTED CONTRIBUTION | AC5: DIFF
C6: GHC | D6: GHC | E6: GHC | F6: GHC | G6: GHC | H6: GHC | I6: GHC | J6: GHC | K6: GHC | L6: GHC | M6: GHC | N6: GHC | O6: GHC | P6: GHC | Q6: GHC | R6: GHC | S6: GHC | T6: GHC | U6: GHC | V6: GHC | W6: GHC | X6: GHC | Y6: GHC | Z6: GHC | AA6: GHC | AB6: GHC | AC6: GHC
A7: 1 | B7: KENNEDY DUODU ACQUAH | C7: 5 | D7: 5 | E7: 5 | F7: 5 | G7: 5 | H7: 5 | I7: 5 | J7: 5 | K7: 5 | L7: 5 | M7: 5 | N7: 5 | O7: 5 | P7: 5 | Q7: 5 | R7: 5 | S7: 5 | T7: 5 | U7: 5 | V7: 5 | W7: 5 | X7: 5 | AA7: =C7+D7+E7+F7+G7+H7+I7+J7+K7+L7+M7+N7+O7+P7+Q7+R7+S7+T7+U7+V7+W7+X7+Y7+Z7 -> 110 | AB7: =5*12 -> 60 | AC7: =AB7-AA7 -> -50
A8: 2 | B8: STEPHEN OBENG ADJEI | C8: 5 | AA8: =C8+D8+E8+F8+G8+H8+I8+J8+K8+L8+M8+N8+O8+P8+Q8+R8+S8+T8+U8+V8+W8+X8+Y8+Z8 -> 5 | AB8: =5*12 -> 60 | AC8: =AB8-AA8 -> 55
A9: 3 | B9: JOSEPH AMIHERE | J9: 5 | K9: 5 | AA9: =C9+D9+E9+F9+G9+H9+I9+J9+K9+L9+M9+N9+O9+P9+Q9+R9+S9+T9+U9+V9+W9+X9+Y9+Z9 -> 10 | AB9: =5*12 -> 60 | AC9: =AB9-AA9 -> 50
A10: 4 | B10: BENJAMIN ATEIMO | C10: 5 | D10: 5 | E10: 5 | F10: 5 | G10: 5 | H10: 5 | I10: 5 | J10: 5 | K10: 5 | L10: 5 | M10: 5 | N10: 5 | O10: 5 | P10: 5 | Q10: 5 | AA10: =C10+D10+E10+F10+G10+H10+I10+J10+K10+L10+M10+N10+O10+P10+Q10+R10+S10+T10+U10+V10+W10+X10+Y10+Z10 -> 75 | AB10: =5*12 -> 60 | AC10: =AB10-AA10 -> -15
A11: 5 | B11: DANIEL ASHEROW | C11: 5 | D11: 5 | E11: 5 | F11: 5 | G11: 5 | H11: 5 | I11: 5 | J11: 5 | K11: 5 | L11: 5 | M11: 5 | AA11: =C11+D11+E11+F11+G11+H11+I11+J11+K11+L11+M11+N11+O11+P11+Q11+R11+S11+T11+U11+V11+W11+X11+Y11+Z11 -> 55 | AB11: =5*12 -> 60 | AC11: =AB11-AA11 -> 5
A12: 6 | B12: ROCKSON-WOOPE THOMAS | C12: 0 | D12: 0 | E12: 0 | F12: 5 | G12: 5 | H12: 5 | I12: 5 | J12: 5 | K12: 5 | L12: 5 | M12: 5 | N12: 5 | O12: 5 | P12: 5 | Q12: 5 | R12: 5 | S12: 5 | T12: 5 | U12: 5 | V12: 5 | AA12: =C12+D12+E12+F12+G12+H12+I12+J12+K12+L12+M12+N12+O12+P12+Q12+R12+S12+T12+U12+V12+W12+X12+Y12+Z12 -> 85 | AB12: =5*9 -> 45 | AC12: =AB12-AA12 -> -40
A13: 7 | B13: ERIC ODURO AMPAABENG | C13: 5 | D13: 5 | E13: 5 | F13: 5 | G13: 5 | H13: 5 | I13: 5 | J13: 5 | K13: 5 | L13: 5 | M13: 5 | N13: 5 | O13: 5 | P13: 5 | Q13: 5 | R13: 5 | S13: 5 | AA13: =C13+D13+E13+F13+G13+H13+I13+J13+K13+L13+M13+N13+O13+P13+Q13+R13+S13+T13+U13+V13+W13+X13+Y13+Z13 -> 85 | AB13: =5*12 -> 60 | AC13: =AB13-AA13 -> -25
A14: 8 | B14: PETER L.Y.N GBORDJOR | C14: 5 | D14: 5 | E14: 5 | F14: 5 | G14: 5 | H14: 5 | I14: 5 | J14: 5 | K14: 5 | L14: 5 | M14: 5 | N14: 5 | O14: 5 | P14: 5 | Q14: 5 | R14: 5 | S14: 5 | T14: 5 | U14: 5 | AA14: =C14+D14+E14+F14+G14+H14+I14+J14+K14+L14+M14+N14+O14+P14+Q14+R14+S14+T14+U14+V14+W14+X14+Y14+Z14 -> 95 | AB14: =5*12 -> 60 | AC14: =AB14-AA14 -> -35
A15: 9 | B15: MICHAEL OKATA | C15: 5 | D15: 5 | E15: 5 | F15: 5 | G15: 5 | H15: 5 | I15: 5 | J15: 5 | K15: 5 | L15: 5 | M15: 5 | N15: 5 | O15: 5 | P15: 5 | Q15: 5 | R15: 5 | S15: 5 | AA15: =C15+D15+E15+F15+G15+H15+I15+J15+K15+L15+M15+N15+O15+P15+Q15+R15+S15+T15+U15+V15+W15+X15+Y15+Z15 -> 85 | AB15: =5*12 -> 60 | AC15: =AB15-AA15 -> -25
A16: 10 | B16: SAMUEL BOSOMPEM | G16: 5 | H16: 5 | I16: 5 | J16: 5 | K16: 5 | L16: 5 | M16: 5 | N16: 5 | O16: 5 | AA16: =C16+D16+E16+F16+G16+H16+I16+J16+K16+L16+M16+N16+O16+P16+Q16+R16+S16+T16+U16+V16+W16+X16+Y16+Z16 -> 45 | AB16: =5*8 -> 40 | AC16: =AB16-AA16 -> -5
A17: 11 | B17: PATRICK NYARKOH | C17: 5 | D17: 5 | E17: 5 | F17: 5 | G17: 5 | H17: 5 | I17: 5 | J17: 5 | K17: 5 | L17: 5 | M17: 5 | N17: 5 | O17: 5 | P17: 5 | Q17: 5 | R17: 5 | AA17: =C17+D17+E17+F17+G17+H17+I17+J17+K17+L17+M17+N17+O17+P17+Q17+R17+S17+T17+U17+V17+W17+X17+Y17+Z17 -> 80 | AB17: =5*12 -> 60 | AC17: =AB17-AA17 -> -20
A18: 12 | B18: DANIEL T NARTEY | C18: 5 | D18: 5 | E18: 5 | F18: 5 | G18: 5 | H18: 5 | I18: 5 | J18: 5 | K18: 5 | L18: 5 | M18: 5 | N18: 5 | O18: 5 | P18: 5 | Q18: 5 | R18: 5 | S18: 5 | T18: 5 | U18: 5 | V18: 5 | W18: 5 | X18: 5 | AA18: =C18+D18+E18+F18+G18+H18+I18+J18+K18+L18+M18+N18+O18+P18+Q18+R18+S18+T18+U18+V18+W18+X18+Y18+Z18 -> 110 | AB18: =5*12 -> 60 | AC18: =AB18-AA18 -> -50
A19: 13 | B19: AGYEMANG BOAKYE | AA19: =C19+D19+E19+F19+G19+H19+I19+J19+K19+L19+M19+N19+O19+P19+Q19+R19+S19+T19+U19+V19+W19+X19+Y19+Z19 -> 0 | AB19: =5*12 -> 60 | AC19: =AB19-AA19 -> 60
A20: 14 | B20: S.D.OWIAFE | C20: 5 | D20: 5 | E20: 5 | F20: 5 | G20: 5 | H20: 5 | I20: 5 | J20: 5 | K20: 5 | L20: 5 | M20: 5 | N20: 5 | O20: 5 | P20: 5 | Q20: 5 | R20: 5 | S20: 5 | AA20: =C20+D20+E20+F20+G20+H20+I20+J20+K20+L20+M20+N20+O20+P20+Q20+R20+S20+T20+U20+V20+W20+X20+Y20+Z20 -> 85 | AB20: =5*12 -> 60 | AC20: =AB20-AA20 -> -25
A21: 15 | B21: SAMUEL NICHOLAS OSEI | AA21: =C21+D21+E21+F21+G21+H21+I21+J21+K21+L21+M21+N21+O21+P21+Q21+R21+S21+T21+U21+V21+W21+X21+Y21+Z21 -> 0 | AB21: =5*12 -> 60 | AC21: =AB21-AA21 -> 60
A22: 16 | B22: PRINCE HENRY AIDOO | C22: 5 | D22: 5 | E22: 5 | F22: 5 | G22: 5 | H22: 5 | I22: 5 | J22: 5 | K22: 5 | L22: 5 | M22: 5 | N22: 5 | O22: 5 | P22: 5 | Q22: 5 | AA22: =C22+D22+E22+F22+G22+H22+I22+J22+K22+L22+M22+N22+O22+P22+Q22+R22+S22+T22+U22+V22+W22+X22+Y22+Z22 -> 75 | AB22: =5*12 -> 60 | AC22: =AB22-AA22 -> -15
A23: 17 | B23: VINCENT ADAMS | C23: 5 | D23: 5 | E23: 5 | F23: 5 | G23: 5 | H23: 5 | I23: 5 | J23: 5 | K23: 5 | L23: 5 | M23: 5 | N23: 5 | O23: 5 | P23: 5 | AA23: =C23+D23+E23+F23+G23+H23+I23+J23+K23+L23+M23+N23+O23+P23+Q23+R23+S23+T23+U23+V23+W23+X23+Y23+Z23 -> 70 | AB23: =5*12 -> 60 | AC23: =AB23-AA23 -> -10
A24: 18 | B24: STEPHEN ODURO | AA24: =C24+D24+E24+F24+G24+H24+I24+J24+K24+L24+M24+N24+O24+P24+Q24+R24+S24+T24+U24+V24+W24+X24+Y24+Z24 -> 0 | AB24: =5*12 -> 60 | AC24: =AB24-AA24 -> 60
A25: 19 | B25: E.J. ARYEETEY | AA25: =C25+D25+E25+F25+G25+H25+I25+J25+K25+L25+M25+N25+O25+P25+Q25+R25+S25+T25+U25+V25+W25+X25+Y25+Z25 -> 0 | AB25: =5*12 -> 60 | AC25: =AB25-AA25 -> 60
A26: 20 | B26: ALEX WILLIAMS | C26: 5 | D26: 5 | E26: 5 | F26: 5 | G26: 5 | H26: 5 | I26: 5 | AA26: =C26+D26+E26+F26+G26+H26+I26+J26+K26+L26+M26+N26+O26+P26+Q26+R26+S26+T26+U26+V26+W26+X26+Y26+Z26 -> 35 | AB26: =5*12 -> 60 | AC26: =AB26-AA26 -> 25
A27: 21 | B27: J.B ESHUN | AA27: =C27+D27+E27+F27+G27+H27+I27+J27+K27+L27+M27+N27+O27+P27+Q27+R27+S27+T27+U27+V27+W27+X27+Y27+Z27 -> 0 | AB27: =5*12 -> 60 | AC27: =AB27-AA27 -> 60
A28: 22 | B28: NANA KWAKYE ABROKWA | AA28: =C28+D28+E28+F28+G28+H28+I28+J28+K28+L28+M28+N28+O28+P28+Q28+R28+S28+T28+U28+V28+W28+X28+Y28+Z28 -> 0 | AB28: =5*12 -> 60 | AC28: =AB28-AA28 -> 60
A29: 23 | B29: EMMANUEL MANTEY | AA29: =C29+D29+E29+F29+G29+H29+I29+J29+K29+L29+M29+N29+O29+P29+Q29+R29+S29+T29+U29+V29+W29+X29+Y29+Z29 -> 0 | AB29: =5*12 -> 60 | AC29: =AB29-AA29 -> 60
A30: 24 | B30: EMMANUEL AMANKWAH | C30: 5 | D30: 5 | E30: 5 | F30: 5 | G30: 5 | H30: 5 | I30: 5 | J30: 5 | K30: 5 | L30: 5 | M30: 5 | N30: 5 | O30: 5 | P30: 5 | AA30: =C30+D30+E30+F30+G30+H30+I30+J30+K30+L30+M30+N30+O30+P30+Q30+R30+S30+T30+U30+V30+W30+X30+Y30+Z30 -> 70 | AB30: =5*12 -> 60 | AC30: =AB30-AA30 -> -10
A31: 25 | B31: ENOCH SARQUAH | C31: 5 | D31: 5 | E31: 5 | F31: 5 | G31: 5 | H31: 5 | I31: 5 | J31: 5 | K31: 5 | L31: 5 | M31: 5 | N31: 5 | O31: 5 | P31: 5 | Q31: 5 | R31: 5 | AA31: =C31+D31+E31+F31+G31+H31+I31+J31+K31+L31+M31+N31+O31+P31+Q31+R31+S31+T31+U31+V31+W31+X31+Y31+Z31 -> 80 | AB31: =5*12 -> 60 | AC31: =AB31-AA31 -> -20
A32: 26 | B32: GILBERT JERRY AMOAH | C32: 5 | D32: 5 | E32: 5 | F32: 5 | G32: 5 | H32: 5 | I32: 5 | J32: 5 | K32: 5 | L32: 5 | M32: 5 | N32: 5 | AA32: =C32+D32+E32+F32+G32+H32+I32+J32+K32+L32+M32+N32+O32+P32+Q32+R32+S32+T32+U32+V32+W32+X32+Y32+Z32 -> 60 | AB32: =5*12 -> 60 | AC32: =AB32-AA32 -> 0
A33: 27 | B33: EMMANUEL AMHED OSAFO | C33: 5 | D33: 5 | E33: 5 | F33: 5 | G33: 5 | H33: 5 | I33: 5 | J33: 5 | K33: 5 | L33: 5 | M33: 5 | N33: 5 | O33: 5 | AA33: =C33+D33+E33+F33+G33+H33+I33+J33+K33+L33+M33+N33+O33+P33+Q33+R33+S33+T33+U33+V33+W33+X33+Y33+Z33 -> 65 | AB33: =5*12 -> 60 | AC33: =AB33-AA33 -> -5
A34: 28 | B34: JOSHUA TETTEY DAWUTEY | F34: 5 | G34: 5 | H34: 5 | I34: 5 | J34: 5 | K34: 5 | L34: 5 | M34: 5 | N34: 5 | O34: 5 | P34: 5 | Q34: 5 | R34: 5 | S34: 5 | T34: 5 | U34: 5 | V34: 5 | W34: 5 | AA34: =C34+D34+E34+F34+G34+H34+I34+J34+K34+L34+M34+N34+O34+P34+Q34+R34+S34+T34+U34+V34+W34+X34+Y34+Z34 -> 90 | AB34: =5*12 -> 60 | AC34: =AB34-AA34 -> -30
A35: 29 | B35: KWESI PREMPEH | AA35: =C35+D35+E35+F35+G35+H35+I35+J35+K35+L35+M35+N35+O35+P35+Q35+R35+S35+T35+U35+V35+W35+X35+Y35+Z35 -> 0 | AB35: =5*12 -> 60 | AC35: =AB35-AA35 -> 60
A36: 30 | B36: ROBERT OFOSU AGYEMANG | C36: 5 | D36: 5 | E36: 5 | F36: 5 | G36: 5 | H36: 5 | I36: 5 | J36: 5 | K36: 5 | L36: 5 | M36: 5 | AA36: =C36+D36+E36+F36+G36+H36+I36+J36+K36+L36+M36+N36+O36+P36+Q36+R36+S36+T36+U36+V36+W36+X36+Y36+Z36 -> 55 | AB36: =5*12 -> 60 | AC36: =AB36-AA36 -> 5
A37: 31 | B37: OSCAR DAPAAH | AA37: =C37+D37+E37+F37+G37+H37+I37+J37+K37+L37+M37+N37+O37+P37+Q37+R37+S37+T37+U37+V37+W37+X37+Y37+Z37 -> 0 | AB37: =5*12 -> 60 | AC37: =AB37-AA37 -> 60
A38: 32 | B38: ANDREWS ADUFUL | C38: 5 | D38: 5 | E38: 5 | F38: 5 | G38: 5 | H38: 5 | I38: 5 | J38: 5 | K38: 5 | L38: 5 | M38: 5 | N38: 5 | O38: 5 | P38: 5 | Q38: 5 | R38: 5 | S38: 5 | T38: 5 | U38: 5 | V38: 5 | AA38: =C38+D38+E38+F38+G38+H38+I38+J38+K38+L38+M38+N38+O38+P38+Q38+R38+S38+T38+U38+V38+W38+X38+Y38+Z38 -> 100 | AB38: =5*12 -> 60 | AC38: =AB38-AA38 -> -40
A39: 33 | B39: SYDNEY SIAW WILLIAMS | R39: 5 | S39: 5 | AA39: =C39+D39+E39+F39+G39+H39+I39+J39+K39+L39+M39+N39+O39+P39+Q39+R39+S39+T39+U39+V39+W39+X39+Y39+Z39 -> 10 | AB39: =5*12 -> 60 | AC39: =AB39-AA39 -> 50
A40: 34 | B40: K.A BEDIAKO | C40: 5 | D40: 5 | E40: 5 | F40: 5 | G40: 5 | H40: 5 | I40: 5 | J40: 5 | K40: 5 | L40: 5 | M40: 5 | N40: 5 | AA40: =C40+D40+E40+F40+G40+H40+I40+J40+K40+L40+M40+N40+O40+P40+Q40+R40+S40+T40+U40+V40+W40+X40+Y40+Z40 -> 60 | AB40: =5*12 -> 60 | AC40: =AB40-AA40 -> 0
A41: 35 | B41: LEONARD PLANG | AA41: =C41+D41+E41+F41+G41+H41+I41+J41+K41+L41+M41+N41+O41+P41+Q41+R41+S41+T41+U41+V41+W41+X41+Y41+Z41 -> 0 | AB41: =5*12 -> 60 | AC41: =AB41-AA41 -> 60
A42: 36 | B42: KOFI ABROKWA | AA42: =C42+D42+E42+F42+G42+H42+I42+J42+K42+L42+M42+N42+O42+P42+Q42+R42+S42+T42+U42+V42+W42+X42+Y42+Z42 -> 0 | AB42: =5*12 -> 60 | AC42: =AB42-AA42 -> 60
A43: 37 | B43: FRANCIS OHENE KWAME | C43: 5 | D43: 5 | E43: 5 | F43: 5 | G43: 5 | H43: 5 | I43: 5 | J43: 5 | K43: 5 | L43: 5 | M43: 5 | N43: 5 | O43: 5 | P43: 5 | Q43: 5 | R43: 5 | AA43: =C43+D43+E43+F43+G43+H43+I43+J43+K43+L43+M43+N43+O43+P43+Q43+R43+S43+T43+U43+V43+W43+X43+Y43+Z43 -> 80 | AB43: =5*12 -> 60 | AC43: =AB43-AA43 -> -20
A44: 38 | B44: AUGUSTUS BLANKSON | C44: 5 | D44: 5 | E44: 5 | F44: 5 | G44: 5 | H44: 5 | I44: 5 | J44: 5 | K44: 5 | L44: 5 | M44: 5 | N44: 5 | AA44: =C44+D44+E44+F44+G44+H44+I44+J44+K44+L44+M44+N44+O44+P44+Q44+R44+S44+T44+U44+V44+W44+X44+Y44+Z44 -> 60 | AB44: =5*12 -> 60 | AC44: =AB44-AA44 -> 0
A45: 39 | B45: JOHN OTENG AGYARKO | C45: 5 | D45: 5 | E45: 5 | F45: 5 | G45: 5 | H45: 5 | I45: 5 | J45: 5 | K45: 5 | L45: 5 | AA45: =C45+D45+E45+F45+G45+H45+I45+J45+K45+L45+M45+N45+O45+P45+Q45+R45+S45+T45+U45+V45+W45+X45+Y45+Z45 -> 50 | AB45: =5*12 -> 60 | AC45: =AB45-AA45 -> 10
A46: 40 | B46: A.M.QUINOO | AA46: =C46+D46+E46+F46+G46+H46+I46+J46+K46+L46+M46+N46+O46+P46+Q46+R46+S46+T46+U46+V46+W46+X46+Y46+Z46 -> 0 | AB46: =5*12 -> 60 | AC46: =AB46-AA46 -> 60
A47: 41 | B47: E.B.ASARE | AA47: =C47+D47+E47+F47+G47+H47+I47+J47+K47+L47+M47+N47+O47+P47+Q47+R47+S47+T47+U47+V47+W47+X47+Y47+Z47 -> 0 | AB47: =5*12 -> 60 | AC47: =AB47-AA47 -> 60
A48: 42 | B48: ASARE MARFO | I48: 5 | J48: 5 | K48: 5 | L48: 5 | M48: 5 | N48: 5 | O48: 5 | P48: 5 | Q48: 5 | R48: 5 | AA48: =C48+D48+E48+F48+G48+H48+I48+J48+K48+L48+M48+N48+O48+P48+Q48+R48+S48+T48+U48+V48+W48+X48+Y48+Z48 -> 50 | AB48: =5*12 -> 60 | AC48: =AB48-AA48 -> 10
A49: 43 | B49: JUSTICE ADDO | AA49: =C49+D49+E49+F49+G49+H49+I49+J49+K49+L49+M49+N49+O49+P49+Q49+R49+S49+T49+U49+V49+W49+X49+Y49+Z49 -> 0 | AB49: =5*12 -> 60 | AC49: =AB49-AA49 -> 60
A50: 44 | B50: EMMANUEL AYESU | C50: 5 | D50: 5 | E50: 5 | F50: 5 | G50: 5 | H50: 5 | I50: 5 | J50: 5 | AA50: =C50+D50+E50+F50+G50+H50+I50+J50+K50+L50+M50+N50+O50+P50+Q50+R50+S50+T50+U50+V50+W50+X50+Y50+Z50 -> 40 | AB50: =5*12 -> 60 | AC50: =AB50-AA50 -> 20
A51: 45 | B51: DANIEL AFAGBEDZI | C51: 5 | D51: 5 | E51: 5 | F51: 5 | G51: 5 | H51: 5 | I51: 5 | J51: 5 | AA51: =C51+D51+E51+F51+G51+H51+I51+J51+K51+L51+M51+N51+O51+P51+Q51+R51+S51+T51+U51+V51+W51+X51+Y51+Z51 -> 40 | AB51: =5*12 -> 60 | AC51: =AB51-AA51 -> 20
A52: 46 | B52: ARHINFUL DONKOR | AA52: =C52+D52+E52+F52+G52+H52+I52+J52+K52+L52+M52+N52+O52+P52+Q52+R52+S52+T52+U52+V52+W52+X52+Y52+Z52 -> 0 | AB52: =5*12 -> 60 | AC52: =AB52-AA52 -> 60
A53: 47 | B53: J.K AFFUL | AA53: =C53+D53+E53+F53+G53+H53+I53+J53+K53+L53+M53+N53+O53+P53+Q53+R53+S53+T53+U53+V53+W53+X53+Y53+Z53 -> 0 | AB53: =5*12 -> 60 | AC53: =AB53-AA53 -> 60
A54: 48 | B54: KRAMPAH FORSON | C54: 5 | D54: 5 | E54: 5 | F54: 5 | G54: 5 | H54: 5 | I54: 5 | J54: 5 | K54: 5 | L54: 5 | M54: 5 | N54: 5 | O54: 5 | P54: 5 | Q54: 5 | R54: 5 | S54: 5 | T54: 5 | U54: 5 | V54: 5 | AA54: =C54+D54+E54+F54+G54+H54+I54+J54+K54+L54+M54+N54+O54+P54+Q54+R54+S54+T54+U54+V54+W54+X54+Y54+Z54 -> 100 | AB54: =5*12 -> 60 | AC54: =AB54-AA54 -> -40
A55: 49 | B55: EDWARD ACQUAH | C55: 5 | D55: 5 | E55: 5 | F55: 5 | G55: 5 | H55: 5 | I55: 5 | J55: 5 | K55: 5 | L55: 5 | M55: 5 | N55: 5 | O55: 5 | P55: 5 | Q55: 5 | AA55: =C55+D55+E55+F55+G55+H55+I55+J55+K55+L55+M55+N55+O55+P55+Q55+R55+S55+T55+U55+V55+W55+X55+Y55+Z55 -> 75 | AB55: =5*12 -> 60 | AC55: =AB55-AA55 -> -15
A56: 50 | B56: KWAME BOADI | C56: 5 | D56: 5 | E56: 5 | F56: 5 | G56: 5 | H56: 5 | I56: 5 | J56: 5 | K56: 5 | L56: 5 | AA56: =C56+D56+E56+F56+G56+H56+I56+J56+K56+L56+M56+N56+O56+P56+Q56+R56+S56+T56+U56+V56+W56+X56+Y56+Z56 -> 50 | AB56: =5*12 -> 60 | AC56: =AB56-AA56 -> 10
A57: 51 | B57: EBENEZER DADZIE | C57: 5 | D57: 5 | E57: 5 | F57: 5 | AA57: =C57+D57+E57+F57+G57+H57+I57+J57+K57+L57+M57+N57+O57+P57+Q57+R57+S57+T57+U57+V57+W57+X57+Y57+Z57 -> 20 | AB57: =5*12 -> 60 | AC57: =AB57-AA57 -> 40
A58: 52 | B58: J.D. TETTEH | AA58: =C58+D58+E58+F58+G58+H58+I58+J58+K58+L58+M58+N58+O58+P58+Q58+R58+S58+T58+U58+V58+W58+X58+Y58+Z58 -> 0 | AB58: =5*12 -> 60 | AC58: =AB58-AA58 -> 60
A59: 53 | B59: JOSEPH ACQUAH | C59: 5 | D59: 5 | E59: 5 | F59: 5 | G59: 5 | H59: 5 | I59: 5 | J59: 5 | K59: 5 | L59: 5 | AA59: =C59+D59+E59+F59+G59+H59+I59+J59+K59+L59+M59+N59+O59+P59+Q59+R59+S59+T59+U59+V59+W59+X59+Y59+Z59 -> 50 | AB59: =5*12 -> 60 | AC59: =AB59-AA59 -> 10
A60: 54 | B60: GEORGE OWUSU AYEH | AA60: =C60+D60+E60+F60+G60+H60+I60+J60+K60+L60+M60+N60+O60+P60+Q60+R60+S60+T60+U60+V60+W60+X60+Y60+Z60 -> 0 | AB60: =5*12 -> 60 | AC60: =AB60-AA60 -> 60
A61: 55 | B61: ASSAH OFORI | AA61: =C61+D61+E61+F61+G61+H61+I61+J61+K61+L61+M61+N61+O61+P61+Q61+R61+S61+T61+U61+V61+W61+X61+Y61+Z61 -> 0 | AB61: =5*12 -> 60 | AC61: =AB61-AA61 -> 60
A62: 56 | B62: SAMUEL EDONU | C62: 5 | D62: 5 | E62: 5 | F62: 5 | G62: 5 | H62: 5 | I62: 5 | J62: 5 | K62: 5 | L62: 5 | AA62: =C62+D62+E62+F62+G62+H62+I62+J62+K62+L62+M62+N62+O62+P62+Q62+R62+S62+T62+U62+V62+W62+X62+Y62+Z62 -> 50 | AB62: =5*12 -> 60 | AC62: =AB62-AA62 -> 10
A63: 57 | B63: S.K. OSEI | AA63: =C63+D63+E63+F63+G63+H63+I63+J63+K63+L63+M63+N63+O63+P63+Q63+R63+S63+T63+U63+V63+W63+X63+Y63+Z63 -> 0 | AB63: =5*12 -> 60 | AC63: =AB63-AA63 -> 60
A64: 58 | B64: ERNEST ATAFUAH | C64: 5 | D64: 5 | E64: 5 | F64: 5 | G64: 5 | H64: 5 | I64: 5 | J64: 5 | K64: 5 | L64: 5 | AA64: =C64+D64+E64+F64+G64+H64+I64+J64+K64+L64+M64+N64+O64+P64+Q64+R64+S64+T64+U64+V64+W64+X64+Y64+Z64 -> 50 | AB64: =5*12 -> 60 | AC64: =AB64-AA64 -> 10
A65: 59 | B65: PAA KWESI DONTWI | C65: 5 | D65: 5 | E65: 5 | F65: 5 | H65: 5 | I65: 5 | J65: 5 | K65: 5 | L65: 5 | M65: 5 | N65: 5 | O65: 5 | P65: 5 | Q65: 5 | AA65: =C65+D65+E65+F65+G65+H65+I65+J65+K65+L65+M65+N65+O65+P65+Q65+R65+S65+T65+U65+V65+W65+X65+Y65+Z65 -> 70 | AB65: =5*12 -> 60 | AC65: =AB65-AA65 -> -10
A66: 60 | B66: D.Y.THOMSON | AA66: =C66+D66+E66+F66+G66+H66+I66+J66+K66+L66+M66+N66+O66+P66+Q66+R66+S66+T66+U66+V66+W66+X66+Y66+Z66 -> 0 | AB66: =5*12 -> 60 | AC66: =AB66-AA66 -> 60
A67: 61 | B67: GODFRED AHINKORA | AA67: =C67+D67+E67+F67+G67+H67+I67+J67+K67+L67+M67+N67+O67+P67+Q67+R67+S67+T67+U67+V67+W67+X67+Y67+Z67 -> 0 | AB67: =5*12 -> 60 | AC67: =AB67-AA67 -> 60
A68: 62 | B68: RICHARD ANKRAH | C68: 5 | D68: 5 | E68: 5 | F68: 5 | G68: 5 | H68: 5 | I68: 5 | J68: 5 | K68: 5 | AA68: =C68+D68+E68+F68+G68+H68+I68+J68+K68+L68+M68+N68+O68+P68+Q68+R68+S68+T68+U68+V68+W68+X68+Y68+Z68 -> 45 | AB68: =5*12 -> 60 | AC68: =AB68-AA68 -> 15
A69: 63 | B69: ASAMOAH OBENG NYARKOH | C69: 5 | D69: 5 | E69: 5 | F69: 5 | G69: 5 | H69: 5 | I69: 5 | J69: 5 | K69: 5 | AA69: =C69+D69+E69+F69+G69+H69+I69+J69+K69+L69+M69+N69+O69+P69+Q69+R69+S69+T69+U69+V69+W69+X69+Y69+Z69 -> 45 | AB69: =5*12 -> 60 | AC69: =AB69-AA69 -> 15
A70: 64 | B70: ALFRED ADJEI | L70: 5 | M70: 5 | N70: 5 | O70: 5 | P70: 5 | Q70: 5 | AA70: =C70+D70+E70+F70+G70+H70+I70+J70+K70+L70+M70+N70+O70+P70+Q70+R70+S70+T70+U70+V70+W70+X70+Y70+Z70 -> 30 | AB70: =5*12 -> 60 | AC70: =AB70-AA70 -> 30
A71: 65 | B71: GEORGE OFFEI GHARTEY | L71: 5 | M71: 5 | N71: 5 | O71: 5 | P71: 5 | Q71: 5 | AA71: =C71+D71+E71+F71+G71+H71+I71+J71+K71+L71+M71+N71+O71+P71+Q71+R71+S71+T71+U71+V71+W71+X71+Y71+Z71 -> 30 | AB71: =5*12 -> 60 | AC71: =AB71-AA71 -> 30
A72: 66 | B72: KURTIS OSAFO SARKODIE | R72: 5 | AA72: =C72+D72+E72+F72+G72+H72+I72+J72+K72+L72+M72+N72+O72+P72+Q72+R72+S72+T72+U72+V72+W72+X72+Y72+Z72 -> 5 | AB72: =5*12 -> 60 | AC72: =AB72-AA72 -> 55
A73: 67 | AA73: =C73+D73+E73+F73+G73+H73+I73+J73+K73+L73+M73+N73+O73+P73+Q73+R73+S73+T73+U73+V73+W73+X73+Y73+Z73 -> 0 | AB73: =5*12 -> 60 | AC73: =AB73-AA73 -> 60
A74: 68 | AA74: =C74+D74+E74+F74+G74+H74+I74+J74+K74+L74+M74+N74+O74+P74+Q74+R74+S74+T74+U74+V74+W74+X74+Y74+Z74 -> 0 | AB74: =5*12 -> 60 | AC74: =AB74-AA74 -> 60
A75: 69 | AA75: =C75+D75+E75+F75+G75+H75+I75+J75+K75+L75+M75+N75+O75+P75+Q75+R75+S75+T75+U75+V75+W75+X75+Y75+Z75 -> 0
A76: 70 | AA76: =SUM(AA7:AA69) -> 2570 | AB76: =SUM(AB7:AB69) -> 3745 | AC76: =SUM(AC7:AC69) -> 1175

Sheet TITHE
A1: =+Expend!A1 -> THE METHODIST CHURCH GHANA
A2: =+Expend!A2 -> ACCRA NORTH DIOCESE
A3: =+Expend!A3 -> GA SUB-URBAN CIRCUIT
A4: =+Expend!A4 -> HEBRON SOCIETY
A5: =+Expend!A5 -> STATEMENT OF ACCOUNT FOR THE PERIOD 1ST JANUARY,2024 TO 31ST DECEMBER,2024
B6: TITHE | C6: 2023 | D6: 2023 | E6: 2023 | F6: 2023 | G6: 2023 | H6: 2023 | I6: 2023 | J6: 2023 | K6: 2024 | L6: 2024 | M6: 2024 | N6: 2024 | O6: 2024 | P6: 2024 | Q6: 2024 | R6: 2024 | S6: 2024 | T6: 2024 | U6: 2024 | V6: 2024 | W6: 2024 | X6: 2024 | Y6: 2024 | Z6: 2024
A7: S/N | B7: NAME | C7: MAY | D7: JUN | E7: JUL | F7: AUG | G7: SEP | H7: OCT | I7: NOV | J7: DEC | K7: JAN | L7: FEB | M7: MAR | N7: APR | O7: MAY | P7: JUN | Q7: JUL | R7: AUG | S7: SEP | T7: OCT | U7: NOV | V7: DEC | W7: JAN | X7: FEB | Y7: MAR | Z7: APR | AA7: TOTAL
C8: GHC | D8: GHC | E8: GHC | F8: GHC | G8: GHC | H8: GHC | I8: GHC | J8: GHC | K8: GHC | L8: GHC | M8: GHC | N8: GHC | O8: GHC | P8: GHC | Q8: GHC | R8: GHC | S8: GHC | T8: GHC | U8: GHC | V8: GHC | W8: GHC | X8: GHC | Y8: GHC | Z8: GHC | AA8: GHC
A9: 1 | B9: GOLDA KAMMASSAH | K9: 50 | L9: 50 | M9: 50 | N9: 50 | O9: 50 | P9: 50 | Q9: 50 | R9: 50 | S9: 50 | T9: 50 | U9: 50 | AA9: =SUM(C9:Z9) -> 550
A10: 2 | B10: ERICA DONKOR | K10: 150 | L10: 60 | M10: 60 | N10: 100 | O10: 100 | P10: 100 | Q10: 100 | R10: 100 | S10: 100 | T10: 100 | U10: 100 | V10: 120 | AA10: =SUM(C10:Z10) -> 1190
A11: 3 | B11: CHARLES FRIMPONG | K11: 150 | L11: 150 | M11: 150 | N11: 150 | O11: 150 | P11: 150 | Q11: 150 | R11: 150 | S11: 150 | T11: 150 | U11: 100 | AA11: =SUM(C11:Z11) -> 1600
A12: 4 | B12: EMMANUEL ASADU | K12: 500 | L12: 500 | M12: 500 | N12: 500 | O12: 500 | P12: 500 | Q12: 500 | R12: 600 | S12: 500 | T12: 500 | U12: 500 | AA12: =SUM(C12:Z12) -> 5600
A13: 5 | B13: JOANA WADDIE | K13: 60 | L13: 60 | M13: 60 | N13: 60 | O13: 60 | P13: 60 | Q13: 60 | R13: 60 | S13: 60 | T13: 70 | U13: 60 | V13: 60 | AA13: =SUM(C13:Z13) -> 730
A14: 6 | B14: DORIS MARFO | K14: 250 | L14: 220 | M14: 230 | N14: 250 | O14: 240 | P14: 250 | Q14: 250 | R14: 250 | S14: 250 | T14: 250 | U14: 250 | AA14: =SUM(C14:Z14) -> 2690
A15: 7 | B15: GLORIA ASARE | K15: 200 | L15: 1100 | M15: 1600 | N15: 1100 | O15: 1100 | P15: 1100 | Q15: 1100 | R15: 1100 | S15: 1100 | T15: 1100 | U15: 1100 | AA15: =SUM(C15:Z15) -> 11700
A16: 8 | B16: PATRICK NYARKOH | K16: 1600 | L16: 1600 | M16: 1600 | N16: 1600 | O16: 1600 | P16: 1600 | Q16: 1600 | R16: 1600 | S16: 1600 | T16: 1600 | U16: 1850 | AA16: =SUM(C16:Z16) -> 17850
A17: 9 | B17: DORIS NYARKOH | K17: 660 | L17: 660 | M17: 660 | N17: 660 | O17: 660 | P17: 660 | Q17: 660 | R17: 660 | S17: 800 | T17: 800 | U17: 800 | AA17: =SUM(C17:Z17) -> 7680
A18: 10 | B18: JUSTINA DADZIE | K18: 100 | L18: 100 | M18: 100 | N18: 100 | O18: 100 | P18: 100 | Q18: 100 | R18: 100 | S18: 100 | T18: 100 | U18: 100 | AA18: =SUM(C18:Z18) -> 1100
A19: 11 | B19: MACHELLE YAMOAH | K19: 265 | L19: 265 | M19: 265 | N19: 265 | O19: 535 | P19: 265 | Q19: 670 | R19: 400 | S19: 400 | T19: 400 | U19: 400 | V19: 400 | AA19: =SUM(C19:Z19) -> 4530
A20: 12 | B20: EDWARD QUARNOR | K20: 170 | L20: 200 | M20: 160 | N20: 150 | O20: 160 | P20: 180 | Q20: 150 | R20: 100 | S20: 130 | T20: 200 | U20: 150 | AA20: =SUM(C20:Z20) -> 1750
A21: 13 | B21: SETH ASARE | K21: 60 | L21: 60 | M21: 60 | N21: 60 | O21: 60 | P21: 60 | Q21: 60 | R21: 60 | S21: 60 | T21: 60 | U21: 60 | AA21: =SUM(C21:Z21) -> 660
A22: 14 | B22: JULIANA ASADU | K22: 350 | L22: 350 | M22: 350 | N22: 350 | O22: 353 | P22: 353 | Q22: 350 | R22: 350 | S22: 400 | T22: 370 | U22: 350 | V22: 355 | AA22: =SUM(C22:Z22) -> 4281
A23: 15 | B23: PHYLLIS NYARKO | K23: 50 | L23: 70 | M23: =60+100+50 -> 210 | N23: 100 | O23: 50 | P23: 100 | Q23: 50 | R23: 100 | S23: 100 | T23: 100 | AA23: =SUM(C23:Z23) -> 930
A24: 16 | B24: JEMIMA AFRIYIE ASAMOAH | K24: 100 | L24: 100 | M24: 100 | N24: 100 | O24: 100 | P24: 100 | Q24: 100 | R24: 100 | S24: 100 | T24: 300 | U24: 300 | AA24: =SUM(C24:Z24) -> 1500
A25: 17 | B25: PHILIP OPOKU | G25: 100 | H25: 100 | I25: 100 | J25: 100 | K25: 100 | L25: 100 | M25: 100 | AA25: =SUM(C25:Z25) -> 700
A26: 18 | B26: FELIX YAMOAH | E26: 100 | F26: 100 | G26: 100 | H26: 100 | I26: 100 | J26: 100 | K26: 150 | L26: 150 | M26: 150 | N26: 150 | O26: 150 | P26: 150 | Q26: 150 | R26: 150 | AA26: =SUM(C26:Z26) -> 1800
A27: 19 | B27: PETER ASARE | J27: 400 | K27: 400 | L27: 400 | M27: 400 | N27: 400 | O27: 400 | P27: 400 | Q27: 400 | R27: 400 | S27: 400 | T27: 400 | U27: 400 | AA27: =SUM(C27:Z27) -> 4800
A28: 20 | B28: ASANTEWA MARINA | J28: 50 | K28: 20 | L28: 50 | M28: 40 | N28: 50 | O28: 50 | P28: 50 | Q28: 50 | R28: 50 | S28: 50 | T28: 50 | U28: 50 | V28: 100 | AA28: =SUM(C28:Z28) -> 660
A29: 21 | B29: NO NAME | K29: 55 | P29: 0 | AA29: =SUM(C29:Z29) -> 55
A30: 22 | B30: PHILOMINA AGYEKUM | K30: 20 | AA30: =SUM(C30:Z30) -> 20
A31: 23 | B31: AMA TUTUA | K31: 1505 | L31: 1520 | M31: 1520 | N31: 1520 | O31: 1600 | P31: 1700 | Q31: 1000 | R31: 1750 | S31: 1800 | AA31: =SUM(C31:Z31) -> 13915
A32: 24 | B32: SAMILIA ASANTE | K32: 30 | AA32: =SUM(C32:Z32) -> 30
A33: 25 | B33: SAMUEL ASARE | K33: 150 | L33: 150 | M33: 150 | N33: 150 | O33: 350 | P33: 180 | Q33: 180 | R33: 360 | S33: 360 | T33: 360 | U33: 360 | AA33: =SUM(C33:Z33) -> 2750
A34: 26 | B34: OBODIA ADJA | AA34: =SUM(C34:Z34) -> 0
A35: 27 | B35: ESTHER ASARE | J35: 10 | K35: 10 | L35: 20 | M35: 20 | N35: 20 | O35: 20 | P35: 20 | Q35: 20 | R35: 20 | S35: 20 | T35: 20 | U35: 20 | V35: 20 | AA35: =SUM(C35:Z35) -> 240
A36: 28 | B36: KATE ANKRAH | K36: 40 | L36: 40 | M36: 40 | N36: 40 | O36: 40 | P36: 40 | Q36: 40 | R36: 40 | S36: 40 | T36: 40 | U36: 40 | V36: 40 | AA36: =SUM(C36:Z36) -> 480
A37: 29 | B37: COMFORT BENABE | K37: 60 | AA37: =SUM(C37:Z37) -> 60
A38: 30 | B38: UNKNOWN | AA38: =SUM(C38:Z38) -> 0
A39: 31 | B39: VICTORIA OPOKU | H39: 20 | I39: 20 | J39: 20 | K39: 20 | L39: 20 | M39: 20 | N39: 20 | O39: 20 | P39: 20 | Q39: 20 | R39: 20 | S39: 20 | AA39: =SUM(C39:Z39) -> 240
A40: 32 | B40: ALFRED OKYERE | H40: 100 | I40: 100 | J40: 100 | K40: 100 | AA40: =SUM(C40:Z40) -> 400
A41: 33 | B41: REBECCA QUARSHIE | H41: 10 | I41: 10 | J41: 10 | K41: 10 | L41: 10 | M41: 10 | N41: 10 | O41: 10 | P41: 10 | Q41: 10 | R41: 10 | S41: 10 | T41: 10 | U41: 10 | V41: 10 | AA41: =SUM(C41:Z41) -> 150
A42: 34 | B42: JOHN BUYAN KAMASSAH | AA42: =SUM(C42:Z42) -> 0
A43: 35 | B43: MABEL MANUFIE | E43: 50 | F43: 50 | G43: 50 | H43: 50 | I43: 50 | J43: 50 | K43: 50 | L43: 50 | M43: 50 | N43: 50 | O43: 50 | P43: 50 | Q43: 50 | R43: 50 | S43: 50 | T43: 50 | U43: 50 | V43: 50 | AA43: =SUM(C43:Z43) -> 900
A44: 36 | B44: AGNES FRIMPONG | N44: 10 | O44: 10 | AA44: =SUM(C44:Z44) -> 20
A45: 37 | B45: MILLICENT ANAKWA AGYEMENG | K45: 20 | L45: 20 | M45: 20 | AA45: =SUM(C45:Z45) -> 60
A46: 38 | B46: DOMINIC ANAKWA | AA46: =SUM(C46:Z46) -> 0
A47: 39 | B47: VIVIAN ASARE | AA47: =SUM(C47:Z47) -> 0
A48: 40 | B48: EVA COMMODORE | AA48: =SUM(C48:Z48) -> 0
A49: 41 | B49: VIDA BOATENG | AA49: =SUM(C49:Z49) -> 0
A50: 42 | B50: PRINCE YAW OKYERE | AA50: =SUM(C50:Z50) -> 0
A51: 43 | B51: SALOMEY OKYERE | AA51: =SUM(C51:Z51) -> 0
A52: 44 | B52: FRANCIS ASARE | AA52: =SUM(C52:Z52) -> 0
A53: 45 | B53: VICTORIA ELLA LAWSON | AA53: =SUM(C53:Z53) -> 0
A54: 46 | B54: ETHEL AMENU | AA54: =SUM(C54:Z54) -> 0
A55: 47 | B55: RUTH AMANKWAAH | AA55: =SUM(C55:Z55) -> 0
A56: 48 | B56: COLLINS OFORI | AA56: =SUM(C56:Z56) -> 0
A57: 49 | B57: CELESTINE OSEI | AA57: =SUM(C57:Z57) -> 0
... A59: 51 | B59: JOSEPH ANINNG | AA59: =SUM(C59:Z59) -> 0
A60: 52 | B60: ANASTASIA ASARE | K60: 50 | L60: 50 | M60: 50 | N60: 50 | O60: 50 | P60: 50 | Q60: 50 | R60: 50 | S60: 50 | T60: 50 | U60: 50 | AA60: =SUM(C60:Z60) -> 550
A61: 53 | B61: JACOB KWESI MENSAH | AA61: =SUM(C61:Z61) -> 0
A62: 54 | B62: KOFI AZASU | P62: 50 | AA62: =SUM(C62:Z62) -> 50
A63: 55 | B63: PATRICK OFOSU | O63: 70 | P63: 70 | Q63: 70 | R63: 70 | S63: 70 | T63: 70 | U63: 70 | AA63: =SUM(C63:Z63) -> 490
A64: 56 | B64: LYDIA NII BOI | O64: 20 | P64: 30 | Q64: 50 | R64: 50 | S64: 20 | T64: 20 | U64: 20 | AA64: =SUM(C64:Z64) -> 210
A65: 57 | B65: DAVID ANKOMAH | O65: 600 | P65: 600 | Q65: 600 | R65: 600 | AA65: =SUM(C65:Z65) -> 2400
A66: 58 | B66: AZIESO JACOB | P66: 20 | Q66: 20 | R66: 20 | S66: 20 | T66: 20 | U66: 20 | V66: 10 | AA66: =SUM(C66:Z66) -> 130
A67: 59 | B67: STEPHEN AMOFA | R67: 50 | AA67: =SUM(C67:Z67) -> 50
A68: 60 | B68: REBECCA ANKAN | S68: 0 | T68: 20 | U68: 20 | AA68: =SUM(C68:Z68) -> 40
A69: 61 | B69: PEPERTUAL ANAMAN | T69: 120 | AA69: =SUM(C69:Z69) -> 120
A70: 62 | B70: V.REV. KOBINA ANAMAN | T70: 400 | U70: 400 | AA70: =SUM(C70:Z70) -> 800
A71: 63 | B71: EBENEZER KONADU | U71: 100 | AA71: =SUM(C71:Z71) -> 100
A72: 64 | B72: REGINA KWARFO | U72: 20 | AA72: =SUM(C72:Z72) -> 20
A73: 65 | B73: ALICE NYELLANOUG | U73: 50 | AA73: =SUM(C73:Z73) -> 50
A74: 66 | B74: EDWAD SAKYI MANTEY | U74: 50 | AA74: =SUM(C74:Z74) -> 50
A75: 67 | B75: REGINA OWUSUA | U75: 30 | AA75: =SUM(C75:Z75) -> 30
C76: =SUM(C9:C33) -> 0 | D76: =SUM(D9:D33) -> 0 | E76: =SUM(E9:E75) -> 150 | F76: =SUM(F9:F75) -> 150 | G76: =SUM(G9:G75) -> 250 | H76: =SUM(H9:H75) -> 380 | I76: =SUM(I9:I75) -> 380 | J76: =SUM(J9:J75) -> 840 | K76: =SUM(K9:K75) -> 7505 | L76: =SUM(L9:L75) -> 8125 | ... AA76: =SUM(AA9:AA75) -> 96711
AA77: =+'Rec & Pmt'!B17 -> 96711
AA78: =+AA77-AA76 -> 0

Sheet CASH BOOK
A1: =+TITHE!A1:N1 -> THE METHODIST CHURCH GHANA
A2: =+TITHE!A2:N2 -> ACCRA NORTH DIOCESE
A3: =+TITHE!A3:N3 -> GA SUB-URBAN CIRCUIT
A4: =+TITHE!A4:N4 -> HEBRON SOCIETY
A5: CASHBOOK
A6: RECEIPTS | H6: PAYMENTS
A7: DATE | B7: DETAILS | C7: FOLIO | D7: REPUBLIC | E7: GA RURAL | F7: CASH | H7: DATE | I7: DETAILS | J7: FOLIO | K7: REPUBLIC | L7: GA RURAL | M7: CASH
D8: GHC | E8: GHC | F8: GHC | K8: GHC | L8: GHC | M8: GHC
A9: 44470 | B9: Bal B/F | D9: =+'Rec & Pmt'!C76 -> 200 | E9: =+'Rec & Pmt'!C75 -> 52205.88 | F9: =+'Rec & Pmt'!C77 -> 6557.7 | H9: 44470 | I9: Bal B/F
B10: JANUARY | E10: =7212.6+1000 -> 8212.6 | F10: ='weekly income statement'!C68 -> 6134.8 | I10: JANUARY | L10: =+Expend!C84+231.2 -> 60231.2 | M10: =Expend!C108-231.2 -> 9547
B11: FEBRUARY | E11: =1600+9635+5360+7387 -> 23982 | F11: ='weekly income statement'!D68 -> 24320.2 | I11: FEBRUARY | L11: =+Expend!D84 -> 46000 | M11: =Expend!D108-L11 -> 25450
B12: MARCH | E12: =22600+9000+5000 -> 36600 | F12: ='weekly income statement'!E68 -> 63348.9 | I12: MARCH | L12: =+Expend!E84-4000-3000-4000 -> 14000 | M12: =Expend!E108-L12 -> 55791
B13: APRIL | E13: 26065 | F13: ='weekly income statement'!F68 -> 26461.6 | I13: APRIL | L13: =+Expend!G89-Expend!G84+25000+1600 -> 26600 | M13: =Expend!F108-L13 -> 28885
B14: MAY | F14: ='weekly income statement'!G68 -> 17574.3 | I14: MAY | M14: =Expend!G108-L14 -> 7750
B15: JUNE | E15: =12360+34890 -> 47250 | F15: ='weekly income statement'!H68 -> 54094.5 | I15: JUNE | L15: =+Expend!H84+1000 -> 44040 | M15: =Expend!H108-L15 -> 54290
B16: JULY | E16: =1600+2610+17000 -> 21210 | F16: ='weekly income statement'!I68 -> 14344.8 | I16: JULY | L16: =+Expend!I84 -> 20000 | M16: =Expend!I108-L16 -> 24210
B17: AUGUST | E17: 1500 | F17: ='weekly income statement'!J68 -> 7404.5 | I17: AUGUST | L17: =+Expend!J84 -> 0 | M17: =Expend!J108-L17 -> 2900
B18: SEPTEMBER | E18: 39720 | F18: ='weekly income statement'!K68 -> 44106.6 | I18: SEPTEMBER | M18: =Expend!K108 -> 42220
B19: OCTOBER | E19: 18000 | F19: ='weekly income statement'!L68 -> 13859.3 | I19: OCTOBER | L19: =+Expend!L80-6000 -> 40000 | M19: =Expend!L108-L19 -> 25100
B20: NOVEMBER | E20: 14000 | F20: ='weekly income statement'!M68 -> 50169.4 | I20: NOVEMBER | M20: =Expend!M108 -> 48536.5
B21: DECEMBER | E21: =34880+14505+3890 -> 53275 | F21: ='weekly income statement'!N68 -> 75147.7 | I21: DECEMBER | L21: =20000+8254.49+8241.29+38460+2020 -> 76975.78 | M21: =Expend!N108-L21 -> 72505
D25: =SUM(D9:D24) -> 200 | E25: =SUM(E9:E24) -> 342020.48 | F25: =SUM(F9:F24) -> 403524.3 | K25: =SUM(K9:K24) -> 0 | L25: =SUM(L9:L24) -> 327846.98 | M25: =SUM(M9:M24) -> 397184.5
H26: CLOSING BALANCE | K26: =D25-K25 -> 200 | L26: =E25-L25 -> 14173.5 | M26: =F25-M25 -> 6339.8
K28: 200 | M28: =K28*L28 -> 0
K29: 100 | M29: =K29*L29 -> 0
K30: 50 | M30: =K30*L30 -> 0
K31: 20 | M31: =K31*L31 -> 0
K32: 10 | M32: =K32*L32 -> 0
K33: 5 | M33: =K33*L33 -> 0
K34: 2 | M34: =K34*L34 -> 0
K35: 1 | M35: =K35*L35 -> 0
M36: =SUM(M28:M35) -> 0
M37: =12160+7802 -> 19962
M38: =+M36-M37 -> -19962
M39: =SUM(M37:M38) -> 0
L41: 50000
L42: -25000
L43: -1640
L44: =SUM(L41:L43) -> 23360
L45: -3080

Sheet ASSETS
A1: TRINITY METHODIST CHURCH
A2: FIXED ASSETS REGISTER
A3: S/N | B3: DATE | C3: DETAILS | D3: QTY | E3: VALUE | F3: REMARKS
A4: 1 | C4: PLASTIC CHAIRS | D4: 20 | E4: 540 | F4: CHURCH
A5: 2 | C5: PLASTIC CHAIRS | D5: 20 | E5: 540 | F5: CHURCH
A6: 3 | C6: KONKA | D6: 1 | E6: 550 | F6: CHURCH
A7: 4 | C7: SPEAKER | D7: 1 | E7: 1200 | F7: CHURCH
A8: 5 | C8: CORDLESS MIC | D8: 2 | F8: DONATED
A9: 6 | C9: PULPIT | D9: 1 | E9: 500 | F9: CHURCH
A10: 7 | C10: LAND | D10: 2PLOTS | E10: 46450 | F10: CHURCH
A11: 8 | C11: FILLING | E11: 35740 | F11: CHURCH
A12: 9 | C12: CANOPY | D12: 1 | E12: 2500 | F12: DONATED
A13: 10 | C13: PLASTIC CHAIRS | D13: 42 | F13: DONATED
A14: 11 | C14: TAMBOURINES | D14: 2 | F14: DONATED
A15: 12 | C15: SPEAKER | D15: 1 | F15: DONATED
A16: 13 | C16: CORDED MIC | D16: 1 | F16: DONATED
A17: 14 | C17: TABLE | D17: 1 | F17: DONATED
A18: 15 | C18: OFFERING BOWL | D18: 1 | F18: DONATED
A19: 16 | C19: KEYBOARD | D19: 1 | E19: 5000 | F19: DONATED
C20: INDUSTRIAL FANS | D20: 2 | E20: 3000
C21: STANDING FAN | D21: 1 | E21: 550
C22: DRUMSET | D22: 1 | E22: 3600
C23: MICRO PHONES | D23: 3 | F23: DONATED
C24: CHAIRS | D24: 40 | E24: 3440

Sheet RETURNS FOR CIRCUIT
A1: THE METHODIST CHURCH GHANA
A2: NORTHERN ACCRA DIOCESE
A3: GA-SUB URBAN CIRCUIT
A4: HEBRON SOCIETY
A6: SOCIETY REVENUE ANALYSIS SHEET | C6: SOCIETY CODE | F6: MONTH | G6: JANUARY
A7: DATE : | F7: WEEK
A9: INCOME SOURCE | B9: NORMAL SERVICE | C9: WEEKDAY | D9: TOTAL | E9: CONNEX | F9: DIOCESE | G9: CIRCUIT | H9: TOTAL ASSESSMENT | I9: SOCIETY
E10: 0.4 | F10: 0.09 | G10: 0.13 | I10: 0.38
B11: GHS | C11: GHS | D11: GHS | E11: GHS | F11: GHS | G11: GHS | H11: GHS | I11: GHS
A12: TITHE | B12: ='RECEIPTS AND PAYMENT ANANLYSIS'!B9 -> 2085 | C12: ='RECEIPTS AND PAYMENT ANANLYSIS'!B10 -> 482.6 | D12: =SUM(B12:C12) -> 2567.6 | E12: =D12*$E$10 -> 1027.04 | F12: =D12*$F$10 -> 231.084 | G12: =D12*$G$10 -> 333.788 | H12: =SUM(E12:G12) -> 1591.912 | I12: =D12*$I$10 -> 975.688
A13: OFFERING | B13: ='RECEIPTS AND PAYMENT ANANLYSIS'!B8 -> 2682.2 | D13: =SUM(B13:C13) -> 2682.2 | E13: =D13*$E$10 -> 1072.88 | F13: =D13*$F$10 -> 241.398 | G13: =D13*$G$10 -> 348.686 | H13: =SUM(E13:G13) -> 1662.964 | I13: =D13*$I$10 -> 1019.236
A14: KOFI & AMA | D14: =SUM(B14:C14) -> 0 | E14: =D14*$E$10 -> 0 | F14: =D14*$F$10 -> 0 | G14: =D14*$G$10 -> 0 | H14: =SUM(E14:G14) -> 0 | I14: =D14*$I$10 -> 0
A15: THANKSOFFERING | B15: ='RECEIPTS AND PAYMENT ANANLYSIS'!B11 -> 350 | D15: =SUM(B15:C15) -> 350 | E15: =D15*$E$10 -> 140 | F15: =D15*$F$10 -> 31.5 | G15: =D15*$G$10 -> 45.5 | H15: =SUM(E15:G15) -> 217 | I15: =D15*$I$10 -> 133
A16: SO MU BI | D16: =SUM(B16:C16) -> 0 | E16: =D16*$E$10 -> 0 | F16: =D16*$F$10 -> 0 | G16: =D16*$G$10 -> 0 | H16: =SUM(E16:G16) -> 0 | I16: =D16*$I$10 -> 0
A17: SPECIAL OFFERING | B17: ='RECEIPTS AND PAYMENT ANANLYSIS'!B14 -> 0 | D17: =SUM(B17:C17) -> 0 | E17: =D17*$E$10 -> 0 | F17: =D17*$F$10 -> 0 | G17: =D17*$G$10 -> 0 | H17: =SUM(E17:G17) -> 0 | I17: =D17*$I$10 -> 0
A18: GRANDTOTAL | B18: =SUM(B12:B17) -> 5117.2 | C18: =SUM(C12:C17) -> 482.6 | D18: =SUM(D12:D17) -> 5599.8 | E18: =SUM(E12:E17) -> 2239.92 | F18: =SUM(F12:F17) -> 503.982 | G18: =SUM(G12:G17) -> 727.974 | H18: =SUM(H12:H17) -> 3471.876 | I18: =SUM(I12:I17) -> 2127.924
A21: THE METHODIST CHURCH GHANA
A22: NORTHERN ACCRA DIOCESE
A23: GA-SUB URBAN CIRCUIT
A24: HEBRON SOCIETY
A26: SOCIETY REVENUE ANALYSIS SHEET | C26: SOCIETY CODE | F26: MONTH | G26: FEBRUARY
A27: DATE : | F27: WEEK
A29: INCOME SOURCE | B29: NORMAL SERVICE | C29: WEEKDAY | D29: TOTAL | E29: CONNEX | F29: DIOCESE | G29: CIRCUIT | H29: TOTAL ASSESSMENT | I29: SOCIETY
E30: 0.4 | F30: 0.09 | G30: 0.13 | I30: 0.38
B31: GHS | C31: GHS | D31: GHS | E31: GHS | F31: GHS | G31: GHS | H31: GHS | I31: GHS
A32: TITHE | B32: ='RECEIPTS AND PAYMENT ANANLYSIS'!C9 -> 9010 | C32: ='RECEIPTS AND PAYMENT ANANLYSIS'!C10 -> 260 | D32: =SUM(B32:C32) -> 9270 | E32: =D32*$E$10 -> 3708 | F32: =D32*$F$10 -> 834.3 | G32: =D32*$G$10 -> 1205.1 | H32: =SUM(E32:G32) -> 5747.4 | I32: =D32*$I$10 -> 3522.6
A33: OFFERING | B33: ='RECEIPTS AND PAYMENT ANANLYSIS'!C8 -> 2715.3 | D33: =SUM(B33:C33) -> 2715.3 | E33: =D33*$E$10 -> 1086.12 | F33: =D33*$F$10 -> 244.377 | G33: =D33*$G$10 -> 352.989 | H33: =SUM(E33:G33) -> 1683.486 | I33: =D33*$I$10 -> 1031.814
A34: KOFI & AMA | D34: =SUM(B34:C34) -> 0 | E34: =D34*$E$10 -> 0 | F34: =D34*$F$10 -> 0 | G34: =D34*$G$10 -> 0 | H34: =SUM(E34:G34) -> 0 | I34: =D34*$I$10 -> 0
A35: THANKSOFFERING | B35: ='RECEIPTS AND PAYMENT ANANLYSIS'!C11 -> 200 | D35: =SUM(B35:C35) -> 200 | E35: =D35*$E$10 -> 80 | F35: =D35*$F$10 -> 18 | G35: =D35*$G$10 -> 26 | H35: =SUM(E35:G35) -> 124 | I35: =D35*$I$10 -> 76
A36: SO MU BI | D36: =SUM(B36:C36) -> 0 | E36: =D36*$E$10 -> 0 | F36: =D36*$F$10 -> 0 | G36: =D36*$G$10 -> 0 | H36: =SUM(E36:G36) -> 0 | I36: =D36*$I$10 -> 0
A37: SPECIAL OFFERING | B37: ='RECEIPTS AND PAYMENT ANANLYSIS'!C14 -> 0 | D37: =SUM(B37:C37) -> 0 | E37: =D37*$E$10 -> 0 | F37: =D37*$F$10 -> 0 | G37: =D37*$G$10 -> 0 | H37: =SUM(E37:G37) -> 0 | I37: =D37*$I$10 -> 0
A38: GRANDTOTAL | B38: =SUM(B32:B37) -> 11925.3 | C38: =SUM(C32:C37) -> 260 | D38: =SUM(D32:D37) -> 12185.3 | E38: =SUM(E32:E37) -> 4874.12 | F38: =SUM(F32:F37) -> 1096.677 | G38: =SUM(G32:G37) -> 1584.089 | H38: =SUM(H32:H37) -> 7554.886 | I38: =SUM(I32:I37) -> 4630.414
A41: THE METHODIST CHURCH GHANA
A42: NORTHERN ACCRA DIOCESE
A43: GA-SUB URBAN CIRCUIT
A44: HEBRON SOCIETY
A46: SOCIETY REVENUE ANALYSIS SHEET | C46: SOCIETY CODE | F46: MONTH | G46: MARCH
A47: DATE : | F47: WEEK
A49: INCOME SOURCE | B49: NORMAL SERVICE | C49: WEEKDAY | D49: TOTAL | E49: CONNEX | F49: DIOCESE | G49: CIRCUIT | H49: TOTAL ASSESSMENT | I49: SOCIETY
E50: 0.4 | F50: 0.09 | G50: 0.13 | I50: 0.38
B51: GHS | C51: GHS | D51: GHS | E51: GHS | F51: GHS | G51: GHS | H51: GHS | I51: GHS
A52: TITHE | B52: ='RECEIPTS AND PAYMENT ANANLYSIS'!D9 -> 10180 | C52: ='RECEIPTS AND PAYMENT ANANLYSIS'!D10 -> 218.5 | D52: =SUM(B52:C52) -> 10398.5 | E52: =D52*$E$10 -> 4159.4 | F52: =D52*$F$10 -> 935.865 | G52: =D52*$G$10 -> 1351.805 | H52: =SUM(E52:G52) -> 6447.07 | I52: =D52*$I$10 -> 3951.43
A53: OFFERING | B53: ='RECEIPTS AND PAYMENT ANANLYSIS'!D8 -> 4454.4 | D53: =SUM(B53:C53) -> 4454.4 | E53: =D53*$E$10 -> 1781.76 | F53: =D53*$F$10 -> 400.896 | G53: =D53*$G$10 -> 579.072 | H53: =SUM(E53:G53) -> 2761.728 | I53: =D53*$I$10 -> 1692.672
A54: KOFI & AMA | D54: =SUM(B54:C54) -> 0 | E54: =D54*$E$10 -> 0 | F54: =D54*$F$10 -> 0 | G54: =D54*$G$10 -> 0 | H54: =SUM(E54:G54) -> 0 | I54: =D54*$I$10 -> 0
A55: THANKSOFFERING | B55: ='RECEIPTS AND PAYMENT ANANLYSIS'!D11 -> 50 | D55: =SUM(B55:C55) -> 50 | E55: =D55*$E$10 -> 20 | F55: =D55*$F$10 -> 4.5 | G55: =D55*$G$10 -> 6.5 | H55: =SUM(E55:G55) -> 31 | I55: =D55*$I$10 -> 19
A56: SO MU BI | D56: =SUM(B56:C56) -> 0 | E56: =D56*$E$10 -> 0 | F56: =D56*$F$10 -> 0 | G56: =D56*$G$10 -> 0 | H56: =SUM(E56:G56) -> 0 | I56: =D56*$I$10 -> 0
A57: SPECIAL OFFERING | B57: ='RECEIPTS AND PAYMENT ANANLYSIS'!D14 -> 0 | D57: =SUM(B57:C57) -> 0 | E57: =D57*$E$10 -> 0 | F57: =D57*$F$10 -> 0 | G57: =D57*$G$10 -> 0 | H57: =SUM(E57:G57) -> 0 | I57: =D57*$I$10 -> 0
A58: GRANDTOTAL | B58: =SUM(B52:B57) -> 14684.4 | C58: =SUM(C52:C57) -> 218.5 | D58: =SUM(D52:D57) -> 14902.9 | E58: =SUM(E52:E57) -> 5961.16 | F58: =SUM(F52:F57) -> 1341.261 | G58: =SUM(G52:G57) -> 1937.377 | H58: =SUM(H52:H57) -> 9239.798 | I58: =SUM(I52:I57) -> 5663.102
A61: THE METHODIST CHURCH GHANA
A62: NORTHERN ACCRA DIOCESE
A63: GA-SUB URBAN CIRCUIT
A64: HEBRON SOCIETY
A66: SOCIETY REVENUE ANALYSIS SHEET | C66: SOCIETY CODE | F66: MONTH | G66: APRIL
A67: DATE : | F67: WEEK
A69: INCOME SOURCE | B69: NORMAL SERVICE | C69: WEEKDAY | D69: TOTAL | E69: CONNEX | F69: DIOCESE | G69: CIRCUIT | H69: TOTAL ASSESSMENT | I69: SOCIETY
E70: 0.4 | F70: 0.09 | G70: 0.13 | I70: 0.38
B71: GHS | C71: GHS | D71: GHS | E71: GHS | F71: GHS | G71: GHS | H71: GHS | I71: GHS
A72: TITHE | B72: ='RECEIPTS AND PAYMENT ANANLYSIS'!E9 -> 5240 | C72: ='RECEIPTS AND PAYMENT ANANLYSIS'!E10 -> 0 | D72: =SUM(B72:C72) -> 5240 | E72: =D72*$E$10 -> 2096 | F72: =D72*$F$10 -> 471.6 | G72: =D72*$G$10 -> 681.2 | H72: =SUM(E72:G72) -> 3248.8 | I72: =D72*$I$10 -> 1991.2
A73: OFFERING | B73: ='RECEIPTS AND PAYMENT ANANLYSIS'!E8 -> 2965.6 | D73: =SUM(B73:C73) -> 2965.6 | E73: =D73*$E$10 -> 1186.24 | F73: =D73*$F$10 -> 266.904 | G73: =D73*$G$10 -> 385.528 | H73: =SUM(E73:G73) -> 1838.672 | I73: =D73*$I$10 -> 1126.928
A74: KOFI & AMA | D74: =SUM(B74:C74) -> 0 | E74: =D74*$E$10 -> 0 | F74: =D74*$F$10 -> 0 | G74: =D74*$G$10 -> 0 | H74: =SUM(E74:G74) -> 0 | I74: =D74*$I$10 -> 0
A75: THANKSOFFERING | B75: ='RECEIPTS AND PAYMENT ANANLYSIS'!E11 -> 100 | D75: =SUM(B75:C75) -> 100 | E75: =D75*$E$10 -> 40 | F75: =D75*$F$10 -> 9 | G75: =D75*$G$10 -> 13 | H75: =SUM(E75:G75) -> 62 | I75: =D75*$I$10 -> 38
A76: SO MU BI | D76: =SUM(B76:C76) -> 0 | E76: =D76*$E$10 -> 0 | F76: =D76*$F$10 -> 0 | G76: =D76*$G$10 -> 0 | H76: =SUM(E76:G76) -> 0 | I76: =D76*$I$10 -> 0
A77: SPECIAL OFFERING | B77: ='RECEIPTS AND PAYMENT ANANLYSIS'!E14 -> 432 | D77: =SUM(B77:C77) -> 432 | E77: =D77*$E$10 -> 172.8 | F77: =D77*$F$10 -> 38.88 | G77: =D77*$G$10 -> 56.16 | H77: =SUM(E77:G77) -> 267.84 | I77: =D77*$I$10 -> 164.16
A78: GRANDTOTAL | B78: =SUM(B72:B77) -> 8737.6 | C78: =SUM(C72:C77) -> 0 | D78: =SUM(D72:D77) -> 8737.6 | E78: =SUM(E72:E77) -> 3495.04 | F78: =SUM(F72:F77) -> 786.384 | G78: =SUM(G72:G77) -> 1135.888 | H78: =SUM(H72:H77) -> 5417.312 | I78: =SUM(I72:I77) -> 3320.288
A82: THE METHODIST CHURCH GHANA
A83: NORTHERN ACCRA DIOCESE
A84: GA-SUB URBAN CIRCUIT
A85: HEBRON SOCIETY
A87: SOCIETY REVENUE ANALYSIS SHEET | C87: SOCIETY CODE | F87: MONTH | G87: MAY
A88: DATE : | F88: WEEK
A90: INCOME SOURCE | B90: NORMAL SERVICE | C90: WEEKDAY | D90: TOTAL | E90: CONNEX | F90: DIOCESE | G90: CIRCUIT | H90: TOTAL ASSESSMENT | I90: SOCIETY
E91: 0.4 | F91: 0.09 | G91: 0.13 | I91: 0.38
B92: GHS | C92: GHS | D92: GHS | E92: GHS | F92: GHS | G92: GHS | H92: GHS | I92: GHS
A93: TITHE | B93: ='RECEIPTS AND PAYMENT ANANLYSIS'!F9 -> 7405 | C93: ='RECEIPTS AND PAYMENT ANANLYSIS'!F10 -> 0 | D93: =SUM(B93:C93) -> 7405 | E93: =D93*$E$10 -> 2962 | F93: =D93*$F$10 -> 666.45 | G93: =D93*$G$10 -> 962.65 | H93: =SUM(E93:G93) -> 4591.1 | I93: =D93*$I$10 -> 2813.9
A94: OFFERING | B94: ='RECEIPTS AND PAYMENT ANANLYSIS'!F8 -> 2499.3 | D94: =SUM(B94:C94) -> 2499.3 | E94: =D94*$E$10 -> 999.72 | F94: =D94*$F$10 -> 224.937 | G94: =D94*$G$10 -> 324.909 | H94: =SUM(E94:G94) -> 1549.566 | I94: =D94*$I$10 -> 949.734
A95: KOFI & AMA | D95: =SUM(B95:C95) -> 0 | E95: =D95*$E$10 -> 0 | F95: =D95*$F$10 -> 0 | G95: =D95*$G$10 -> 0 | H95: =SUM(E95:G95) -> 0 | I95: =D95*$I$10 -> 0
A96: THANKSOFFERING | B96: ='RECEIPTS AND PAYMENT ANANLYSIS'!F11 -> 250 | D96: =SUM(B96:C96) -> 250 | E96: =D96*$E$10 -> 100 | F96: =D96*$F$10 -> 22.5 | G96: =D96*$G$10 -> 32.5 | H96: =SUM(E96:G96) -> 155 | I96: =D96*$I$10 -> 95
A97: SO MU BI | D97: =SUM(B97:C97) -> 0 | E97: =D97*$E$10 -> 0 | F97: =D97*$F$10 -> 0 | G97: =D97*$G$10 -> 0 | H97: =SUM(E97:G97) -> 0 | I97: =D97*$I$10 -> 0
A98: SPECIAL OFFERING | B98: ='RECEIPTS AND PAYMENT ANANLYSIS'!F14 -> 0 | D98: =SUM(B98:C98) -> 0 | E98: =D98*$E$10 -> 0 | F98: =D98*$F$10 -> 0 | G98: =D98*$G$10 -> 0 | H98: =SUM(E98:G98) -> 0 | I98: =D98*$I$10 -> 0
A99: GRANDTOTAL | B99: =SUM(B93:B98) -> 10154.3 | C99: =SUM(C93:C98) -> 0 | D99: =SUM(D93:D98) -> 10154.3 | E99: =SUM(E93:E98) -> 4061.72 | F99: =SUM(F93:F98) -> 913.887 | G99: =SUM(G93:G98) -> 1320.059 | H99: =SUM(H93:H98) -> 6295.666 | I99: =SUM(I93:I98) -> 3858.634
A102: THE METHODIST CHURCH GHANA
A103: NORTHERN ACCRA DIOCESE
A104: GA-SUB URBAN CIRCUIT
A105: HEBRON SOCIETY
A107: SOCIETY REVENUE ANALYSIS SHEET | C107: SOCIETY CODE | F107: MONTH | G107: JUNE
A108: DATE : | F108: WEEK
A110: INCOME SOURCE | B110: NORMAL SERVICE | C110: WEEKDAY | D110: TOTAL | E110: CONNEX | F110: DIOCESE | G110: CIRCUIT | H110: TOTAL ASSESSMENT | I110: SOCIETY
E111: 0.4 | F111: 0.09 | G111: 0.13 | I111: 0.38
B112: GHS | C112: GHS | D112: GHS | E112: GHS | F112: GHS | G112: GHS | H112: GHS | I112: GHS
A113: TITHE | B113: ='RECEIPTS AND PAYMENT ANANLYSIS'!G9 -> 9338 | C113: ='RECEIPTS AND PAYMENT ANANLYSIS'!G10 -> 0 | D113: =SUM(B113:C113) -> 9338 | E113: =D113*$E$10 -> 3735.2 | F113: =D113*$F$10 -> 840.42 | G113: =D113*$G$10 -> 1213.94 | H113: =SUM(E113:G113) -> 5789.56 | I113: =D113*$I$10 -> 3548.44
A114: OFFERING | B114: ='RECEIPTS AND PAYMENT ANANLYSIS'!G8 -> 3969.5 | D114: =SUM(B114:C114) -> 3969.5 | E114: =D114*$E$10 -> 1587.8 | F114: =D114*$F$10 -> 357.255 | G114: =D114*$G$10 -> 516.035 | H114: =SUM(E114:G114) -> 2461.09 | I114: =D114*$I$10 -> 1508.41
A115: KOFI & AMA | D115: =SUM(B115:C115) -> 0 | E115: =D115*$E$10 -> 0 | F115: =D115*$F$10 -> 0 | G115: =D115*$G$10 -> 0 | H115: =SUM(E115:G115) -> 0 | I115: =D115*$I$10 -> 0
A116: THANKSOFFERING | B116: ='RECEIPTS AND PAYMENT ANANLYSIS'!G11 -> 0 | D116: =SUM(B116:C116) -> 0 | E116: =D116*$E$10 -> 0 | F116: =D116*$F$10 -> 0 | G116: =D116*$G$10 -> 0 | H116: =SUM(E116:G116) -> 0 | I116: =D116*$I$10 -> 0
A117: SO MU BI | D117: =SUM(B117:C117) -> 0 | E117: =D117*$E$10 -> 0 | F117: =D117*$F$10 -> 0 | G117: =D117*$G$10 -> 0 | H117: =SUM(E117:G117) -> 0 | I117: =D117*$I$10 -> 0
A118: SPECIAL OFFERING | B118: ='RECEIPTS AND PAYMENT ANANLYSIS'!G14 -> 0 | D118: =SUM(B118:C118) -> 0 | E118: =D118*$E$10 -> 0 | F118: =D118*$F$10 -> 0 | G118: =D118*$G$10 -> 0 | H118: =SUM(E118:G118) -> 0 | I118: =D118*$I$10 -> 0
A119: GRANDTOTAL | B119: =SUM(B113:B118) -> 13307.5 | C119: =SUM(C113:C118) -> 0 | D119: =SUM(D113:D118) -> 13307.5 | E119: =SUM(E113:E118) -> 5323 | F119: =SUM(F113:F118) -> 1197.675 | G119: =SUM(G113:G118) -> 1729.975 | H119: =SUM(H113:H118) -> 8250.65 | I119: =SUM(I113:I118) -> 5056.85
A123: THE METHODIST CHURCH GHANA
A124: NORTHERN ACCRA DIOCESE
A125: GA-SUB URBAN CIRCUIT
A126: HEBRON SOCIETY
...

Sheet Stage
A1: PROJECT ACCOUNT | G1: HEBRON METHODIST CHURCH
A2: FOUNDATION COST | D2: 155306 | G2: ESTIMATE OF WORK TO BE DONE TO COMPLETE STAGE 1
A3: ADVAVCE PAYMENT TO CONTRACTOR | B3: FIRST PAYMENT | C3: 40356 | H3: QTY | I3: RATE | J3: AMOUNT
B4: SECOND PAYMENT | C4: 40000 | I4: GHS | J4: GHS
B5: THIRD PAYMENT | C5: 22500 | G5: CEMENT | H5: 150 | I5: 90 | J5: =+H5*I5 -> 13500
B6: TOTAL CHEQUES ISSUED | C6: =SUM(C3:C5) -> 102856 | G6: SAND | H6: 1 | I6: 2000 | J6: =+H6*I6 -> 2000 | K6: 1400
B7: 15 TRIPS OF SAND | C7: -7500 | D7: contactor through advance from church | G7: STONE | H7: 2 | I7: 2600 | J7: =+H7*I7 -> 5200 | K7: 2400
C8: =SUM(C6:C7) -> 95356 | G8: CONCRETE WORKS | H8: 1 | I8: 4800 | J8: =+H8*I8 -> 4800
B9: 10 Additional Trips of Sand@700 | C9: -7000 | D9: church | E9: variation | G9: RUBBER (DPM) | H9: 5 | I9: 600 | J9: =+H9*I9 -> 3000
B10: 1 TRIP BIG SAND | C10: -1000 | D10: church | E10: variation | G10: WATER | H10: 2 | I10: 200 | J10: =+H10*I10 -> 400
B11: Payloader for the road sand | C11: -500 | D11: church | E11: variation | G11: CONCRETE MIXER RENTAL | H11: 2 | I11: 500 | J11: =+H11*I11 -> 1000
B12: 100 BAGS OF CEMENT DONATION | C12: -9000 | D12: church | G12: BACKHOLE RENTAL | H12: 1 | I12: 1500 | J12: =+H12*I12 -> 1500
J13: =SUM(J5:J12) -> 31400
B15: TOTAL SPENT CONTRACTOR | D15: =+C8 -> 95356 | G15: TOTAL COST OF WORK DONE TO DATE | J15: 102590
B16: TOTAL SPENT CHURCH | D16: =-C7-C9-C10-C11-C12 -> 25000 | G16: TOTAL FUNDS ADVANCED | J16: -95356
G17: BALANCE OF LABOUR CARRIED OUT | J17: =SUM(J15:J16) -> 7234
D18: =SUM(D15:D17) -> 120356
G19: TOTAL FUNDS TO COMPLETE PHASE 1 | J19: =+J13+J17 -> 38634 | K19: 37134 | L19: =+J19-K19 -> 1500
B20: balance to complete foundation | D20: =+D2-D18 -> 34950 | G20: FUNDS AVAILABLE- 19-5-2023
H21: REPUBLIC | I21: 200
H22: GA RURAL BANK | I22: 38644
H23: CASH | I23: 1396.9 | J23: =-SUM(I21:I23) -> -40240.9
G25: SURPLUS | J25: =SUM(J19:J24) -> -1606.9

Sheet Sheet2
A1: HEBRON METHODIST CHURCH
A3: WELFARE
C4: GHS
A5: TOTAL RECEIPTS | C5: =+'weekly income statement'!O54 -> 4704.5
A7: EXPENDITURE
A8: REV. BISMARKS WIFE DONATION | C8: 200
A9: DONATION TO DISABLED | C9: 200
A10: MOTHERS DAY SCREENING | C10: 300
A11: MARINA'S FATHER DONATION | C11: 200
A12: SECTIONAL PICNIC | C12: 500
A13: LYDIA NIIBOI FATHER | C13: 200
C14: 0
C15: =SUM(C8:C14) -> 1600
A17: BALANCE OF WELFARE FUNDS | C17: =+C5-C15 -> 3104.5

Sheet EXP DETAILS
A1: HEBRON METHODIST
A2: S/N | B2: DATE | C2: DETAILS | D2: RECEIPT NO. | E2: AMOUNT
E3: GHS
A4: 1 | C4: NADMO | E4: 600
C5: PURCHASE OF SPEAKER | E5: 1250
C6: FILLING OF LAND | E6: 9000 | J6: 1600 | L6: 1550
C7: BISHOP | E7: 100 | J7: 40 | L7: -900
C8: BARCODE SITE PLAN- SURVEYOR | E8: 1200 | J8: 200 | L8: =SUM(L6:L7) -> 650
C9: COMMUNION ELEMENT | E9: 100 | J9: 100
C10: LENT BOOK | E10: 144 | J10: 50
C11: LAND WEEDING | E11: 150 | K11: 600
C12: PURCHASE OF 20 PLASTIC CHAIRS | E12: 540 | J12: =SUM(J6:J11) -> 1990
C13: 15 TRIPS FOR LAND FILLING | E13: =550*15 -> 8250
C14: HARVEST SOUVINIRS | E14: 615
