Workbook

Sheet CASH BOOK 1
A1: CASHBOOK
A2: JANUARY
A3: RECEIPTS | I3: PAYMENTS
A4: DATE | B4: DETAILS | C4: FOLIO | D4: REPUBLIC | E4: GA RURAL | F4: PETTY CASH | G4: CASH | I4: DATE | J4: DETAILS | K4: FOLIO | L4: REPUBLIC | M4: GA RURAL | N4: PETTY CASH | O4: CASH
D5: GHC | E5: GHC | F5: GHC | G5: GHC | L5: GHC | M5: GHC | N5: GHC | O5: GHC
B6: Bal B/F | G6: 1312 | I6: 45683 | J6: SNACKS FOR QM | O6: 500
A7: 45688 | B7: ALLNIGHT | G7: 1974.5
D10: =SUM(D6:D9) -> 0 | E10: =SUM(E6:E9) -> 0 | F10: =SUM(F6:F9) -> 0 | G10: =SUM(G6:G9) -> 3286.5 | L10: =SUM(L6:L9) -> 0 | M10: =SUM(M6:M9) -> 0 | N10: =SUM(N6:N9) -> 0 | O10: =SUM(O6:O9) -> 500
G11: =G10-G6 -> 1974.5 | I11: CLOSING BALANCE | L11: =D10-L10 -> 0 | M11: =E10-M10 -> 0 | N11: =F10-N10 -> 0 | O11: =G10-O10 -> 2786.5
O12: =M10+O10 -> 500
A14: FEBRUARY
A15: RECEIPTS | I15: PAYMENTS
A16: DATE | B16: DETAILS | C16: FOLIO | D16: REPUBLIC | E16: GA RURAL | F16: PETTY CASH | G16: CASH | I16: DATE | J16: DETAILS | K16: FOLIO | L16: REPUBLIC | M16: GA RURAL | N16: PETTY CASH | O16: CASH
D17: GHC | E17: GHC | F17: GHC | G17: GHC | L17: GHC | M17: GHC | N17: GHC | O17: GHC
A18: 45689 | B18: Bal B/F | D18: =L11 -> 0 | E18: =M11 -> 0 | F18: =N11 -> 0 | G18: =O11 -> 2786.5
A19: 45714 | B19: KOLEMAN RETREAT | G19: 147.4
P21: 2000
D23: =SUM(D18:D22) -> 0 | E23: =SUM(E18:E22) -> 0 | F23: =SUM(F18:F22) -> 0 | G23: =SUM(G18:G22) -> 2933.9 | L23: =SUM(L18:L22) -> 0 | M23: =SUM(M18:M22) -> 0 | N23: =SUM(N18:N22) -> 0 | O23: =SUM(O18:O22) -> 0
G24: =G23-G18 -> 147.4 | I24: CLOSING BALANCE | L24: =D23-L23 -> 0 | M24: =E23-M23 -> 0 | N24: =F23-N23 -> 0 | O24: =G23-O23 -> 2933.9
M25: =M23+O23 -> 0 | O25: =M25-'[1]RECEIPTS AND PAYMENT ANANLYSIS'!C72 -> -68600.14
A26: MARCH
A27: RECEIPTS | I27: PAYMENTS
A28: DATE | B28: DETAILS | C28: FOLIO | D28: REPUBLIC | E28: GA RURAL | F28: PETTY CASH | G28: CASH | I28: DATE | J28: DETAILS | K28: FOLIO | L28: REPUBLIC | M28: GA RURAL | N28: PETTY CASH | O28: CASH
D29: GHC | E29: GHC | F29: GHC | G29: GHC | L29: GHC | M29: GHC | N29: GHC | O29: GHC
A30: 45717 | B30: Bal B/F | D30: =L24 -> 0 | E30: =M24 -> 0 | F30: =N24 -> 0 | G30: =O24 -> 2933.9 | I30: 45717 | J30: T&T FOR EVANGELIST | O30: 100
A31: 45746 | B31: REVIVAL | G31: 1405 | I31: 45716 | J31: T&T 2 SPEAKERS REVIVAL | O31: 1000
J32: SNACK FOR QUARTERLY MEETING | O32: 500
D37: =SUM(D30:D36) -> 0 | E37: =SUM(E30:E36) -> 0 | F37: =SUM(F30:F36) -> 0 | G37: =SUM(G30:G36) -> 4338.9 | L37: =SUM(L30:L36) -> 0 | M37: =SUM(M30:M36) -> 0 | N37: =SUM(N30:N36) -> 0 | O37: =SUM(O30:O36) -> 1600
G38: =G37-G30 -> 1405 | I38: CLOSING BALANCE | L38: =D37-L37 -> 0 | M38: =E37-M37 -> 0 | N38: =F37-N37 -> 0 | O38: =G37-O37 -> 2738.9
O40: =O38-O39 -> 2738.9
M41: ='[1]CASH BOOK'!L26 -> -85383.86 | O41: ='[1]CASH BOOK'!M26 -> 54923.56
M42: =M41-M39-N38 -> -85383.86 | O42: =O41-O39 -> 54923.56
M43: 2000 | O43: =+O42+M42 -> -30460.3
M44: =M42-M43 -> -87383.86
A45: APRIL
A46: RECEIPTS | I46: PAYMENTS
A47: DATE | B47: DETAILS | C47: FOLIO | D47: REPUBLIC | E47: GA RURAL | F47: PETTY CASH | G47: CASH | I47: DATE | J47: DETAILS | K47: FOLIO | L47: REPUBLIC | M47: GA RURAL | N47: PETTY CASH | O47: CASH
D48: GHC | E48: GHC | F48: GHC | G48: GHC | L48: GHC | M48: GHC | N48: GHC | O48: GHC
A49: 45748 | B49: Bal B/F | D49: =L38 -> 0 | E49: =M38 -> 0 | F49: =N38 -> 0 | G49: =O38 -> 2738.9
D52: =SUM(D49:D51) -> 0 | E52: =SUM(E49:E51) -> 0 | F52: =SUM(F49:F51) -> 0 | G52: =SUM(G49:G51) -> 2738.9 | L52: =SUM(L49:L51) -> 0 | M52: =SUM(M49:M51) -> 0 | N52: =SUM(N49:N51) -> 0 | O52: =SUM(O49:O51) -> 0
G53: =G52-G49 -> 0 | I53: CLOSING BALANCE | L53: =D52-L52 -> 0 | M53: =E52-M52 -> 0 | N53: =F52-N52 -> 0 | O53: =G52-O52 -> 2738.9
A59: MAY
A60: RECEIPTS | I60: PAYMENTS
A61: DATE | B61: DETAILS | C61: FOLIO | D61: REPUBLIC | E61: GA RURAL | F61: PETTY CASH | G61: CASH | I61: DATE | J61: DETAILS | K61: FOLIO | L61: REPUBLIC | M61: GA RURAL | N61: PETTY CASH | O61: CASH
D62: GHC | E62: GHC | F62: GHC | G62: GHC | L62: GHC | M62: GHC | N62: GHC | O62: GHC
A63: 45778 | B63: Bal B/F | D63: =L53 -> 0 | E63: =M53 -> 0 | F63: =N53 -> 0 | G63: =O53 -> 2738.9
A64: 45807 | B64: BISHOP VISIT | G64: 784
D69: =SUM(D63:D68) -> 0 | E69: =SUM(E63:E68) -> 0 | F69: =SUM(F63:F68) -> 0 | G69: =SUM(G63:G68) -> 3522.9 | L69: =SUM(L63:L68) -> 0 | M69: =SUM(M63:M68) -> 0 | N69: =SUM(N63:N68) -> 0 | O69: =SUM(O63:O68) -> 0
G70: =G69-G63 -> 784 | I70: CLOSING BALANCE | L70: =D69-L69 -> 0 | M70: =E69-M69 -> 0 | N70: =F69-N69 -> 0 | O70: =G69-O69 -> 3522.9
A74: JUNE
A75: RECEIPTS | I75: PAYMENTS
A76: DATE | B76: DETAILS | C76: FOLIO | D76: REPUBLIC | E76: GA RURAL | F76: PETTY CASH | G76: CASH | I76: DATE | J76: DETAILS | K76: FOLIO | L76: REPUBLIC | M76: GA RURAL | N76: PETTY CASH | O76: CASH
D77: GHC | E77: GHC | F77: GHC | G77: GHC | L77: GHC | M77: GHC | N77: GHC | O77: GHC
A78: 45809 | B78: Bal B/F | D78: =L70 -> 0 | E78: =M70 -> 0 | F78: =N70 -> 0 | G78: =O70 -> 3522.9
D86: =SUM(D78:D85) -> 0 | E86: =SUM(E78:E85) -> 0 | F86: =SUM(F78:F85) -> 0 | G86: =SUM(G78:G85) -> 3522.9 | L86: =SUM(L78:L85) -> 0 | M86: =SUM(M78:M85) -> 0 | N86: =SUM(N78:N85) -> 0 | O86: =SUM(O78:O85) -> 0
G87: =G86-G78 -> 0 | I87: CLOSING BALANCE | L87: =D86-L86 -> 0 | M87: =E86-M86 -> 0 | N87: =F86-N86 -> 0 | O87: =G86-O86 -> 3522.9
A92: JULY
A93: RECEIPTS | I93: PAYMENTS
A94: DATE | B94: DETAILS | C94: FOLIO | D94: REPUBLIC | E94: GA RURAL | F94: PETTY CASH | G94: CASH | I94: DATE | J94: DETAILS | K94: FOLIO | L94: REPUBLIC | M94: GA RURAL | N94: PETTY CASH | O94: CASH
D95: GHC | E95: GHC | F95: GHC | G95: GHC | L95: GHC | M95: GHC | N95: GHC | O95: GHC
A96: 45839 | B96: Bal B/F | D96: =L87 -> 0 | E96: =M87 -> 0 | F96: =N87 -> 0 | G96: =O87 -> 3522.9 | I96: 45856 | J96: PAYMENT TO EMMANUEL DUNCAN FARMS FOR CIRCUIT OFFICE | M96: 15000
A97: 45849 | B97: ADVANCE FROM SATELLITE | E97: 18000 | I97: 45858 | J97: CASH DEPOSIT TO BANK | O97: 3522
A98: 45856 | B98: ADVANCE FROM HEBRON | E98: 6000
A99: 45858 | B99: CASH DEPOSIT | E99: 3522
D105: =SUM(D96:D104) -> 0 | E105: =SUM(E96:E104) -> 27522 | F105: =SUM(F96:F104) -> 0 | G105: =SUM(G96:G104) -> 3522.9 | L105: =SUM(L96:L104) -> 0 | M105: =SUM(M96:M104) -> 15000 | N105: =SUM(N96:N104) -> 0 | O105: =SUM(O96:O104) -> 3522
G106: =G105-G96 -> 0 | I106: CLOSING BALANCE | L106: =D105-L105 -> 0 | M106: =E105-M105 -> 12522 | N106: =F105-N105 -> 0 | O106: =G105-O105 -> 0.9
A110: AUGUST
A111: RECEIPTS | I111: PAYMENTS
A112: DATE | B112: DETAILS | C112: FOLIO | D112: REPUBLIC | E112: GA RURAL | F112: PETTY CASH | G112: CASH | I112: DATE | J112: DETAILS | K112: FOLIO | L112: REPUBLIC | M112: GA RURAL | N112: PETTY CASH | O112: CASH
D113: GHC | E113: GHC | F113: GHC | G113: GHC | L113: GHC | M113: GHC | N113: GHC | O113: GHC
A114: 45870 | B114: Bal B/F | D114: =L106 -> 0 | E114: =M106 -> 12522 | F114: =N106 -> 0 | G114: =O106 -> 0.9 | I114: 18-8-25 | J114: PAYMENT TO EMMANUEL DUNCAN FARMS FOR CIRCUIT OFFICE | M114: 15000
A115: 18-8-25 | B115: ADVANCE FROM HEBRON | E115: 6000 | J115: CITATION | O115: 600
B116: SEND OFF LEVY | C116: SATELLITE | G116: =4000+1120 -> 5120 | J116: LUNCH | O116: 2500
C117: HEBRON | G117: 2500 | J117: PASTRIES | O117: 600
C118: KORLEMAN | G118: 1000 | J118: DRINKS | O118: 620
C119: MEDIE | G119: 1000 | J119: WATER | O119: 300
C120: SAMSAM | G120: 500 | J120: CASH DONATIONS | O120: 6500
C121: MEMPEMEHUASEM | G121: 700
C122: MANCHIE | G122: 300
D126: =SUM(D114:D125) -> 0 | E126: =SUM(E114:E125) -> 18522 | F126: =SUM(F114:F125) -> 0 | G126: =SUM(G114:G125) -> 11120.9 | L126: =SUM(L114:L125) -> 0 | M126: =SUM(M114:M125) -> 15000 | N126: =SUM(N114:N125) -> 0 | O126: =SUM(O114:O125) -> 11120
G127: =G126-G114 -> 11120 | I127: CLOSING BALANCE | L127: =D126-L126 -> 0 | M127: =E126-M126 -> 3522 | N127: =F126-N126 -> 0 | O127: =G126-O126 -> 0.9
A131: SEPTEMBER
A132: RECEIPTS | I132: PAYMENTS
A133: DATE | B133: DETAILS | C133: FOLIO | D133: REPUBLIC | E133: GA RURAL | F133: PETTY CASH | G133: CASH | I133: DATE | J133: DETAILS | K133: FOLIO | L133: REPUBLIC | M133: GA RURAL | N133: PETTY CASH | O133: CASH
D134: GHC | E134: GHC | F134: GHC | G134: GHC | L134: GHC | M134: GHC | N134: GHC | O134: GHC
A135: 45901 | B135: Bal B/F | D135: =L127 -> 0 | E135: =M127 -> 3522 | F135: =N127 -> 0 | G135: =O127 -> 0.9
D144: =SUM(D135:D143) -> 0 | E144: =SUM(E135:E143) -> 3522 | F144: =SUM(F135:F143) -> 0 | G144: =SUM(G135:G143) -> 0.9 | L144: =SUM(L135:L143) -> 0 | M144: =SUM(M135:M143) -> 0 | N144: =SUM(N135:N143) -> 0 | O144: =SUM(O135:O143) -> 0
G145: =G144-G135 -> 0 | I145: CLOSING BALANCE | L145: =D144-L144 -> 0 | M145: =E144-M144 -> 3522 | N145: =F144-N144 -> 0 | O145: =G144-O144 -> 0.9
A148: OCTOBER
A149: RECEIPTS | I149: PAYMENTS
A150: DATE | B150: DETAILS | C150: FOLIO | D150: REPUBLIC | E150: GA RURAL | F150: PETTY CASH | G150: CASH | I150: DATE | J150: DETAILS | K150: FOLIO | L150: REPUBLIC | M150: GA RURAL | N150: PETTY CASH | O150: CASH
D151: GHC | E151: GHC | F151: GHC | G151: GHC | L151: GHC | M151: GHC | N151: GHC | O151: GHC
A152: 45931 | B152: Bal B/F | D152: =L145 -> 0 | E152: =M145 -> 3522 | F152: =N145 -> 0 | G152: =O145 -> 0.9 | I152: 45934 | J152: Food for guest | O152: 1450
A153: 45933 | B153: Funds from Ga-sub | G153: 3000 | J153: Drinks | O153: 795
A154: 45956 | B154: FUNDS FROM BRO PATRICK | G154: 765 | J154: Water | O154: 172
A155: 45956 | B155: FUNDS FROM SATELLITE | G155: 300 | J155: Pastries | O155: 570
A156: 46303 | B156: MMC- MOBI | C156: 0000011 | G156: 338 | J156: T&T | O156: 100
A157: 46303 | B157: KMC- MOB | C157: 0000012 | G157: 420
A158: 46310 | B158: MEMCC- MOB | C158: 0000013 | G158: 247.52 | I158: 45956 | J158: REFRESHMENT FOR CIRCUIT MEETING | O158: 765
A159: 46314 | B159: MAMC- MOBI | C159: 0000014 | G159: 373 | J159: BISCUITS FOR MEETING | O159: 300
...

Sheet Inc & Exp
A1: NORTHERN ACCRA DIOCESE
A2: GA SUB-URBAN CIRCUIT
A3: KUNTUNSE SECTION
A5: INCOME AND EXPENDITURE ACCOUNT FOR THE PERIOD
A6: JANUARY TO JUNE 2025
B8: NOTES | C8: AMOUNT
C9: GHS
A10: INCOME | B10: 1 | C10: =TB!I9+TB!I10+TB!I11+TB!I12 -> 4310.4
A12: EXPENDITURE | B12: 2 | C12: =-TB!H15-TB!H16-TB!H17 -> -1600
A14: SURPLUS/(DEFICIT) | C14: =SUM(C10:C13) -> 2710.4
A17: STATEMENT OF FINANCIAL POSITION AS AT
A18: JUNE 2025
A19: ASSETS
A21: NON CURRENT ASSETS
A22: CASH | C22: =TB!H19 -> 4022.4
C23: =SUM(C22) -> 4022.4
A25: FINANCED BY
A26: ACCUMULATED FUND | C26: =TB!I21 -> 1312
A27: SURPLUS | C27: =C14 -> 2710.4
C28: =SUM(C26:C27) -> 4022.4
A30: NOTES
A31: INCOME : | B31: 1
A32: ALL NIGHT SERVICE | B32: 1974
A33: RETREAT | B33: 147.4
A34: REVIVAL | B34: 1405
A35: OFFERING- BISHOP VISIT | B35: 784
B36: =SUM(B31:B35) -> 4311.4
A38: EXPENDITURE | B38: 2
A39: SNACK- QUARTERLY MEETING | B39: =500 -> 500
A40: T&T EVANGELIST | B40: 100
A41: HONARARIUM TO SPEAKER REVIVAL | B41: 1000
B42: =SUM(B39:B41) -> 1600
A44: ……………………………………. | B44: ……………………………………
A45: REV. BENJAMIN F. ESSEL | B45: PATRICK NYARKOH
A46: (SECTIONAL MINISTER) | B46: (SECTIONAL STEWARD)

Sheet TB
A1: NORTHERN ACCRA DIOCESE
A2: GA SUB-URBAN CIRCUIT
A3: KUNTUNSE SECTION
A4: TRIAL BALANCE AS AT JUNE 30TH 2025
A5: DETAILS | B5: OPENING BALANCE | D5: CURRENT TRANSACTIONS | F5: ADJUSTMENTS | H5: CLOSING BALANCE
B6: DR | C6: CR | D6: DR | E6: CR | F6: DR | G6: CR | H6: DR | I6: CR
B7: GHS | C7: GHS | D7: GHS | E7: GHS | F7: GHS | G7: GHS | H7: GHS | I7: GHS
A8: INCOME : | H8: =B8-C8+D8-E8+F8-G8 -> 0 | I8: =C8-B8+E8-D8+G8-F8 -> 0
A9: ALL NIGHT SERVICE | E9: 1974 | I9: =C9-B9+E9-D9+G9-F9 -> 1974
A10: RETREAT | E10: 147.4 | I10: =C10-B10+E10-D10+G10-F10 -> 147.4
A11: REVIVAL | E11: 1405 | I11: =C11-B11+E11-D11+G11-F11 -> 1405
A12: OFFERING | E12: 784 | I12: =C12-B12+E12-D12+G12-F12 -> 784
H13: =B13-C13+D13-E13+F13-G13 -> 0 | I13: =C13-B13+E13-D13+G13-F13 -> 0
A14: EXPENDITURE | H14: =B14-C14+D14-E14+F14-G14 -> 0 | I14: =C14-B14+E14-D14+G14-F14 -> 0
A15: SNACK | D15: 500 | H15: =B15-C15+D15-E15+F15-G15 -> 500
A16: T&T | D16: 100 | H16: =B16-C16+D16-E16+F16-G16 -> 100
A17: HONARARIUM TO PREACHERS | D17: 1000 | H17: =B17-C17+D17-E17+F17-G17 -> 1000
H18: =B18-C18+D18-E18+F18-G18 -> 0 | I18: =C18-B18+E18-D18+G18-F18 -> 0
A19: CASH | B19: 1312 | D19: =2210.4+500 -> 2710.4 | H19: =B19-C19+D19-E19+F19-G19 -> 4022.4
A20: BANK | H20: =B20-C20+D20-E20+F20-G20 -> 0 | I20: =C20-B20+E20-D20+G20-F20 -> 0
A21: ACCUMULATED FUND | C21: 1312 | I21: =C21-B21+E21-D21+G21-F21 -> 1312
A22: RECEIVABLE | H22: =B22-C22+D22-E22+F22-G22 -> 0 | I22: =C22-B22+E22-D22+G22-F22 -> 0
A23: PAYABLE | H23: =B23-C23+D23-E23+F23-G23 -> 0 | I23: =C23-B23+E23-D23+G23-F23 -> 0
H24: =B24-C24+D24-E24+F24-G24 -> 0 | I24: =C24-B24+E24-D24+G24-F24 -> 0
H25: =B25-C25+D25-E25+F25-G25 -> 0 | I25: =C25-B25+E25-D25+G25-F25 -> 0
A26: TOTAL | B26: =SUM(B8:B25) -> 1312 | C26: =SUM(C8:C25) -> 1312 | D26: =SUM(D8:D25) -> 4310.4 | E26: =SUM(E8:E25) -> 4310.4 | F26: =SUM(F8:F25) -> 0 | G26: =SUM(G8:G25) -> 0 | H26: =SUM(H8:H25) -> 5622.4 | I26: =SUM(I8:I25) -> 5622.4
E27: =E26-D26 -> 0

Sheet Inuaguration
A1: THE METHODIST CHURCH GHANA
A2: NORTHERN ACCRA DIOCESE
A3: KUTUNSE CIRCUIT
A5: DATE | B5: DETAILS | D5: PAYMENT | E5: BANK
A6: 46045 | B6: DEPOSIT | C6: GRB | E6: 2133 | F6: DOM
A7: 46045 | B7: DEPOSIT | C7: GRB | E7: 6493.99 | F7: DOM
A8: 46036 | B8: FK PAYMENT | C8: GCB | D8: 2000 | F8: DOM
A9: 46041 | B9: DEPOSIT | E9: 3900 | F9: DOM
A10: 46041 | B10: DEPOSIT | E10: 5000 | F10: DOM
A11: 46027 | B11: DEPOSIT-LOAN | E11: 50000 | F11: ROMEO
A12: 46378 | B12: DEPOSIT | E12: 1216.4 | F12: JOSH
A13: 46378 | B13: DEPOSIT | E13: 3276.2 | F13: JOSH
A14: 46297 | B14: DEPOSIT | E14: 1380 | F14: JOSH
A15: 46350 | B15: DEPOSIT | E15: 8293 | F15: JOSH
A16: 46386 | B16: DEPOSIT | E16: 2335 | F16: DOM
A17: 46332 | B17: DEPOSIT | E17: 14493.99 | F17: DOM
A18: 46364 | B18: DEPOSIT | E18: 1789 | F18: DOM
A19: 46366 | B19: DEPOSIT | E19: 750 | F19: DOM
A20: 46364 | B20: DEPOSIT | E20: 31922.4 | F20: DOM
A21: 46365 | B21: PMT V.REV ANAMAN | D21: 2400 | E21: 2400 | F21: DOM
A22: 46365 | B22: GODWIN AGBEBO | D22: 1374
A23: 46364 | B23: SARAH DUKER | D23: 569.32
A24: 46364 | B24: V.REV FIANKO | D24: 7000
A25: 46372 | B25: EMMANUEL DUNCAN | D25: 24000
A26: 46373 | B26: DEPOSIT | E26: 6544.35
A27: 46350 | B27: DEPOSIT | E27: 68155.18
A28: 46340 | B28: GODWIN AGBEBO | D28: 1374.67
A29: 46308 | B29: DEPOSIT | E29: 8823.84
A30: 46358 | B30: DEPOSIT | E30: 1231
A31: 46308 | B31: DEPOSIT | E31: 3264.3
A32: 46336 | B32: DEPOSIT | E32: 1800
A33: 46346 | B33: DEPOSIT | E33: 4904
A34: 46366 | B34: DEPOSIT | E34: 16000
A35: 46366 | B35: DEPOSIT | E35: 9577.45
A36: 46387 | B36: DEPOSIT | E36: 6590.03
A37: 46375 | B37: MDF | D37: 3586 | F37: PD
A38: 46376 | B38: DMDF | D38: 2406 | F38: PD
A39: 46378 | B39: STATIONARY | C39: WBL | F39: 2532 | G39: DIO DEBT
C40: S.SCH SYLL | F40: 1080
C41: LECT | F41: 250
C42: BANNER | F42: 1250
F43: =SUM(F39:F42) -> 5112
A45: 46029 | B45: FK | C45: FK | F45: 1000
B46: FK | C46: FK | F46: 1000
B47: INAUGRATION | C47: INAUGRATION | F47: 30000
B48: RECEIPT BOOKS | C48: RECEIPT BOOKS | F48: 2775
F49: =SUM(F45:F48) -> 34775
A50: 46383 | B50: COVENANT ENVELOPES | F50: 500
A51: 46027 | B51: WATCHNIGHT | D51: 7017
B52: SAT | C52: 3488
B53: HEB | C53: 2081
B54: MED | C54: 646
B55: MEM | C55: 304
B56: KOR | C56: 261
B57: MAN | C57: 134
B58: SAM | C58: 103
A59: 46038 | B59: FIANKO | D59: 800
B60: ANAMAN | D60: 600
A61: 46349 | B61: CONEXION | C61: OCT | D61: 19844.8
B62: DIOCESE | D62: 4465.08
A63: 46349 | B63: CONEXION | C63: NOV | D63: 19321.04
B64: DIOCESE | D64: 4347.23
A65: 46027 | B65: DEPOSIT | E65: 17244
A67: 46379 | B67: SALARIES | C67: 1000
B68: ANAMAN | C68: 800
B69: GODWIN | C69: 1374.67
B70: DUKER | C70: 586.64
B71: DUKER | C71: 732.68
C72: =SUM(C67:C71) -> 4493.99
A73: 46331 | B73: WESLYAN VOICE | D73: 700
A74: 46385 | B74: FIANKO | C74: 3000
B75: ANAMAN | C75: 800
B76: FURNISHING | C76: 16000
C77: =SUM(C74:C76) -> 19800
A79: 46381 | B79: FIANKO | C79: 1000
B80: ANAMAN | C80: 800
B81: GODWIN | C81: 1374.67
B82: DUKER | C82: 586.64
B83: GA-SUB | C83: 732.68
B84: YDM- REFRESH | C84: 300
B85: REFRESH FINANCE COM | C85: 295
A87: 46366 | B87: CONEXION | D87: 19844.8
B89: SAT | C89: 2645.26 | D89: 4465.08
B90: MED | C90: 238.82
B91: KOR | C91: 244.17
B92: MAN | C92: 41.04
B93: SAM | C93: 32.58
B94: MEM | C94: 75.69
B95: HE | C95: 1187.52

Sheet Petty cash voucher
A1: THE METHODIST CHURCH GHANA
A2: KUTUNSE CIRCUIT
A4: PETTY CASH VOUCHER
A6: PAYEE …..................................... | C6: NO.001
A8: DATE….......................................
A10: DETAILS OF PAYMENT | C10: GHS
A20: AMT IN WORDS
A25: …................................. ….............................. …...............................
A26: RECEIVED BY PREPARED BY APPROVED BY

Sheet PETTY CASH BOOK
A1: THE METHODIST CHURCH GHANA
A2: KUTUNSE CIRCUIT
A4: PETTY CASH ANALYSIS BOOK
A5: 46023
A6: DATE | B6: AMT RECEIVED | C6: PARTICULARS | D6: VOUCHER NO. | E6: TOTAL | F6: PRINTING | G6: T&T | H6: FUEL | I6: WAGES | J6: COMMUNICATION | K6: CLEANING | L6: UTILITIES | M6: MISC.
B7: GHS | E7: GHS | F7: GHS | G7: GHS | H7: GHS | I7: GHS | J7: GHS | K7: GHS | L7: GHS | M7: GHS
C25: TOTAL GHS
A28: SUMMARY :
E29: GHS
A30: CASH ON HAND ( OPENING BALANCE)
A32: ADD FLOAT RECEIVED
A35: LESS TOTAL DISBURSMENT
A38: AMT TO BE REPLENISHED

Sheet FIXED ASSET REGISTER
A1: THE METHODIST CHURCH GHANA
A2: KUTUNSE CIRCUIT
A4: FIXED ASSET REGISTER
A6: ID. NO | B6: DESCRIPTION | C6: BRAND | D6: MODEL NO. | E6: SERIAL NO | F6: PURCHASE VALUE | G6: PURCHASE DATE | H6: LOCATION | I6: PERSON IN CUSTODY
F7: GHS

Sheet INVENTORY LIST
A1: THE METHODIST CHURCH GHANA
A2: KUTUNSE CIRCUIT
A4: INVENTORY LIST
A6: NO. | B6: NAME OF ITEM | C6: BEGINNING INVENTORY | D6: PURCHASES DURING YEAR | E6: ITEMS SOLD OR DELETED | F6: ENDING INVENTORY | G6: UNIT AVERAGE COST | H6: TOTAL VALUE
G7: GHS | H7: GHS
F8: =C8+D8-E8 -> 0 | H8: =F8*G8 -> 0
F9: =C9+D9-E9 -> 0 | H9: =F9*G9 -> 0
F10: =C10+D10-E10 -> 0 | H10: =F10*G10 -> 0
F11: =C11+D11-E11 -> 0 | H11: =F11*G11 -> 0
F12: =C12+D12-E12 -> 0 | H12: =F12*G12 -> 0
F13: =C13+D13-E13 -> 0 | H13: =F13*G13 -> 0
F14: =C14+D14-E14 -> 0 | H14: =F14*G14 -> 0
F15: =C15+D15-E15 -> 0 | H15: =F15*G15 -> 0
F16: =C16+D16-E16 -> 0 | H16: =F16*G16 -> 0
F17: =C17+D17-E17 -> 0 | H17: =F17*G17 -> 0
F18: =C18+D18-E18 -> 0 | H18: =F18*G18 -> 0
F19: =C19+D19-E19 -> 0 | H19: =F19*G19 -> 0
... F24: =C24+D24-E24 -> 0 | H24: =F24*G24 -> 0

Sheet INCOME STATEMENT
A1: THE METHODIST CHURCH GHANA
A2: KUTUNSE CIRCUIT
A4: INCOME AND EXPENDITURE FOR THE YEAR ENDED …...................................
A6: INCOME | B6: NOTES | C6: CIRCUIT OFFICE | D6: SATELLITE | E6: MEDIE | F6: KORLEMAN | G6: MANCHIE | H6: SAMSAM | I6: MEMPEMEHUASEM | J6: HEBRON | K6: TOTAL
C7: GHS | D7: GHS | E7: GHS | F7: GHS | G7: GHS | H7: GHS | I7: GHS | J7: GHS | K7: GHS
A8: OFFERTORY | K8: =SUM(C8:J8) -> 0
A9: TITHE | K9: =SUM(C9:J9) -> 0
A10: KOFI & AMA | K10: =SUM(C10:J10) -> 0
A11: THANKS OFFERING | K11: =SUM(C11:J11) -> 0
A12: SPECIAL OFFERING | K12: =SUM(C12:J12) -> 0
A13: SO MU BI | K13: =SUM(C13:J13) -> 0
A14: HARVEST PROCEEDS | K14: =SUM(C14:J14) -> 0
A15: WELFARE DUES | K15: =SUM(C15:J15) -> 0
A16: MPRP | K16: =SUM(C16:J16) -> 0
A17: SEED FUND | K17: =SUM(C17:J17) -> 0
A18: WATCHNIGHT | K18: =SUM(C18:J18) -> 0
A19: SALE OF STATIONARY | K19: =SUM(C19:J19) -> 0
... A26: COVENANT SUNDAY | K26: =SUM(C26:J26) -> 0
A27: MISC. | B27: 1 | K27: =SUM(C27:J27) -> 0
K28: =SUM(C28:J28) -> 0
A29: TOTAL INCOME (A) | C29: =SUM(C8:C28) -> 0 | D29: =SUM(D8:D28) -> 0 | E29: =SUM(E8:E28) -> 0 | F29: =SUM(F8:F28) -> 0 | G29: =SUM(G8:G28) -> 0 | H29: =SUM(H8:H28) -> 0 | I29: =SUM(I8:I28) -> 0 | J29: =SUM(J8:J28) -> 0 | K29: =SUM(K8:K28) -> 0
A31: EXPENDITURE
A33: SALARIES & WAGES : | K33: =SUM(C33:J33) -> 0
A34: MINISTERIAL | K34: =SUM(C34:J34) -> 0
A35: OTHERS | K35: =SUM(C35:J35) -> 0
A36: ALLOWANCES : | K36: =SUM(C36:J36) -> 0
A37: MINISTERIAL | K37: =SUM(C37:J37) -> 0
A38: OTHERS | K38: =SUM(C38:J38) -> 0
A39: T&T, HONARARIUM | K39: =SUM(C39:J39) -> 0
A40: MANSE EXPENSES | K40: =SUM(C40:J40) -> 0
A41: UTILITIES - | B41: 2 | K41: =SUM(C41:J41) -> 0
A42: CLEANING AND SANITATION | K42: =SUM(C42:J42) -> 0
A43: PURCHASE OF STATIONARY | B43: 3 | K43: =SUM(C43:J43) -> 0
A44: CONFERENCE AND SYNOD EXPENSES | K44: =SUM(C44:J44) -> 0
A45: EDUCATION AND TRAINING | K45: =SUM(C45:J45) -> 0
A46: REPAIRS AND MAINTENANCE | B46: 4 | K46: =SUM(C46:J46) -> 0
A47: CONTRIBUTIONS | B47: 5 | K47: =SUM(C47:J47) -> 0
A48: ASSISTANCE TO ORGANISATIONS | K48: =SUM(C48:J48) -> 0
A49: EVANGELISM EXPENSES | K49: =SUM(C49:J49) -> 0
A50: MEDICAL EXPENSES | K50: =SUM(C50:J50) -> 0
A51: WELFARE EXPENSES | K51: =SUM(C51:J51) -> 0
A52: PROPERTY RATES | K52: =SUM(C52:J52) -> 0
A53: HARVEST EXPENSES | K53: =SUM(C53:J53) -> 0
A54: DEPRECIATION | K54: =SUM(C54:J54) -> 0
A55: PRINTING & STATIONARY | K55: =SUM(C55:J55) -> 0
A56: HIRING OF CHAIRS AND EQUIP | K56: =SUM(C56:J56) -> 0
A57: MDF | K57: =SUM(C57:J57) -> 0
A58: WATCHNIGHT | K58: =SUM(C58:J58) -> 0
A59: COVENANT | K59: =SUM(C59:J59) -> 0
A60: MISCE. | K60: =SUM(C60:J60) -> 0
A61: TOTAL EXPENDITURE | C61: =SUM(C32:C60) -> 0 | D61: =SUM(D32:D60) -> 0 | E61: =SUM(E32:E60) -> 0 | F61: =SUM(F32:F60) -> 0 | G61: =SUM(G32:G60) -> 0 | H61: =SUM(H32:H60) -> 0 | I61: =SUM(I32:I60) -> 0 | J61: =SUM(J32:J60) -> 0 | K61: =SUM(K32:K60) -> 0
A63: EXCESS INCOME OVER EXPENDITURE | C63: =C29-C61 -> 0 | D63: =D29-D61 -> 0 | E63: =E29-E61 -> 0 | F63: =F29-F61 -> 0 | G63: =G29-G61 -> 0 | H63: =H29-H61 -> 0 | I63: =I29-I61 -> 0 | J63: =J29-J61 -> 0 | K63: =K29-K61 -> 0

Sheet SOFP
A1: THE METHODIST CHURCH GHANA
A2: KUTUNSE CIRCUIT
A4: STATEMENT OF FINANCIAL POSITION AS AT …...................................
A7: ASSETS | B7: NOTES | C7: 2025 | D7: 2024
A8: PROPERTY,PLANT & EQUIPMENT
A9: LONG TERM INVESTMENT
A10: INVESTMENT PROPERTIES
C11: =SUM(C8:C10) -> 0 | D11: =SUM(D8:D10) -> 0
A13: CURRENT ASSETS
A14: SHORT TERM INVESTMENT
A15: STAFF SALARY ADVANCE
A16: RENT PREPAYMENT
A17: INVENTORY - STATIONARY
A18: DEPOSITS
A19: INTEREST RECEIVABLES
A20: SUNDRY RECEIVABLES
A21: CASH & BANK
C22: =SUM(C14:C21) -> 0 | D22: =SUM(D14:D21) -> 0
A24: TOTAL ASSETS | C24: =C11+C22 -> 0 | D24: =D11+D22 -> 0
A27: LIABILITIES
A28: FUND & SURPLUS
A29: ACCUMULATED FUND
A30: EXCESS INCOME OVER EXPENDITURE
C31: =SUM(C28:C30) -> 0 | D31: =SUM(D28:D30) -> 0
A33: CURRENT LIABILITIES
A34: UNPAID UTILITIES
A35: OUTSTANDING SALARIES
A36: BANK OVERDRAFT
A37: OUTSTANDING MDF
A38: SUNDRY PAYABLES
C39: =SUM(C34:C38) -> 0 | D39: =SUM(D34:D38) -> 0
A41: TOTAL LIABILITIES | C41: =C31+C39 -> 0 | D41: =D31+D39 -> 0

Sheet Final
A1: METHODIST CHURCH GHANA
A2: KUTUNSE CIRCUIT
A4: INCOME AND EXPENDITURE FOR INAUGURATION ON 25TH JANUARY 2026
A6: INCOME | C6: BUDGET | D6: ACTUAL
C7: GHS | D7: GHS
A8: CAROL SERVICE | D8: 3077.5
A9: COVENANT ENVELOPES | D9: 16614
A10: LOAN | D10: 50000
A11: INCOME FROM SISTER CIRCUITS | D11: 19450
A12: OFFERING & APPEAL | D12: 34772
A13: APPEAL FROM INDIVIDUALS | D13: 10400
D15: =SUM(D8:D13) -> 134313.5
D17: 50000
A18: EXPENDITURE
A19: HOSPITALITY | C19: 25870 | D19: 34715
A20: SECURITY | C20: 1375 | D20: 3375
A21: MEDIA & PUBLICITY | C21: 11140 | D21: 15656
A22: PRAYER | C22: 4440 | D22: 2500
A23: PROTOCOL & USHERING | C23: 10360 | D23: 22490
A24: MISC. | C24: 6815 | D24: 8050
C25: =SUM(C19:C24) -> 60000 | D25: =SUM(D19:D24) -> 86786
A27: Excess Income over expenditure | D27: =D15-D25 -> 47527.5
A29: REFUNDS TO BE DONE FROM INAUGURATION
C30: GHS
A31: LOAN | C31: 50000
A32: MEDIA | C32: =D21 -> 15656
A33: DECO REFUND | C33: 6000
A34: COMPACTOR | C34: 1300
A35: GENERATOR | C35: 2500
A36: EXCESS HOSPITALITY | C36: =5996+1500 -> 7496
C37: =SUM(C31:C36) -> 82952

Sheet Final (2)
A1: METHODIST CHURCH GHANA
A2: KUTUNSE CIRCUIT
A4: INCOME AND EXPENDITURE FOR INAUGURATION ON 25TH JANUARY 2026
A6: INCOME | C6: BUDGET | D6: ACTUAL
C7: GHS | D7: GHS
A8: CAROL SERVICE | D8: 3077.5
A9: COVENANT ENVELOPES | D9: 16614
A10: INCOME FROM SISTER CIRCUITS | D10: =CIRCUITS!C25 -> 21450
A11: OFFERING & APPEAL | D11: =OFFERING!C12 -> 34772.7
A12: APPEAL FROM INDIVIDUALS | D12: 10400
D14: =SUM(D8:D12) -> 86314.2
A17: LOAN WITHDRAWN FOR INAUGURATION | D17: 50000
A19: EXPENDITURE
A20: HOSPITALITY | C20: 25870 | D20: 34715
A21: SECURITY | C21: 1375 | D21: 3375
A22: MEDIA & PUBLICITY | C22: 11140 | D22: 15656
A23: PRAYER | C23: 4440 | D23: 2500
A24: PROTOCOL & USHERING | C24: 10360 | D24: 22490
A25: MISC. | C25: 6815 | D25: 8050
C26: =SUM(C20:C25) -> 60000 | D26: =SUM(D20:D25) -> 86786
A28: EXCESS EXPENDITURE ON FUNDS ADVANCED FOR PROGRAM | D28: =D17-D26 -> -36786
A30: REFUNDS TO BE DONE FROM INAUGURATION
C31: GHS
A32: LOAN | C32: 50000
A33: MEDIA | C33: =D22 -> 15656
A34: DECO REFUND | C34: 6000
A35: COMPACTOR | C35: 1300
A36: GENERATOR | C36: 2500
A37: EXCESS HOSPITALITY | C37: =5996+1500+3834 -> 11330
C38: =SUM(C32:C37) -> 86786
A41: NOTE
C42: GHS
A43: POST DATED CHEQUE | C43: 500
A44: FUNDS WITH SATELLITE | C44: 6000
A45: PLEDGE | C45: 200
C46: =SUM(C43:C45) -> 6700
A48: SUPPORT FOR WASHROOM
A49: 8 TOILET SEATS TO BE PAID | C49: 8000

Sheet Individual
C1: METHODIST CHURCH GHANA
C2: NORTHERN ACCRA DIOCES
C3: KUTUNSE CIRCUIT
A4: INDIVIDUAL SUPPORT TOWARDS INAUGURATION AND INDUCTION OF KUTUNSE CIRCUIT AND ITS SUPERINTENDENT MINISTER
A5: ITEM | B5: NAME | C5: AMOUNT | D5: SOCIETY | E5: MODE OF PAYMENT | F5: STATUS
A6: 1 | B6: Mr. Aidoo | C6: 500 | D6: Satellite | E6: Cash | F6: Deposited
A7: 2 | B7: Mr. Gyasi | C7: 1000 | D7: Satellite | E7: Cash | F7: Deposited
A8: 3 | B8: Ms Gloria Asare | C8: 500 | D8: Hebron | E8: Cash | F8: Deposited
A9: 4 | B9: Mr. Peter Asare | C9: 200 | D9: Hebron | E9: Cash | F9: Deposited
A10: 5 | B10: Mr. & Mrs. Montford | C10: 500 | D10: Medie | E10: Cheque | F10: Deposited
A11: 6 | B11: Mr. Sarfo Bempah | C11: 2000 | D11: Satellite | E11: Cheque | F11: Yet to receive
A12: 7 | B12: Lucy Oduro | C12: 500 | D12: Satellite | E12: Cash | F12: Deposited
A13: 8 | B13: Mr. John Amoanyi | C13: 1000 | D13: Satellite | E13: Cash | F13: Deposited
A14: 9 | B14: Madam Rosina Akomah | C14: 200 | D14: Satellite | E14: Cash | F14: Deposited
A15: 10 | B15: Prof Kyerematen | C15: 2000 | D15: Satellite | E15: Cheque | F15: Yet to receive
A16: 11 | B16: Mr. Benjamin Hagan | C16: 1000 | D16: Satellite | E16: Cash | F16: Received
A17: 12 | B17: Abraham Nii Kwatchey | C17: 1000
A18: 13
A19: 14
A20: 15
A21: 16
B22: TOTAL | C22: =SUM(C6:C21) -> 10400

Sheet CIRCUITS
A1: THE METHODIST CHURCH GHANA
A2: NORTHERN ACCRA DIOCESE
A3: KUTUNSE CIRCUIT
A4: CIRCUITS DONATIONS
A5: S/N | B5: CIRCUIT NAME | C5: AMOUNT | D5: MODE OF PAYMENT
C6: GHS
A7: 1 | B7: AWOSHIE | C7: 500
A8: 2 | B8: NGLESHIE AMANFRO | C8: 500
A9: 3 | B9: KWABENYA | C9: 1000
A10: 4 | B10: ADJEN KOTOKU | C10: 150
A11: 5 | B11: GA SUB URBAN | C11: 10000
A12: 6 | B12: AFIAMAN SOCIETY | C12: 200
A13: 7 | B13: KWASHIEMAN NORTH | C13: 500
A14: 8 | B14: KOJO ASHONG SECTION | C14: 400
A15: 9 | B15: ADENTA | C15: 1000
A16: 10 | B16: ASHONGMAN | C16: 500
A17: 11 | B17: NEW ACHIMOTA | C17: 500
A18: 12 | B18: ASHALE BOTWE | C18: 500
... A23: 17 | B23: MADINA | C23: 1000
B25: TOTAL | C25: =SUM(C7:C24) -> 21450

Sheet OFFERING
A1: THE METHODIST CHURCH GHANA
A2: NORTHERN ACCAR DIOCESE
A3: KUTUNSE CIRCUIT
A4: OFFERINGS RECEIVED
A5: S/N | B5: DATE | C5: AMOUNT | D5: STATUS
A6: 1 | B6: Wednesday, 21 Jan 2026 | C6: 945
A7: 2 | B7: Thursday, 22 Jan 2026 | C7: 1188
A8: 3 | B8: Friday, 23 Jan 2026 | C8: 8015.7
A9: 4 | B9: Sunday, 25 Jan 2026 | C9: 16075
A10: 5 | B10: Appeal | C10: 8349
B11: Pledges | C11: 200
B12: TOTAL | C12: =SUM(C6:C11) -> 34772.7

Sheet EXPENSES (2)
A1: METHODIST CHURCH GHANA
A2: NORTHERN ACCRA DIOCES
A3: KUTUNSE CIRCUIT
A4: EXPENSES
A7: HOSPITALITY
A8: S/N | B8: DESCRIPTION | C8: AMOUNT
A9: 1 | B9: Hotel Reservation | C9: 450
A10: 2 | B10: Food | C10: 9000
A11: 3 | B11: Pastries | C11: 7820
A12: 4 | B12: Drink | C12: 6921
A13: 5 | B13: Water | C13: 2024
A14: 6 | B14: Buffet | C14: 7000
A15: 7 | B15: Breakfast | C15: 1500
C16: =SUM(C9:C15) -> 34715
A19: MEDIA & PUBLICITY
A20: 1 | B20: Printing of Brochure | C20: 11991
A21: 2 | B21: TV bracket (2) | C21: 640
A22: 3 | B22: TV splitter (2) | C22: 315
A23: 4 | B23: Video and Photography- Camera rent and Transport | C23: 2710
C24: =SUM(C20:C23) -> 15656
A26: MISCELLANEOUS
A27: 1 | B27: ECG (Manse) | C27: 200
A28: 2 | B28: Honouriarium ( Ministers) | C28: =4800-1800 -> 3000
A29: 3 | B29: Organist- Guest Organist Satellite | C29: 400
A30: 4 | B30: Cleaner- For the day | C30: 300
A31: 5 | B31: Sacks | C31: 50
A32: 6 | B32: Generator | C32: 2500
A33: 7 | B33: Fuel For Generator | C33: 300
A34: 8 | B34: Compactor and TnT | C34: 1300
C35: =SUM(C27:C34) -> 8050
A37: PRAYER
A38: 1 | B38: Communion | C38: 700
A39: 2 | B39: Revival - Guest Minister | C39: 1800
C40: =SUM(C38:C39) -> 2500
A42: PROTOCOL
A43: 1 | B43: Medical | C43: 400
A44: 2 | B44: Decor | C44: 6000
A45: 3 | B45: Decor | C45: 11000
A46: 4 | B46: Tags and Labels | C46: 1430
A47: 5 | B47: Clothes | C47: 1110
A48: 6 | B48: Curtains | C48: 700
A49: 7 | B49: Detergents | C49: 500
A50: 8 | B50: First Aid | C50: 1000
A51: 9 | B51: Table cloth | C51: 350
C52: =SUM(C43:C51) -> 22490
A54: SECURITY
A55: 4 | B55: Security | C55: 3375
A57: Grand total | C57: =C55+C52+C40+C35+C24+C16 -> 86786
